clkDivider/clkDivider_by5_counter.v
//////////////////////////////////////////////////////////////////////
// Module Name: clkDivider_by5_counter.v
// Description: Clock Divider by 5 Counter
// Designer: Barney Peng
// Date: 03/24/2024
//////////////////////////////////////////////////////////////////////

//module counter #(parameter WIDTH (3) /* 3 bit counter*/)(
module clkDivider_by5_counter (
	input clk,
	input resetn,

	output o_count_end, 		      // counter reaches max value
	output wire [WIDTH-1 : 0] o_count,   // Output of the counter(remember that 8-bit: [7:0](7 to 0))


	output  o_tff_out_1,
	output  o_tff_out_2,
	output  o_div5_clk

);

	parameter WIDTH = 3; /* 2  bit counter*/

	reg tff_1_en_p;
	reg tff_2_en_p;

	reg [WIDTH-1 : 0] o_count_p;

	
	reg o_tff_1_out_p;
	reg o_tff_2_out_p;
	


	wire clk_gate;		// gated clock
	
	
	assign clk_gate = clk;
	// Counter
	always @(negedge resetn or posedge clk_gate)       // At every positive edge of the clock or negative edge of restn
		begin
			if  (~resetn)
		 		o_count_p <= 2'h0;		 // If reset is asserted, set the counter to 0
			else if(o_count_p >= 3'd4)
				o_count_p <=  2'h0;      // Otherwise, deassign the output

			else 
				o_count_p <=  o_count_p + 1;         // Increment the counter by 1
		end//Counter

	//TFF_01_Enable
		always @(negedge resetn or posedge clk_gate)       // At every positive edge of the clock or negative edge of restn
		begin
			if  (~resetn)
			tff_1_en_p <= 1'd0;		 // 
			else if(o_count_p == 2'h0)
			tff_1_en_p <=  1;         // (when counter value==0, i_tff_1_en_p = 1)
			else
			tff_1_en_p <=  1'd0;      // Otherwise, deassign the output
		end	//TFF_01_Enable


	//TFF_02_Enable
		always @(negedge resetn or posedge clk_gate)       // At every positive edge of the clock or negative edge of restn
		begin
			if  (~resetn)
			tff_2_en_p <= 1'd0;		 // 
			else if(o_count_p == 2'd3)
			tff_2_en_p <=  1;         // (when counter value==2, i_tff_2_en_p = 1)
			else
			tff_2_en_p <=  1'd0;      // Otherwise, deassign the output
		end	//TFF_02_Enable

	//TFF_01_out
		always @ (negedge resetn or posedge clk_gate)
		begin
			if  (~resetn)
			o_tff_1_out_p <= 1'd0;		 // 
			else if(tff_1_en_p)
			o_tff_1_out_p <= ~o_tff_1_out_p;         // (when counter value==0, i_tff_1_en_p = 1)
			else
			o_tff_1_out_p = o_tff_1_out_p;
		end	//TFF_01_out

	//TFF_02_out
		always @ (negedge resetn or negedge clk_gate)
		begin
			if  (~resetn)
			o_tff_2_out_p <= 1'd0;		 // 
			else if(tff_2_en_p)
			o_tff_2_out_p <= ~o_tff_2_out_p;         // (when counter value==0, i_tff_1_en_p = 1)
			else
			o_tff_2_out_p = o_tff_2_out_p;
		end	//TFF_02_out


	assign o_count_end = (o_count == 3'd4);
	assign o_count = o_count_p;
	assign o_tff_out_1 = o_tff_1_out_p;
	assign o_tff_out_2 = o_tff_2_out_p;
	assign o_div5_clk = o_tff_1_out_p ^ o_tff_2_out_p; // ^ is XOR operator


endmodule // counter

clkDivider/clkDivider_by5_counter_tb.v
`timescale 1ns / 1ps //set the timescale for the module
//////////////////////////////////////////////////////////////////////
// Module Name: clkDivider_by5_counter_tb.v
// Description: Clock Divider by 5 Counter
// Designer: Barney Peng
// Date: 03/24/2024
//////////////////////////////////////////////////////////////////////

module clkDivider_by5_counter_tb;


reg resetn;

parameter WIDTH = 3; /* 2  bit counter*/
wire  o_count_end;
wire [WIDTH-1:0] o_count;

initial begin
    resetn = 0;
    #20   resetn = 1;
    #4000 resetn = 1;
    $finish;
end

// free running clock clk
reg clk = 0;
always #1 clk = !clk;

initial begin
    $monitor("At time %t, o_count = %h (%0d)", $time, o_count, o_count);
end



initial begin
    $monitor("At time %t, o_div5_clk = %h (%0d)", $time, o_div5_clk, o_div5_clk);
end

initial begin
    $dumpfile("clkDivider_by5_counter.vcd");
    $dumpvars(0,clkDivider_by5_counter_tb);
end

clkDivider_by5_counter u_clkDivider_by5_counter (
    .clk(clk),
    .resetn(resetn),

    .o_count_end(o_count_end),
    .o_count(o_count),

    .o_div5_clk(o_div5_clk)
);

endmodule

clkDivider/clkDivider_by5_counter.vcd
$date
	Sun Mar 24 13:44:27 2024
$end
$version
	Icarus Verilog
$end
$timescale
	1ps
$end
$scope module clkDivider_by5_counter_tb $end
$var wire 1 ! o_div5_clk $end
$var wire 1 " o_count_end $end
$var wire 3 # o_count [2:0] $end
$var parameter 32 $ WIDTH $end
$var reg 1 % clk $end
$var reg 1 & resetn $end
$scope module u_clkDivider_by5_counter $end
$var wire 1 % clk $end
$var wire 1 ' clk_gate $end
$var wire 1 ! o_div5_clk $end
$var wire 1 ( o_tff_out_1 $end
$var wire 1 ) o_tff_out_2 $end
$var wire 1 & resetn $end
$var wire 1 " o_count_end $end
$var wire 3 * o_count [2:0] $end
$var parameter 32 + WIDTH $end
$var reg 3 , o_count_p [2:0] $end
$var reg 1 - o_tff_1_out_p $end
$var reg 1 . o_tff_2_out_p $end
$var reg 1 / tff_1_en_p $end
$var reg 1 0 tff_2_en_p $end
$upscope $end
$upscope $end
$enddefinitions $end
$comment Show the parameter values. $end
$dumpall
b11 +
b11 $
$end
#0
$dumpvars
00
0/
0.
0-
b0 ,
b0 *
0)
0(
0'
0&
0%
b0 #
0"
0!
$end
#1000
1'
1%
#2000
0'
0%
#3000
1'
1%
#4000
0'
0%
#5000
1'
1%
#6000
0'
0%
#7000
1'
1%
#8000
0'
0%
#9000
1'
1%
#10000
0'
0%
#11000
1'
1%
#12000
0'
0%
#13000
1'
1%
#14000
0'
0%
#15000
1'
1%
#16000
0'
0%
#17000
1'
1%
#18000
0'
0%
#19000
1'
1%
#20000
0'
0%
1&
#21000
1/
b1 #
b1 *
b1 ,
1'
1%
#22000
0'
0%
#23000
1!
b10 #
b10 *
b10 ,
0/
1(
1-
1'
1%
#24000
0'
0%
#25000
b11 #
b11 *
b11 ,
1'
1%
#26000
0'
0%
#27000
1"
b100 #
b100 *
b100 ,
10
1'
1%
#28000
0!
1)
1.
0'
0%
#29000
00
0"
b0 #
b0 *
b0 ,
1'
1%
#30000
0'
0%
#31000
b1 #
b1 *
b1 ,
1/
1'
1%
#32000
0'
0%
#33000
1!
0(
0-
0/
b10 #
b10 *
b10 ,
1'
1%
#34000
0'
0%
#35000
b11 #
b11 *
b11 ,
1'
1%
#36000
0'
0%
#37000
10
1"
b100 #
b100 *
b100 ,
1'
1%
#38000
0!
0)
0.
0'
0%
#39000
0"
b0 #
b0 *
b0 ,
00
1'
1%
#40000
0'
0%
#41000
1/
b1 #
b1 *
b1 ,
1'
1%
#42000
0'
0%
#43000
1!
b10 #
b10 *
b10 ,
0/
1(
1-
1'
1%
#44000
0'
0%
#45000
b11 #
b11 *
b11 ,
1'
1%
#46000
0'
0%
#47000
1"
b100 #
b100 *
b100 ,
10
1'
1%
#48000
0!
1)
1.
0'
0%
#49000
00
0"
b0 #
b0 *
b0 ,
1'
1%
#50000
0'
0%
#51000
b1 #
b1 *
b1 ,
1/
1'
1%
#52000
0'
0%
#53000
1!
0(
0-
0/
b10 #
b10 *
b10 ,
1'
1%
#54000
0'
0%
#55000
b11 #
b11 *
b11 ,
1'
1%
#56000
0'
0%
#57000
10
1"
b100 #
b100 *
b100 ,
1'
1%
#58000
0!
0)
0.
0'
0%
#59000
0"
b0 #
b0 *
b0 ,
00
1'
1%
#60000
0'
0%
#61000
1/
b1 #
b1 *
b1 ,
1'
1%
#62000
0'
0%
#63000
1!
b10 #
b10 *
b10 ,
0/
1(
1-
1'
1%
#64000
0'
0%
#65000
b11 #
b11 *
b11 ,
1'
1%
#66000
0'
0%
#67000
1"
b100 #
b100 *
b100 ,
10
1'
1%
#68000
0!
1)
1.
0'
0%
#69000
00
0"
b0 #
b0 *
b0 ,
1'
1%
#70000
0'
0%
#71000
b1 #
b1 *
b1 ,
1/
1'
1%
#72000
0'
0%
#73000
1!
0(
0-
0/
b10 #
b10 *
b10 ,
1'
1%
#74000
0'
0%
#75000
b11 #
b11 *
b11 ,
1'
1%
#76000
0'
0%
#77000
10
1"
b100 #
b100 *
b100 ,
1'
1%
#78000
0!
0)
0.
0'
0%
#79000
0"
b0 #
b0 *
b0 ,
00
1'
1%
#80000
0'
0%
#81000
1/
b1 #
b1 *
b1 ,
1'
1%
#82000
0'
0%
#83000
1!
b10 #
b10 *
b10 ,
0/
1(
1-
1'
1%
#84000
0'
0%
#85000
b11 #
b11 *
b11 ,
1'
1%
#86000
0'
0%
#87000
1"
b100 #
b100 *
b100 ,
10
1'
1%
#88000
0!
1)
1.
0'
0%
#89000
00
0"
b0 #
b0 *
b0 ,
1'
1%
#90000
0'
0%
#91000
b1 #
b1 *
b1 ,
1/
1'
1%
#92000
0'
0%
#93000
1!
0(
0-
0/
b10 #
b10 *
b10 ,
1'
1%
#94000
0'
0%
#95000
b11 #
b11 *
b11 ,
1'
1%
#96000
0'
0%
#97000
10
1"
b100 #
b100 *
b100 ,
1'
1%
#98000
0!
0)
0.
0'
0%
#99000
0"
b0 #
b0 *
b0 ,
00
1'
1%
#100000
0'
0%
#101000
1/
b1 #
b1 *
b1 ,
1'
1%
#102000
0'
0%
#103000
1!
b10 #
b10 *
b10 ,
0/
1(
1-
1'
1%
#104000
0'
0%
#105000
b11 #
b11 *
b11 ,
1'
1%
#106000
0'
0%
#107000
1"
b100 #
b100 *
b100 ,
10
1'
1%
#108000
0!
1)
1.
0'
0%
#109000
00
0"
b0 #
b0 *
b0 ,
1'
1%
#110000
0'
0%
#111000
b1 #
b1 *
b1 ,
1/
1'
1%
#112000
0'
0%
#113000
1!
0(
0-
0/
b10 #
b10 *
b10 ,
1'
1%
#114000
0'
0%
#115000
b11 #
b11 *
b11 ,
1'
1%
#116000
0'
0%
#117000
10
1"
b100 #
b100 *
b100 ,
1'
1%
#118000
0!
0)
0.
0'
0%
#119000
0"
b0 #
b0 *
b0 ,
00
1'
1%
#120000
0'
0%
#121000
1/
b1 #
b1 *
b1 ,
1'
1%
#122000
0'
0%
#123000
1!
b10 #
b10 *
b10 ,
0/
1(
1-
1'
1%
#124000
0'
0%
#125000
b11 #
b11 *
b11 ,
1'
1%
#126000
0'
0%
#127000
1"
b100 #
b100 *
b100 ,
10
1'
1%
#128000
0!
1)
1.
0'
0%
#129000
00
0"
b0 #
b0 *
b0 ,
1'
1%
#130000
0'
0%
#131000
b1 #
b1 *
b1 ,
1/
1'
1%
#132000
0'
0%
#133000
1!
0(
0-
0/
b10 #
b10 *
b10 ,
1'
1%
#134000
0'
0%
#135000
b11 #
b11 *
b11 ,
1'
1%
#136000
0'
0%
#137000
10
1"
b100 #
b100 *
b100 ,
1'
1%
#138000
0!
0)
0.
0'
0%
#139000
0"
b0 #
b0 *
b0 ,
00
1'
1%
#140000
0'
0%
#141000
1/
b1 #
b1 *
b1 ,
1'
1%
#142000
0'
0%
#143000
1!
b10 #
b10 *
b10 ,
0/
1(
1-
1'
1%
#144000
0'
0%
#145000
b11 #
b11 *
b11 ,
1'
1%
#146000
0'
0%
#147000
1"
b100 #
b100 *
b100 ,
10
1'
1%
#148000
0!
1)
1.
0'
0%
#149000
00
0"
b0 #
b0 *
b0 ,
1'
1%
#150000
0'
0%
#151000
b1 #
b1 *
b1 ,
1/
1'
1%
#152000
0'
0%
#153000
1!
0(
0-
0/
b10 #
b10 *
b10 ,
1'
1%
#154000
0'
0%
#155000
b11 #
b11 *
b11 ,
1'
1%
#156000
0'
0%
#157000
10
1"
b100 #
b100 *
b100 ,
1'
1%
#158000
0!
0)
0.
0'
0%
#159000
0"
b0 #
b0 *
b0 ,
00
1'
1%
#160000
0'
0%
#161000
1/
b1 #
b1 *
b1 ,
1'
1%
#162000
0'
0%
#163000
1!
b10 #
b10 *
b10 ,
0/
1(
1-
1'
1%
#164000
0'
0%
#165000
b11 #
b11 *
b11 ,
1'
1%
#166000
0'
0%
#167000
1"
b100 #
b100 *
b100 ,
10
1'
1%
#168000
0!
1)
1.
0'
0%
#169000
00
0"
b0 #
b0 *
b0 ,
1'
1%
#170000
0'
0%
#171000
b1 #
b1 *
b1 ,
1/
1'
1%
#172000
0'
0%
#173000
1!
0(
0-
0/
b10 #
b10 *
b10 ,
1'
1%
#174000
0'
0%
#175000
b11 #
b11 *
b11 ,
1'
1%
#176000
0'
0%
#177000
10
1"
b100 #
b100 *
b100 ,
1'
1%
#178000
0!
0)
0.
0'
0%
#179000
0"
b0 #
b0 *
b0 ,
00
1'
1%
#180000
0'
0%
#181000
1/
b1 #
b1 *
b1 ,
1'
1%
#182000
0'
0%
#183000
1!
b10 #
b10 *
b10 ,
0/
1(
1-
1'
1%
#184000
0'
0%
#185000
b11 #
b11 *
b11 ,
1'
1%
#186000
0'
0%
#187000
1"
b100 #
b100 *
b100 ,
10
1'
1%
#188000
0!
1)
1.
0'
0%
#189000
00
0"
b0 #
b0 *
b0 ,
1'
1%
#190000
0'
0%
#191000
b1 #
b1 *
b1 ,
1/
1'
1%
#192000
0'
0%
#193000
1!
0(
0-
0/
b10 #
b10 *
b10 ,
1'
1%
#194000
0'
0%
#195000
b11 #
b11 *
b11 ,
1'
1%
#196000
0'
0%
#197000
10
1"
b100 #
b100 *
b100 ,
1'
1%
#198000
0!
0)
0.
0'
0%
#199000
0"
b0 #
b0 *
b0 ,
00
1'
1%
#200000
0'
0%
#201000
1/
b1 #
b1 *
b1 ,
1'
1%
#202000
0'
0%
#203000
1!
b10 #
b10 *
b10 ,
0/
1(
1-
1'
1%
#204000
0'
0%
#205000
b11 #
b11 *
b11 ,
1'
1%
#206000
0'
0%
#207000
1"
b100 #
b100 *
b100 ,
10
1'
1%
#208000
0!
1)
1.
0'
0%
#209000
00
0"
b0 #
b0 *
b0 ,
1'
1%
#210000
0'
0%
#211000
b1 #
b1 *
b1 ,
1/
1'
1%
#212000
0'
0%
#213000
1!
0(
0-
0/
b10 #
b10 *
b10 ,
1'
1%
#214000
0'
0%
#215000
b11 #
b11 *
b11 ,
1'
1%
#216000
0'
0%
#217000
10
1"
b100 #
b100 *
b100 ,
1'
1%
#218000
0!
0)
0.
0'
0%
#219000
0"
b0 #
b0 *
b0 ,
00
1'
1%
#220000
0'
0%
#221000
1/
b1 #
b1 *
b1 ,
1'
1%
#222000
0'
0%
#223000
1!
b10 #
b10 *
b10 ,
0/
1(
1-
1'
1%
#224000
0'
0%
#225000
b11 #
b11 *
b11 ,
1'
1%
#226000
0'
0%
#227000
1"
b100 #
b100 *
b100 ,
10
1'
1%
#228000
0!
1)
1.
0'
0%
#229000
00
0"
b0 #
b0 *
b0 ,
1'
1%
#230000
0'
0%
#231000
b1 #
b1 *
b1 ,
1/
1'
1%
#232000
0'
0%
#233000
1!
0(
0-
0/
b10 #
b10 *
b10 ,
1'
1%
#234000
0'
0%
#235000
b11 #
b11 *
b11 ,
1'
1%
#236000
0'
0%
#237000
10
1"
b100 #
b100 *
b100 ,
1'
1%
#238000
0!
0)
0.
0'
0%
#239000
0"
b0 #
b0 *
b0 ,
00
1'
1%
#240000
0'
0%
#241000
1/
b1 #
b1 *
b1 ,
1'
1%
#242000
0'
0%
#243000
1!
b10 #
b10 *
b10 ,
0/
1(
1-
1'
1%
#244000
0'
0%
#245000
b11 #
b11 *
b11 ,
1'
1%
#246000
0'
0%
#247000
1"
b100 #
b100 *
b100 ,
10
1'
1%
#248000
0!
1)
1.
0'
0%
#249000
00
0"
b0 #
b0 *
b0 ,
1'
1%
#250000
0'
0%
#251000
b1 #
b1 *
b1 ,
1/
1'
1%
#252000
0'
0%
#253000
1!
0(
0-
0/
b10 #
b10 *
b10 ,
1'
1%
#254000
0'
0%
#255000
b11 #
b11 *
b11 ,
1'
1%
#256000
0'
0%
#257000
10
1"
b100 #
b100 *
b100 ,
1'
1%
#258000
0!
0)
0.
0'
0%
#259000
0"
b0 #
b0 *
b0 ,
00
1'
1%
#260000
0'
0%
#261000
1/
b1 #
b1 *
b1 ,
1'
1%
#262000
0'
0%
#263000
1!
b10 #
b10 *
b10 ,
0/
1(
1-
1'
1%
#264000
0'
0%
#265000
b11 #
b11 *
b11 ,
1'
1%
#266000
0'
0%
#267000
1"
b100 #
b100 *
b100 ,
10
1'
1%
#268000
0!
1)
1.
0'
0%
#269000
00
0"
b0 #
b0 *
b0 ,
1'
1%
#270000
0'
0%
#271000
b1 #
b1 *
b1 ,
1/
1'
1%
#272000
0'
0%
#273000
1!
0(
0-
0/
b10 #
b10 *
b10 ,
1'
1%
#274000
0'
0%
#275000
b11 #
b11 *
b11 ,
1'
1%
#276000
0'
0%
#277000
10
1"
b100 #
b100 *
b100 ,
1'
1%
#278000
0!
0)
0.
0'
0%
#279000
0"
b0 #
b0 *
b0 ,
00
1'
1%
#280000
0'
0%
#281000
1/
b1 #
b1 *
b1 ,
1'
1%
#282000
0'
0%
#283000
1!
b10 #
b10 *
b10 ,
0/
1(
1-
1'
1%
#284000
0'
0%
#285000
b11 #
b11 *
b11 ,
1'
1%
#286000
0'
0%
#287000
1"
b100 #
b100 *
b100 ,
10
1'
1%
#288000
0!
1)
1.
0'
0%
#289000
00
0"
b0 #
b0 *
b0 ,
1'
1%
#290000
0'
0%
#291000
b1 #
b1 *
b1 ,
1/
1'
1%
#292000
0'
0%
#293000
1!
0(
0-
0/
b10 #
b10 *
b10 ,
1'
1%
#294000
0'
0%
#295000
b11 #
b11 *
b11 ,
1'
1%
#296000
0'
0%
#297000
10
1"
b100 #
b100 *
b100 ,
1'
1%
#298000
0!
0)
0.
0'
0%
#299000
0"
b0 #
b0 *
b0 ,
00
1'
1%
#300000
0'
0%
#301000
1/
b1 #
b1 *
b1 ,
1'
1%
#302000
0'
0%
#303000
1!
b10 #
b10 *
b10 ,
0/
1(
1-
1'
1%
#304000
0'
0%
#305000
b11 #
b11 *
b11 ,
1'
1%
#306000
0'
0%
#307000
1"
b100 #
b100 *
b100 ,
10
1'
1%
#308000
0!
1)
1.
0'
0%
#309000
00
0"
b0 #
b0 *
b0 ,
1'
1%
#310000
0'
0%
#311000
b1 #
b1 *
b1 ,
1/
1'
1%
#312000
0'
0%
#313000
1!
0(
0-
0/
b10 #
b10 *
b10 ,
1'
1%
#314000
0'
0%
#315000
b11 #
b11 *
b11 ,
1'
1%
#316000
0'
0%
#317000
10
1"
b100 #
b100 *
b100 ,
1'
1%
#318000
0!
0)
0.
0'
0%
#319000
0"
b0 #
b0 *
b0 ,
00
1'
1%
#320000
0'
0%
#321000
1/
b1 #
b1 *
b1 ,
1'
1%
#322000
0'
0%
#323000
1!
b10 #
b10 *
b10 ,
0/
1(
1-
1'
1%
#324000
0'
0%
#325000
b11 #
b11 *
b11 ,
1'
1%
#326000
0'
0%
#327000
1"
b100 #
b100 *
b100 ,
10
1'
1%
#328000
0!
1)
1.
0'
0%
#329000
00
0"
b0 #
b0 *
b0 ,
1'
1%
#330000
0'
0%
#331000
b1 #
b1 *
b1 ,
1/
1'
1%
#332000
0'
0%
#333000
1!
0(
0-
0/
b10 #
b10 *
b10 ,
1'
1%
#334000
0'
0%
#335000
b11 #
b11 *
b11 ,
1'
1%
#336000
0'
0%
#337000
10
1"
b100 #
b100 *
b100 ,
1'
1%
#338000
0!
0)
0.
0'
0%
#339000
0"
b0 #
b0 *
b0 ,
00
1'
1%
#340000
0'
0%
#341000
1/
b1 #
b1 *
b1 ,
1'
1%
#342000
0'
0%
#343000
1!
b10 #
b10 *
b10 ,
0/
1(
1-
1'
1%
#344000
0'
0%
#345000
b11 #
b11 *
b11 ,
1'
1%
#346000
0'
0%
#347000
1"
b100 #
b100 *
b100 ,
10
1'
1%
#348000
0!
1)
1.
0'
0%
#349000
00
0"
b0 #
b0 *
b0 ,
1'
1%
#350000
0'
0%
#351000
b1 #
b1 *
b1 ,
1/
1'
1%
#352000
0'
0%
#353000
1!
0(
0-
0/
b10 #
b10 *
b10 ,
1'
1%
#354000
0'
0%
#355000
b11 #
b11 *
b11 ,
1'
1%
#356000
0'
0%
#357000
10
1"
b100 #
b100 *
b100 ,
1'
1%
#358000
0!
0)
0.
0'
0%
#359000
0"
b0 #
b0 *
b0 ,
00
1'
1%
#360000
0'
0%
#361000
1/
b1 #
b1 *
b1 ,
1'
1%
#362000
0'
0%
#363000
1!
b10 #
b10 *
b10 ,
0/
1(
1-
1'
1%
#364000
0'
0%
#365000
b11 #
b11 *
b11 ,
1'
1%
#366000
0'
0%
#367000
1"
b100 #
b100 *
b100 ,
10
1'
1%
#368000
0!
1)
1.
0'
0%
#369000
00
0"
b0 #
b0 *
b0 ,
1'
1%
#370000
0'
0%
#371000
b1 #
b1 *
b1 ,
1/
1'
1%
#372000
0'
0%
#373000
1!
0(
0-
0/
b10 #
b10 *
b10 ,
1'
1%
#374000
0'
0%
#375000
b11 #
b11 *
b11 ,
1'
1%
#376000
0'
0%
#377000
10
1"
b100 #
b100 *
b100 ,
1'
1%
#378000
0!
0)
0.
0'
0%
#379000
0"
b0 #
b0 *
b0 ,
00
1'
1%
#380000
0'
0%
#381000
1/
b1 #
b1 *
b1 ,
1'
1%
#382000
0'
0%
#383000
1!
b10 #
b10 *
b10 ,
0/
1(
1-
1'
1%
#384000
0'
0%
#385000
b11 #
b11 *
b11 ,
1'
1%
#386000
0'
0%
#387000
1"
b100 #
b100 *
b100 ,
10
1'
1%
#388000
0!
1)
1.
0'
0%
#389000
00
0"
b0 #
b0 *
b0 ,
1'
1%
#390000
0'
0%
#391000
b1 #
b1 *
b1 ,
1/
1'
1%
#392000
0'
0%
#393000
1!
0(
0-
0/
b10 #
b10 *
b10 ,
1'
1%
#394000
0'
0%
#395000
b11 #
b11 *
b11 ,
1'
1%
#396000
0'
0%
#397000
10
1"
b100 #
b100 *
b100 ,
1'
1%
#398000
0!
0)
0.
0'
0%
#399000
0"
b0 #
b0 *
b0 ,
00
1'
1%
#400000
0'
0%
#401000
1/
b1 #
b1 *
b1 ,
1'
1%
#402000
0'
0%
#403000
1!
b10 #
b10 *
b10 ,
0/
1(
1-
1'
1%
#404000
0'
0%
#405000
b11 #
b11 *
b11 ,
1'
1%
#406000
0'
0%
#407000
1"
b100 #
b100 *
b100 ,
10
1'
1%
#408000
0!
1)
1.
0'
0%
#409000
00
0"
b0 #
b0 *
b0 ,
1'
1%
#410000
0'
0%
#411000
b1 #
b1 *
b1 ,
1/
1'
1%
#412000
0'
0%
#413000
1!
0(
0-
0/
b10 #
b10 *
b10 ,
1'
1%
#414000
0'
0%
#415000
b11 #
b11 *
b11 ,
1'
1%
#416000
0'
0%
#417000
10
1"
b100 #
b100 *
b100 ,
1'
1%
#418000
0!
0)
0.
0'
0%
#419000
0"
b0 #
b0 *
b0 ,
00
1'
1%
#420000
0'
0%
#421000
1/
b1 #
b1 *
b1 ,
1'
1%
#422000
0'
0%
#423000
1!
b10 #
b10 *
b10 ,
0/
1(
1-
1'
1%
#424000
0'
0%
#425000
b11 #
b11 *
b11 ,
1'
1%
#426000
0'
0%
#427000
1"
b100 #
b100 *
b100 ,
10
1'
1%
#428000
0!
1)
1.
0'
0%
#429000
00
0"
b0 #
b0 *
b0 ,
1'
1%
#430000
0'
0%
#431000
b1 #
b1 *
b1 ,
1/
1'
1%
#432000
0'
0%
#433000
1!
0(
0-
0/
b10 #
b10 *
b10 ,
1'
1%
#434000
0'
0%
#435000
b11 #
b11 *
b11 ,
1'
1%
#436000
0'
0%
#437000
10
1"
b100 #
b100 *
b100 ,
1'
1%
#438000
0!
0)
0.
0'
0%
#439000
0"
b0 #
b0 *
b0 ,
00
1'
1%
#440000
0'
0%
#441000
1/
b1 #
b1 *
b1 ,
1'
1%
#442000
0'
0%
#443000
1!
b10 #
b10 *
b10 ,
0/
1(
1-
1'
1%
#444000
0'
0%
#445000
b11 #
b11 *
b11 ,
1'
1%
#446000
0'
0%
#447000
1"
b100 #
b100 *
b100 ,
10
1'
1%
#448000
0!
1)
1.
0'
0%
#449000
00
0"
b0 #
b0 *
b0 ,
1'
1%
#450000
0'
0%
#451000
b1 #
b1 *
b1 ,
1/
1'
1%
#452000
0'
0%
#453000
1!
0(
0-
0/
b10 #
b10 *
b10 ,
1'
1%
#454000
0'
0%
#455000
b11 #
b11 *
b11 ,
1'
1%
#456000
0'
0%
#457000
10
1"
b100 #
b100 *
b100 ,
1'
1%
#458000
0!
0)
0.
0'
0%
#459000
0"
b0 #
b0 *
b0 ,
00
1'
1%
#460000
0'
0%
#461000
1/
b1 #
b1 *
b1 ,
1'
1%
#462000
0'
0%
#463000
1!
b10 #
b10 *
b10 ,
0/
1(
1-
1'
1%
#464000
0'
0%
#465000
b11 #
b11 *
b11 ,
1'
1%
#466000
0'
0%
#467000
1"
b100 #
b100 *
b100 ,
10
1'
1%
#468000
0!
1)
1.
0'
0%
#469000
00
0"
b0 #
b0 *
b0 ,
1'
1%
#470000
0'
0%
#471000
b1 #
b1 *
b1 ,
1/
1'
1%
#472000
0'
0%
#473000
1!
0(
0-
0/
b10 #
b10 *
b10 ,
1'
1%
#474000
0'
0%
#475000
b11 #
b11 *
b11 ,
1'
1%
#476000
0'
0%
#477000
10
1"
b100 #
b100 *
b100 ,
1'
1%
#478000
0!
0)
0.
0'
0%
#479000
0"
b0 #
b0 *
b0 ,
00
1'
1%
#480000
0'
0%
#481000
1/
b1 #
b1 *
b1 ,
1'
1%
#482000
0'
0%
#483000
1!
b10 #
b10 *
b10 ,
0/
1(
1-
1'
1%
#484000
0'
0%
#485000
b11 #
b11 *
b11 ,
1'
1%
#486000
0'
0%
#487000
1"
b100 #
b100 *
b100 ,
10
1'
1%
#488000
0!
1)
1.
0'
0%
#489000
00
0"
b0 #
b0 *
b0 ,
1'
1%
#490000
0'
0%
#491000
b1 #
b1 *
b1 ,
1/
1'
1%
#492000
0'
0%
#493000
1!
0(
0-
0/
b10 #
b10 *
b10 ,
1'
1%
#494000
0'
0%
#495000
b11 #
b11 *
b11 ,
1'
1%
#496000
0'
0%
#497000
10
1"
b100 #
b100 *
b100 ,
1'
1%
#498000
0!
0)
0.
0'
0%
#499000
0"
b0 #
b0 *
b0 ,
00
1'
1%
#500000
0'
0%
#501000
1/
b1 #
b1 *
b1 ,
1'
1%
#502000
0'
0%
#503000
1!
b10 #
b10 *
b10 ,
0/
1(
1-
1'
1%
#504000
0'
0%
#505000
b11 #
b11 *
b11 ,
1'
1%
#506000
0'
0%
#507000
1"
b100 #
b100 *
b100 ,
10
1'
1%
#508000
0!
1)
1.
0'
0%
#509000
00
0"
b0 #
b0 *
b0 ,
1'
1%
#510000
0'
0%
#511000
b1 #
b1 *
b1 ,
1/
1'
1%
#512000
0'
0%
#513000
1!
0(
0-
0/
b10 #
b10 *
b10 ,
1'
1%
#514000
0'
0%
#515000
b11 #
b11 *
b11 ,
1'
1%
#516000
0'
0%
#517000
10
1"
b100 #
b100 *
b100 ,
1'
1%
#518000
0!
0)
0.
0'
0%
#519000
0"
b0 #
b0 *
b0 ,
00
1'
1%
#520000
0'
0%
#521000
1/
b1 #
b1 *
b1 ,
1'
1%
#522000
0'
0%
#523000
1!
b10 #
b10 *
b10 ,
0/
1(
1-
1'
1%
#524000
0'
0%
#525000
b11 #
b11 *
b11 ,
1'
1%
#526000
0'
0%
#527000
1"
b100 #
b100 *
b100 ,
10
1'
1%
#528000
0!
1)
1.
0'
0%
#529000
00
0"
b0 #
b0 *
b0 ,
1'
1%
#530000
0'
0%
#531000
b1 #
b1 *
b1 ,
1/
1'
1%
#532000
0'
0%
#533000
1!
0(
0-
0/
b10 #
b10 *
b10 ,
1'
1%
#534000
0'
0%
#535000
b11 #
b11 *
b11 ,
1'
1%
#536000
0'
0%
#537000
10
1"
b100 #
b100 *
b100 ,
1'
1%
#538000
0!
0)
0.
0'
0%
#539000
0"
b0 #
b0 *
b0 ,
00
1'
1%
#540000
0'
0%
#541000
1/
b1 #
b1 *
b1 ,
1'
1%
#542000
0'
0%
#543000
1!
b10 #
b10 *
b10 ,
0/
1(
1-
1'
1%
#544000
0'
0%
#545000
b11 #
b11 *
b11 ,
1'
1%
#546000
0'
0%
#547000
1"
b100 #
b100 *
b100 ,
10
1'
1%
#548000
0!
1)
1.
0'
0%
#549000
00
0"
b0 #
b0 *
b0 ,
1'
1%
#550000
0'
0%
#551000
b1 #
b1 *
b1 ,
1/
1'
1%
#552000
0'
0%
#553000
1!
0(
0-
0/
b10 #
b10 *
b10 ,
1'
1%
#554000
0'
0%
#555000
b11 #
b11 *
b11 ,
1'
1%
#556000
0'
0%
#557000
10
1"
b100 #
b100 *
b100 ,
1'
1%
#558000
0!
0)
0.
0'
0%
#559000
0"
b0 #
b0 *
b0 ,
00
1'
1%
#560000
0'
0%
#561000
1/
b1 #
b1 *
b1 ,
1'
1%
#562000
0'
0%
#563000
1!
b10 #
b10 *
b10 ,
0/
1(
1-
1'
1%
#564000
0'
0%
#565000
b11 #
b11 *
b11 ,
1'
1%
#566000
0'
0%
#567000
1"
b100 #
b100 *
b100 ,
10
1'
1%
#568000
0!
1)
1.
0'
0%
#569000
00
0"
b0 #
b0 *
b0 ,
1'
1%
#570000
0'
0%
#571000
b1 #
b1 *
b1 ,
1/
1'
1%
#572000
0'
0%
#573000
1!
0(
0-
0/
b10 #
b10 *
b10 ,
1'
1%
#574000
0'
0%
#575000
b11 #
b11 *
b11 ,
1'
1%
#576000
0'
0%
#577000
10
1"
b100 #
b100 *
b100 ,
1'
1%
#578000
0!
0)
0.
0'
0%
#579000
0"
b0 #
b0 *
b0 ,
00
1'
1%
#580000
0'
0%
#581000
1/
b1 #
b1 *
b1 ,
1'
1%
#582000
0'
0%
#583000
1!
b10 #
b10 *
b10 ,
0/
1(
1-
1'
1%
#584000
0'
0%
#585000
b11 #
b11 *
b11 ,
1'
1%
#586000
0'
0%
#587000
1"
b100 #
b100 *
b100 ,
10
1'
1%
#588000
0!
1)
1.
0'
0%
