clkDivider/clkDivider_by8_counter.v
//////////////////////////////////////////////////////////////////////
// Module Name: counterCase02.v
// Description: Counter with clock gating and counter valid control
// Designer: Barney Peng
// Date: 03/19/2024
//////////////////////////////////////////////////////////////////////

//module counter #(parameter WIDTH (8) /* 8 bit counter*/)(
module clkDivider_by8_counter (
  input clk,
  input resetn,
  //input i_clk_en,           // Clock and reset and enable inputs

  output o_count_end, 		      // counter reaches max value
  output wire [WIDTH-1 : 0] o_count,   // Output of the counter(remember that 8-bit: [7:0](7 to 0))
  //output reg div2_clk,
  //output reg div4_clk,
  output reg div8_clk

);

	parameter WIDTH = 3; /* 8 bit counter*/

	reg [WIDTH-1 : 0] o_count_p;
	wire clk_gate;		// gated clock
	
	//assign clk_gate = clk & i_clk_en;
	assign clk_gate = clk;

	always @(negedge resetn or posedge clk_gate)       // At every positive edge of the clock or negative edge of restn
		begin
			if  (~resetn)
		 		o_count_p <= 3'h0;		 // If reset is asserted, set the counter to 0
			else 
				o_count_p <=  o_count_p + 1;         // Increment the counter by 1
		end


		always @(negedge resetn or posedge clk_gate)       // At every positive edge of the clock or negative edge of restn
		begin
			if  (~resetn)
				div8_clk <= 3'h0;		 // If reset is asserted, set the counter to 0
			else if(o_count_p < 3'd4)
				div8_clk <=  0;         // Increment the counter by 1
			else if(o_count_p >= 3'd4)
				div8_clk <=  1;         // Increment the counter by 1
			else
				div8_clk <=  div8_clk;      // Otherwise, deassign the output
		end


	assign o_count_end = (o_count == 3'd7);
	assign o_count = o_count_p;


endmodule // counter

clkDivider/clkDivider_by8_counter_tb.v
`timescale 1ns / 1ps //set the timescale for the module
//////////////////////////////////////////////////////////////////////
// Module Name: counterCase02_tb.v
// Description: Counter with clock gating and counter valid control
// Designer: Barney Peng
// Date: 03/18/2024
//////////////////////////////////////////////////////////////////////

module clkDivider_by8_counter_tb;
//Reference: https://youtu.be/5Kync4z5VOw?si=u34tsfena2Eo7J3K

/* Make a reset that pulse once. */
reg resetn;
//reg i_clk_en; //give initial values to the signals

wire  o_count_end;
wire [2:0] o_count;

initial begin
    resetn = 0;
    #20   resetn = 1;
    #4000 resetn = 1;
    $finish;
end

// free running clock clk
reg clk = 0;
always #1 clk = !clk;

initial begin
    $monitor("At time %t, o_count = %h (%0d)", $time, o_count, o_count);
end
/*
initial begin
          i_clk_en = 0;
    #100  i_clk_en = 1; // gated the clock the counter after some delay
    #1500 i_clk_en = 0; // gated the clock the counter after some cycles
end
*/


initial begin
   // $monitor("At time %t, div2_clk = %h (%0d)", $time, div2_clk, div2_clk);
  //  $monitor("At time %t, div4_clk = %h (%0d)", $time, div4_clk, div4_clk);
    $monitor("At time %t, div8_clk = %h (%0d)", $time, div8_clk, div8_clk);
end

initial begin
    $dumpfile("clkDivider_by8_counter.vcd");
    $dumpvars(0,clkDivider_by8_counter_tb);
end

clkDivider_by8_counter u_clkDivider_by8_counter (
    .clk(clk),
    .resetn(resetn),
    //.i_clk_en(i_clk_en),

    .o_count_end(o_count_end),
    .o_count(o_count),

   // .div2_clk(div2_clk),
   // .div4_clk(div4_clk),
    .div8_clk(div8_clk)
);

endmodule

clkDivider/clkDivider_by8_counter.vcd
$date
	Tue Mar 19 23:16:05 2024
$end
$version
	Icarus Verilog
$end
$timescale
	1ps
$end
$scope module clkDivider_by8_counter_tb $end
$var wire 1 ! o_count_end $end
$var wire 3 " o_count [2:0] $end
$var wire 1 # div8_clk $end
$var reg 1 $ clk $end
$var reg 1 % resetn $end
$scope module u_clkDivider_by8_counter $end
$var wire 1 $ clk $end
$var wire 1 & clk_gate $end
$var wire 1 % resetn $end
$var wire 1 ! o_count_end $end
$var wire 3 ' o_count [2:0] $end
$var parameter 32 ( WIDTH $end
$var reg 1 # div8_clk $end
$var reg 3 ) o_count_p [2:0] $end
$upscope $end
$upscope $end
$enddefinitions $end
$comment Show the parameter values. $end
$dumpall
b11 (
$end
#0
$dumpvars
b0 )
b0 '
0&
0%
0$
0#
b0 "
0!
$end
#1000
1&
1$
#2000
0&
0$
#3000
1&
1$
#4000
0&
0$
#5000
1&
1$
#6000
0&
0$
#7000
1&
1$
#8000
0&
0$
#9000
1&
1$
#10000
0&
0$
#11000
1&
1$
#12000
0&
0$
#13000
1&
1$
#14000
0&
0$
#15000
1&
1$
#16000
0&
0$
#17000
1&
1$
#18000
0&
0$
#19000
1&
1$
#20000
0&
0$
1%
#21000
b1 "
b1 '
b1 )
1&
1$
#22000
0&
0$
#23000
b10 "
b10 '
b10 )
1&
1$
#24000
0&
0$
#25000
b11 "
b11 '
b11 )
1&
1$
#26000
0&
0$
#27000
b100 "
b100 '
b100 )
1&
1$
#28000
0&
0$
#29000
1#
b101 "
b101 '
b101 )
1&
1$
#30000
0&
0$
#31000
b110 "
b110 '
b110 )
1&
1$
#32000
0&
0$
#33000
1!
b111 "
b111 '
b111 )
1&
1$
#34000
0&
0$
#35000
0!
b0 "
b0 '
b0 )
1&
1$
#36000
0&
0$
#37000
0#
b1 "
b1 '
b1 )
1&
1$
#38000
0&
0$
#39000
b10 "
b10 '
b10 )
1&
1$
#40000
0&
0$
#41000
b11 "
b11 '
b11 )
1&
1$
#42000
0&
0$
#43000
b100 "
b100 '
b100 )
1&
1$
#44000
0&
0$
#45000
1#
b101 "
b101 '
b101 )
1&
1$
#46000
0&
0$
#47000
b110 "
b110 '
b110 )
1&
1$
#48000
0&
0$
#49000
1!
b111 "
b111 '
b111 )
1&
1$
#50000
0&
0$
#51000
0!
b0 "
b0 '
b0 )
1&
1$
#52000
0&
0$
#53000
0#
b1 "
b1 '
b1 )
1&
1$
#54000
0&
0$
#55000
b10 "
b10 '
b10 )
1&
1$
#56000
0&
0$
#57000
b11 "
b11 '
b11 )
1&
1$
#58000
0&
0$
#59000
b100 "
b100 '
b100 )
1&
1$
#60000
0&
0$
#61000
1#
b101 "
b101 '
b101 )
1&
1$
#62000
0&
0$
#63000
b110 "
b110 '
b110 )
1&
1$
#64000
0&
0$
#65000
1!
b111 "
b111 '
b111 )
1&
1$
#66000
0&
0$
#67000
0!
b0 "
b0 '
b0 )
1&
1$
#68000
0&
0$
#69000
0#
b1 "
b1 '
b1 )
1&
1$
#70000
0&
0$
#71000
b10 "
b10 '
b10 )
1&
1$
#72000
0&
0$
#73000
b11 "
b11 '
b11 )
1&
1$
#74000
0&
0$
#75000
b100 "
b100 '
b100 )
1&
1$
#76000
0&
0$
#77000
1#
b101 "
b101 '
b101 )
1&
1$
#78000
0&
0$
#79000
b110 "
b110 '
b110 )
1&
1$
#80000
0&
0$
#81000
1!
b111 "
b111 '
b111 )
1&
1$
#82000
0&
0$
#83000
0!
b0 "
b0 '
b0 )
1&
1$
#84000
0&
0$
#85000
0#
b1 "
b1 '
b1 )
1&
1$
#86000
0&
0$
#87000
b10 "
b10 '
b10 )
1&
1$
#88000
0&
0$
#89000
b11 "
b11 '
b11 )
1&
1$
#90000
0&
0$
#91000
b100 "
b100 '
b100 )
1&
1$
#92000
0&
0$
#93000
1#
b101 "
b101 '
b101 )
1&
1$
#94000
0&
0$
#95000
b110 "
b110 '
b110 )
1&
1$
#96000
0&
0$
#97000
1!
b111 "
b111 '
b111 )
1&
1$
#98000
0&
0$
#99000
0!
b0 "
b0 '
b0 )
1&
1$
#100000
0&
0$
#101000
0#
b1 "
b1 '
b1 )
1&
1$
#102000
0&
0$
#103000
b10 "
b10 '
b10 )
1&
1$
#104000
0&
0$
#105000
b11 "
b11 '
b11 )
1&
1$
#106000
0&
0$
#107000
b100 "
b100 '
b100 )
1&
1$
#108000
0&
0$
#109000
1#
b101 "
b101 '
b101 )
1&
1$
#110000
0&
0$
#111000
b110 "
b110 '
b110 )
1&
1$
#112000
0&
0$
#113000
1!
b111 "
b111 '
b111 )
1&
1$
#114000
0&
0$
#115000
0!
b0 "
b0 '
b0 )
1&
1$
#116000
0&
0$
#117000
0#
b1 "
b1 '
b1 )
1&
1$
#118000
0&
0$
#119000
b10 "
b10 '
b10 )
1&
1$
#120000
0&
0$
#121000
b11 "
b11 '
b11 )
1&
1$
#122000
0&
0$
#123000
b100 "
b100 '
b100 )
1&
1$
#124000
0&
0$
#125000
1#
b101 "
b101 '
b101 )
1&
1$
#126000
0&
0$
#127000
b110 "
b110 '
b110 )
1&
1$
#128000
0&
0$
#129000
1!
b111 "
b111 '
b111 )
1&
1$
#130000
0&
0$
#131000
0!
b0 "
b0 '
b0 )
1&
1$
#132000
0&
0$
#133000
0#
b1 "
b1 '
b1 )
1&
1$
#134000
0&
0$
#135000
b10 "
b10 '
b10 )
1&
1$
#136000
0&
0$
#137000
b11 "
b11 '
b11 )
1&
1$
#138000
0&
0$
#139000
b100 "
b100 '
b100 )
1&
1$
#140000
0&
0$
#141000
1#
b101 "
b101 '
b101 )
1&
1$
#142000
0&
0$
#143000
b110 "
b110 '
b110 )
1&
1$
#144000
0&
0$
#145000
1!
b111 "
b111 '
b111 )
1&
1$
#146000
0&
0$
#147000
0!
b0 "
b0 '
b0 )
1&
1$
#148000
0&
0$
#149000
0#
b1 "
b1 '
b1 )
1&
1$
#150000
0&
0$
#151000
b10 "
b10 '
b10 )
1&
1$
#152000
0&
0$
#153000
b11 "
b11 '
b11 )
1&
1$
#154000
0&
0$
#155000
b100 "
b100 '
b100 )
1&
1$
#156000
0&
0$
#157000
1#
b101 "
b101 '
b101 )
1&
1$
#158000
0&
0$
#159000
b110 "
b110 '
b110 )
1&
1$
#160000
0&
0$
#161000
1!
b111 "
b111 '
b111 )
1&
1$
#162000
0&
0$
#163000
0!
b0 "
b0 '
b0 )
1&
1$
#164000
0&
0$
#165000
0#
b1 "
b1 '
b1 )
1&
1$
#166000
0&
0$
#167000
b10 "
b10 '
b10 )
1&
1$
#168000
0&
0$
#169000
b11 "
b11 '
b11 )
1&
1$
#170000
0&
0$
#171000
b100 "
b100 '
b100 )
1&
1$
#172000
0&
0$
#173000
1#
b101 "
b101 '
b101 )
1&
1$
#174000
0&
0$
#175000
b110 "
b110 '
b110 )
1&
1$
#176000
0&
0$
#177000
1!
b111 "
b111 '
b111 )
1&
1$
#178000
0&
0$
#179000
0!
b0 "
b0 '
b0 )
1&
1$
#180000
0&
0$
#181000
0#
b1 "
b1 '
b1 )
1&
1$
#182000
0&
0$
#183000
b10 "
b10 '
b10 )
1&
1$
#184000
0&
0$
#185000
b11 "
b11 '
b11 )
1&
1$
#186000
0&
0$
#187000
b100 "
b100 '
b100 )
1&
1$
#188000
0&
0$
#189000
1#
b101 "
b101 '
b101 )
1&
1$
#190000
0&
0$
#191000
b110 "
b110 '
b110 )
1&
1$
#192000
0&
0$
#193000
1!
b111 "
b111 '
b111 )
1&
1$
#194000
0&
0$
#195000
0!
b0 "
b0 '
b0 )
1&
1$
#196000
0&
0$
#197000
0#
b1 "
b1 '
b1 )
1&
1$
#198000
0&
0$
#199000
b10 "
b10 '
b10 )
1&
1$
#200000
0&
0$
#201000
b11 "
b11 '
b11 )
1&
1$
#202000
0&
0$
#203000
b100 "
b100 '
b100 )
1&
1$
#204000
0&
0$
#205000
1#
b101 "
b101 '
b101 )
1&
1$
#206000
0&
0$
#207000
b110 "
b110 '
b110 )
1&
1$
#208000
0&
0$
#209000
1!
b111 "
b111 '
b111 )
1&
1$
#210000
0&
0$
#211000
0!
b0 "
b0 '
b0 )
1&
1$
#212000
0&
0$
#213000
0#
b1 "
b1 '
b1 )
1&
1$
#214000
0&
0$
#215000
b10 "
b10 '
b10 )
1&
1$
#216000
0&
0$
#217000
b11 "
b11 '
b11 )
1&
1$
#218000
0&
0$
#219000
b100 "
b100 '
b100 )
1&
1$
#220000
0&
0$
#221000
1#
b101 "
b101 '
b101 )
1&
1$
#222000
0&
0$
#223000
b110 "
b110 '
b110 )
1&
1$
#224000
0&
0$
#225000
1!
b111 "
b111 '
b111 )
1&
1$
#226000
0&
0$
#227000
0!
b0 "
b0 '
b0 )
1&
1$
#228000
0&
0$
#229000
0#
b1 "
b1 '
b1 )
1&
1$
#230000
0&
0$
#231000
b10 "
b10 '
b10 )
1&
1$
#232000
0&
0$
#233000
b11 "
b11 '
b11 )
1&
1$
#234000
0&
0$
#235000
b100 "
b100 '
b100 )
1&
1$
#236000
0&
0$
#237000
1#
b101 "
b101 '
b101 )
1&
1$
#238000
0&
0$
#239000
b110 "
b110 '
b110 )
1&
1$
#240000
0&
0$
#241000
1!
b111 "
b111 '
b111 )
1&
1$
#242000
0&
0$
#243000
0!
b0 "
b0 '
b0 )
1&
1$
#244000
0&
0$
#245000
0#
b1 "
b1 '
b1 )
1&
1$
#246000
0&
0$
#247000
b10 "
b10 '
b10 )
1&
1$
#248000
0&
0$
#249000
b11 "
b11 '
b11 )
1&
1$
#250000
0&
0$
#251000
b100 "
b100 '
b100 )
1&
1$
#252000
0&
0$
#253000
1#
b101 "
b101 '
b101 )
1&
1$
#254000
0&
0$
#255000
b110 "
b110 '
b110 )
1&
1$
#256000
0&
0$
#257000
1!
b111 "
b111 '
b111 )
1&
1$
#258000
0&
0$
#259000
0!
b0 "
b0 '
b0 )
1&
1$
#260000
0&
0$
#261000
0#
b1 "
b1 '
b1 )
1&
1$
#262000
0&
0$
#263000
b10 "
b10 '
b10 )
1&
1$
#264000
0&
0$
#265000
b11 "
b11 '
b11 )
1&
1$
#266000
0&
0$
#267000
b100 "
b100 '
b100 )
1&
1$
#268000
0&
0$
#269000
1#
b101 "
b101 '
b101 )
1&
1$
#270000
0&
0$
#271000
b110 "
b110 '
b110 )
1&
1$
#272000
0&
0$
#273000
1!
b111 "
b111 '
b111 )
1&
1$
#274000
0&
0$
#275000
0!
b0 "
b0 '
b0 )
1&
1$
#276000
0&
0$
#277000
0#
b1 "
b1 '
b1 )
1&
1$
#278000
0&
0$
#279000
b10 "
b10 '
b10 )
1&
1$
#280000
0&
0$
#281000
b11 "
b11 '
b11 )
1&
1$
#282000
0&
0$
#283000
b100 "
b100 '
b100 )
1&
1$
#284000
0&
0$
#285000
1#
b101 "
b101 '
b101 )
1&
1$
#286000
0&
0$
#287000
b110 "
b110 '
b110 )
1&
1$
#288000
0&
0$
#289000
1!
b111 "
b111 '
b111 )
1&
1$
#290000
0&
0$
#291000
0!
b0 "
b0 '
b0 )
1&
1$
#292000
0&
0$
#293000
0#
b1 "
b1 '
b1 )
1&
1$
#294000
0&
0$
#295000
b10 "
b10 '
b10 )
1&
1$
#296000
0&
0$
#297000
b11 "
b11 '
b11 )
1&
1$
#298000
0&
0$
#299000
b100 "
b100 '
b100 )
1&
1$
#300000
0&
0$
#301000
1#
b101 "
b101 '
b101 )
1&
1$
#302000
0&
0$
#303000
b110 "
b110 '
b110 )
1&
1$
#304000
0&
0$
#305000
1!
b111 "
b111 '
b111 )
1&
1$
#306000
0&
0$
#307000
0!
b0 "
b0 '
b0 )
1&
1$
#308000
0&
0$
#309000
0#
b1 "
b1 '
b1 )
1&
1$
#310000
0&
0$
#311000
b10 "
b10 '
b10 )
1&
1$
#312000
0&
0$
#313000
b11 "
b11 '
b11 )
1&
1$
#314000
0&
0$
#315000
b100 "
b100 '
b100 )
1&
1$
#316000
0&
0$
#317000
1#
b101 "
b101 '
b101 )
1&
1$
#318000
0&
0$
#319000
b110 "
b110 '
b110 )
1&
1$
#320000
0&
0$
#321000
1!
b111 "
b111 '
b111 )
1&
1$
#322000
0&
0$
#323000
0!
b0 "
b0 '
b0 )
1&
1$
#324000
0&
0$
#325000
0#
b1 "
b1 '
b1 )
1&
1$
#326000
0&
0$
#327000
b10 "
b10 '
b10 )
1&
1$
#328000
0&
0$
#329000
b11 "
b11 '
b11 )
1&
1$
#330000
0&
0$
#331000
b100 "
b100 '
b100 )
1&
1$
#332000
0&
0$
#333000
1#
b101 "
b101 '
b101 )
1&
1$
#334000
0&
0$
#335000
b110 "
b110 '
b110 )
1&
1$
#336000
0&
0$
#337000
1!
b111 "
b111 '
b111 )
1&
1$
#338000
0&
0$
#339000
0!
b0 "
b0 '
b0 )
1&
1$
#340000
0&
0$
#341000
0#
b1 "
b1 '
b1 )
1&
1$
#342000
0&
0$
#343000
b10 "
b10 '
b10 )
1&
1$
#344000
0&
0$
#345000
b11 "
b11 '
b11 )
1&
1$
#346000
0&
0$
#347000
b100 "
b100 '
b100 )
1&
1$
#348000
0&
0$
#349000
1#
b101 "
b101 '
b101 )
1&
1$
#350000
0&
0$
#351000
b110 "
b110 '
b110 )
1&
1$
#352000
0&
0$
#353000
1!
b111 "
b111 '
b111 )
1&
1$
#354000
0&
0$
#355000
0!
b0 "
b0 '
b0 )
1&
1$
#356000
0&
0$
#357000
0#
b1 "
b1 '
b1 )
1&
1$
#358000
0&
0$
#359000
b10 "
b10 '
b10 )
1&
1$
#360000
0&
0$
#361000
b11 "
b11 '
b11 )
1&
1$
#362000
0&
0$
#363000
b100 "
b100 '
b100 )
1&
1$
#364000
0&
0$
#365000
1#
b101 "
b101 '
b101 )
1&
1$
#366000
0&
0$
#367000
b110 "
b110 '
b110 )
1&
1$
#368000
0&
0$
#369000
1!
b111 "
b111 '
b111 )
1&
1$
#370000
0&
0$
#371000
0!
b0 "
b0 '
b0 )
1&
1$
#372000
0&
0$
#373000
0#
b1 "
b1 '
b1 )
1&
1$
#374000
0&
0$
#375000
b10 "
b10 '
b10 )
1&
1$
#376000
0&
0$
#377000
b11 "
b11 '
b11 )
1&
1$
#378000
0&
0$
#379000
b100 "
b100 '
b100 )
1&
1$
#380000
0&
0$
#381000
1#
b101 "
b101 '
b101 )
1&
1$
#382000
0&
0$
#383000
b110 "
b110 '
b110 )
1&
1$
#384000
0&
0$
#385000
1!
b111 "
b111 '
b111 )
1&
1$
#386000
0&
0$
#387000
0!
b0 "
b0 '
b0 )
1&
1$
#388000
0&
0$
#389000
0#
b1 "
b1 '
b1 )
1&
1$
#390000
0&
0$
#391000
b10 "
b10 '
b10 )
1&
1$
#392000
0&
0$
#393000
b11 "
b11 '
b11 )
1&
1$
#394000
0&
0$
#395000
b100 "
b100 '
b100 )
1&
1$
#396000
0&
0$
#397000
1#
b101 "
b101 '
b101 )
1&
1$
#398000
0&
0$
#399000
b110 "
b110 '
b110 )
1&
1$
#400000
0&
0$
#401000
1!
b111 "
b111 '
b111 )
1&
1$
#402000
0&
0$
#403000
0!
b0 "
b0 '
b0 )
1&
1$
#404000
0&
0$
#405000
0#
b1 "
b1 '
b1 )
1&
1$
#406000
0&
0$
#407000
b10 "
b10 '
b10 )
1&
1$
#408000
0&
0$
#409000
b11 "
b11 '
b11 )
1&
1$
#410000
0&
0$
#411000
b100 "
b100 '
b100 )
1&
1$
#412000
0&
0$
#413000
1#
b101 "
b101 '
b101 )
1&
1$
#414000
0&
0$
#415000
b110 "
b110 '
b110 )
1&
1$
#416000
0&
0$
#417000
1!
b111 "
b111 '
b111 )
1&
1$
#418000
0&
0$
#419000
0!
b0 "
b0 '
b0 )
1&
1$
#420000
0&
0$
#421000
0#
b1 "
b1 '
b1 )
1&
1$
#422000
0&
0$
#423000
b10 "
b10 '
b10 )
1&
1$
#424000
0&
0$
#425000
b11 "
b11 '
b11 )
1&
1$
#426000
0&
0$
#427000
b100 "
b100 '
b100 )
1&
1$
#428000
0&
0$
#429000
1#
b101 "
b101 '
b101 )
1&
1$
#430000
0&
0$
#431000
b110 "
b110 '
b110 )
1&
1$
#432000
0&
0$
#433000
1!
b111 "
b111 '
b111 )
1&
1$
#434000
0&
0$
#435000
0!
b0 "
b0 '
b0 )
1&
1$
#436000
0&
0$
#437000
0#
b1 "
b1 '
b1 )
1&
1$
#438000
0&
0$
#439000
b10 "
b10 '
b10 )
1&
1$
#440000
0&
0$
#441000
b11 "
b11 '
b11 )
1&
1$
#442000
0&
0$
#443000
b100 "
b100 '
b100 )
1&
1$
#444000
0&
0$
#445000
1#
b101 "
b101 '
b101 )
1&
1$
#446000
0&
0$
#447000
b110 "
b110 '
b110 )
1&
1$
#448000
0&
0$
#449000
1!
b111 "
b111 '
b111 )
1&
1$
#450000
0&
0$
#451000
0!
b0 "
b0 '
b0 )
1&
1$
#452000
0&
0$
#453000
0#
b1 "
b1 '
b1 )
1&
1$
#454000
0&
0$
#455000
b10 "
b10 '
b10 )
1&
1$
#456000
0&
0$
#457000
b11 "
b11 '
b11 )
1&
1$
#458000
0&
0$
#459000
b100 "
b100 '
b100 )
1&
1$
#460000
0&
0$
#461000
1#
b101 "
b101 '
b101 )
1&
1$
#462000
0&
0$
#463000
b110 "
b110 '
b110 )
1&
1$
#464000
0&
0$
#465000
1!
b111 "
b111 '
b111 )
1&
1$
#466000
0&
0$
#467000
0!
b0 "
b0 '
b0 )
1&
1$
#468000
0&
0$
#469000
0#
b1 "
b1 '
b1 )
1&
1$
#470000
0&
0$
#471000
b10 "
b10 '
b10 )
1&
1$
#472000
0&
0$
#473000
b11 "
b11 '
b11 )
1&
1$
#474000
0&
0$
#475000
b100 "
b100 '
b100 )
1&
1$
#476000
0&
0$
#477000
1#
b101 "
b101 '
b101 )
1&
1$
#478000
0&
0$
#479000
b110 "
b110 '
b110 )
1&
1$
#480000
0&
0$
#481000
1!
b111 "
b111 '
b111 )
1&
1$
#482000
0&
0$
#483000
0!
b0 "
b0 '
b0 )
1&
1$
#484000
0&
0$
#485000
0#
b1 "
b1 '
b1 )
1&
1$
#486000
0&
0$
#487000
b10 "
b10 '
b10 )
1&
1$
#488000
0&
0$
#489000
b11 "
b11 '
b11 )
1&
1$
#490000
0&
0$
#491000
b100 "
b100 '
b100 )
1&
1$
#492000
0&
0$
#493000
1#
b101 "
b101 '
b101 )
1&
1$
#494000
0&
0$
#495000
b110 "
b110 '
b110 )
1&
1$
#496000
0&
0$
#497000
1!
b111 "
b111 '
b111 )
1&
1$
#498000
0&
0$
#499000
0!
b0 "
b0 '
b0 )
1&
1$
#500000
0&
0$
#501000
0#
b1 "
b1 '
b1 )
1&
1$
#502000
0&
0$
#503000
b10 "
b10 '
b10 )
1&
1$
#504000
0&
0$
#505000
b11 "
b11 '
b11 )
1&
1$
#506000
0&
0$
#507000
b100 "
b100 '
b100 )
1&
1$
#508000
0&
0$
#509000
1#
b101 "
b101 '
b101 )
1&
1$
#510000
0&
0$
#511000
b110 "
b110 '
b110 )
1&
1$
#512000
0&
0$
#513000
1!
b111 "
b111 '
b111 )
1&
1$
#514000
0&
0$
#515000
0!
b0 "
b0 '
b0 )
1&
1$
#516000
0&
0$
#517000
0#
b1 "
b1 '
b1 )
1&
1$
#518000
0&
0$
#519000
b10 "
b10 '
b10 )
1&
1$
#520000
0&
0$
#521000
b11 "
b11 '
b11 )
1&
1$
#522000
0&
0$
#523000
b100 "
b100 '
b100 )
1&
1$
#524000
0&
0$
#525000
1#
b101 "
b101 '
b101 )
1&
1$
#526000
0&
0$
#527000
b110 "
b110 '
b110 )
1&
1$
#528000
0&
0$
#529000
1!
b111 "
b111 '
b111 )
1&
1$
#530000
0&
0$
#531000
0!
b0 "
b0 '
b0 )
1&
1$
#532000
0&
0$
#533000
0#
b1 "
b1 '
b1 )
1&
1$
#534000
0&
0$
#535000
b10 "
b10 '
b10 )
1&
1$
#536000
0&
0$
#537000
b11 "
b11 '
b11 )
1&
1$
#538000
0&
0$
#539000
b100 "
b100 '
b100 )
1&
1$
#540000
0&
0$
#541000
1#
b101 "
b101 '
b101 )
1&
1$
#542000
0&
0$
#543000
b110 "
b110 '
b110 )
1&
1$
#544000
0&
0$
#545000
1!
b111 "
b111 '
b111 )
1&
1$
#546000
0&
0$
#547000
0!
b0 "
b0 '
b0 )
1&
1$
#548000
0&
0$
#549000
0#
b1 "
b1 '
b1 )
1&
1$
#550000
0&
0$
#551000
b10 "
b10 '
b10 )
1&
1$
#552000
0&
0$
#553000
b11 "
b11 '
b11 )
1&
1$
#554000
0&
0$
#555000
b100 "
b100 '
b100 )
1&
1$
#556000
0&
0$
#557000
1#
b101 "
b101 '
b101 )
1&
1$
#558000
0&
0$
#559000
b110 "
b110 '
b110 )
1&
1$
#560000
0&
0$
#561000
1!
b111 "
b111 '
b111 )
1&
1$
#562000
0&
0$
#563000
0!
b0 "
b0 '
b0 )
1&
1$
#564000
0&
0$
#565000
0#
b1 "
b1 '
b1 )
1&
1$
#566000
0&
0$
#567000
b10 "
b10 '
b10 )
1&
1$
#568000
0&
0$
#569000
b11 "
b11 '
b11 )
1&
1$
#570000
0&
0$
#571000
b100 "
b100 '
b100 )
1&
1$
#572000
0&
0$
#573000
1#
b101 "
b101 '
b101 )
1&
1$
#574000
0&
0$
#575000
b110 "
b110 '
b110 )
1&
1$
#576000
0&
0$
#577000
1!
b111 "
b111 '
b111 )
1&
1$
#578000
0&
0$
#579000
0!
b0 "
b0 '
b0 )
1&
1$
#580000
0&
0$
#581000
0#
b1 "
b1 '
b1 )
1&
1$
#582000
0&
0$
#583000
b10 "
b10 '
b10 )
1&
1$
#584000
0&
0$
#585000
b11 "
b11 '
b11 )
1&
1$
#586000
0&
0$
#587000
b100 "
b100 '
b100 )
1&
1$
#588000
0&
0$
#589000
1#
b101 "
b101 '
b101 )
1&
1$
#590000
0&
0$
#591000
b110 "
b110 '
b110 )
1&
1$
#592000
0&
0$
#593000
1!
b111 "
b111 '
b111 )
1&
1$
#594000
0&
0$
#595000
0!
b0 "
b0 '
b0 )
1&
1$
#596000
0&
0$
#597000
0#
b1 "
b1 '
b1 )
1&
1$
#598000
0&
0$
#599000
b10 "
b10 '
b10 )
1&
1$
#600000
0&
0$
#601000
b11 "
b11 '
b11 )
1&
1$
#602000
0&
0$
#603000
b100 "
b100 '
b100 )
1&
1$
#604000
0&
0$
#605000
1#
b101 "
b101 '
b101 )
1&
1$
#606000
0&
0$
#607000
b110 "
b110 '
b110 )
1&
1$
#608000
0&
0$
#609000
1!
b111 "
b111 '
b111 )
1&
1$
#610000
0&
0$
#611000
0!
b0 "
b0 '
b0 )
1&
1$
#612000
0&
0$
#613000
0#
b1 "
b1 '
b1 )
1&
1$
#614000
0&
0$
#615000
b10 "
b10 '
b10 )
1&
1$
#616000
0&
0$
#617000
b11 "
b11 '
b11 )
1&
1$
#618000
0&
0$
#619000
b100 "
b100 '
b100 )
1&
1$
#620000
0&
0$
#621000
1#
b101 "
b101 '
b101 )
1&
1$
#622000
0&
0$
#623000
b110 "
b110 '
b110 )
1&
1$
#624000
0&
0$
#625000
1!
b111 "
b111 '
b111 )
1&
1$
#626000
0&
0$
#627000
0!
b0 "
b0 '
b0 )
1&
1$
#628000
0&
0$
#629000
0#
b1 "
b1 '
b1 )
1&
1$
#630000
0&
0$
#631000
b10 "
b10 '
b10 )
1&
1$
#632000
0&
0$
#633000
b11 "
b11 '
b11 )
1&
1$
#634000
0&
0$
#635000
b100 "
b100 '
b100 )
1&
1$
#636000
0&
0$
#637000
1#
b101 "
b101 '
b101 )
1&
1$
#638000
0&
0$
#639000
b110 "
b110 '
b110 )
1&
1$
#640000
0&
0$
#641000
1!
b111 "
b111 '
b111 )
1&
1$
#642000
0&
0$
#643000
0!
b0 "
b0 '
b0 )
1&
1$
#644000
0&
0$
#645000
0#
b1 "
b1 '
b1 )
1&
1$
#646000
0&
0$
#647000
b10 "
b10 '
b10 )
1&
1$
#648000
0&
0$
#649000
b11 "
b11 '
b11 )
1&
1$
#650000
0&
0$
#651000
b100 "
b100 '
b100 )
1&
1$
#652000
0&
0$
#653000
1#
b101 "
b101 '
b101 )
1&
1$
#654000
0&
0$
#655000
b110 "
b110 '
b110 )
1&
1$
#656000
0&
0$
#657000
1!
b111 "
b111 '
b111 )
1&
1$
#658000
0&
0$
#659000
0!
b0 "
b0 '
b0 )
1&
1$
#660000
0&
0$
#661000
0#
b1 "
b1 '
b1 )
1&
1$
#662000
0&
0$
#663000
b10 "
b10 '
b10 )
1&
1$
#664000
0&
0$
#665000
b11 "
b11 '
b11 )
1&
1$
#666000
0&
0$
#667000
b100 "
b100 '
b100 )
1&
1$
#668000
0&
0$
#669000
1#
b101 "
b101 '
b101 )
1&
1$
#670000
0&
0$
#671000
b110 "
b110 '
b110 )
1&
1$
#672000
0&
0$
#673000
1!
b111 "
b111 '
b111 )
1&
1$
#674000
0&
0$
#675000
0!
b0 "
b0 '
b0 )
1&
1$
#676000
0&
0$
#677000
0#
b1 "
b1 '
b1 )
1&
1$
#678000
0&
0$
#679000
b10 "
b10 '
b10 )
1&
1$
#680000
0&
0$
#681000
b11 "
b11 '
b11 )
1&
1$
#682000
0&
0$
#683000
b100 "
b100 '
b100 )
1&
1$
#684000
0&
0$
#685000
1#
b101 "
b101 '
b101 )
1&
1$
#686000
0&
0$
#687000
b110 "
b110 '
b110 )
1&
1$
#688000
0&
0$
#689000
1!
b111 "
b111 '
b111 )
1&
1$
#690000
0&
0$
#691000
0!
b0 "
b0 '
b0 )
1&
1$
#692000
0&
0$
#693000
0#
b1 "
b1 '
b1 )
1&
1$
#694000
0&
0$
#695000
b10 "
b10 '
b10 )
1&
1$
#696000
0&
0$
#697000
b11 "
b11 '
b11 )
1&
1$
#698000
0&
0$
#699000
b100 "
b100 '
b100 )
1&
1$
#700000
0&
0$
#701000
1#
b101 "
b101 '
b101 )
1&
1$
#702000
0&
0$
#703000
b110 "
b110 '
b110 )
1&
1$
#704000
0&
0$
#705000
1!
b111 "
b111 '
b111 )
1&
1$
#706000
0&
0$
#707000
0!
b0 "
b0 '
b0 )
1&
1$
#708000
0&
0$
#709000
0#
b1 "
b1 '
b1 )
1&
1$
#710000
0&
0$
#711000
b10 "
b10 '
b10 )
1&
1$
#712000
0&
0$
#713000
b11 "
b11 '
b11 )
1&
1$
#714000
0&
0$
#715000
b100 "
b100 '
b100 )
1&
1$
#716000
0&
0$
#717000
1#
b101 "
b101 '
b101 )
1&
1$
#718000
0&
0$
#719000
b110 "
b110 '
b110 )
1&
1$
#720000
0&
0$
