adder/adder_4b.v
    //////////////////////////////////////////////////////////////////////
    // Module Name: adder_4b.v
    // Description: 4-bit adder
    // Designer: Barney Peng
    // Date: 04/13/2024
    //////////////////////////////////////////////////////////////////////



    module adder_4b (

        input [WIDTH-1:0] i_a,
        input [WIDTH-1:0] i_b,
        output [WIDTH:0] o_sum
    
    );
        parameter WIDTH = 4; 
        
        reg [WIDTH:0] sum_p;
        reg [WIDTH-1:0] cout;
        reg [WIDTH-1:0] cin;
  

    //

    /*
    always @(*) begin
        sum_p = i_a^i_b^cin;
        cout = (i_a&i_b)|(i_b&cin)|(i_a&cin);
        cin = cout;
    end*/


    always @(*)
        begin
    // [0] //Half Adder for the first bit (bit [0])
            sum_p[0] = i_a[0]^i_b[0];
            cout[0] = (i_a[0]&i_b[0]);
    // [1] //Full Adder for the rest of the bits (bit [1] to bit [3])
            sum_p[1] = i_a[1]^i_b[1]^cout[0];        // sum_p = ((~i_a)*(~i_b)*cout)+((~i_a)*i_b*(~cout))+(i_a*(~i_b)*(~cout))+(i_a*(i_b)*(cout))
            cout[1] = (i_a[1]&i_b[1])|(i_b[1]&cout[0])|(i_a[1]&cout[0]); // cout = (i_a)(i_b)+(i_a)(cout)+(i_b)(cout)
    // [2]
            sum_p[2] = i_a[2]^i_b[2]^cout[1];
            cout[2] = (i_a[2]&i_b[2])|(i_b[2]&cout[1])|(i_a[2]&cout[1]);
    // [3]
            sum_p[3] = i_a[3]^i_b[3]^cout[2];
            cout[3] = (i_a[3]&i_b[3])|(i_b[3]&cout[2])|(i_a[3]&cout[2]);
    // [4]  
            sum_p[4] = cout[3];
        end


    assign o_sum = sum_p;

    endmodule//adder_4b

adder/adder_4b_tb.v
//////////////////////////////////////////////////////////////////////
// Module Name: adder_4b_tb.v
// Description: 4-bit adder testbench
// Designer: Barney Peng
// Date: 04/13/2024
//////////////////////////////////////////////////////////////////////

module adder_4b_tb;

    parameter WIDTH = 4;

    reg [WIDTH-1:0] i_a;
    reg [WIDTH-1:0] i_b;
    wire [WIDTH:0] o_sum;


    initial begin
        i_a <= 4'b0000;
        i_b <= 4'b0000;
    
        #20; // Delay to allow simulation to progress


        #10; i_a <= 4'b0001;
        #10; i_b <= 4'b0001;
    
        
        #10; i_a <= 4'b0000;
        #10; i_b <= 4'b0001;
    

        #10; i_a <= 4'b1111;
        #10; i_b <= 4'b1111;


        #10; i_a <= 4'b0000;
        #10; i_b <= 4'b0000;

        #1000;
        $finish;
    end

    initial begin
        $monitor("At time %t, o_sum = %h (%0d)", $time, o_sum, o_sum);
    end

    initial begin
        $dumpfile("adder_4b.vcd");
        $dumpvars(0, adder_4b_tb);
    end
    

adder_4b u_adder_4b (
 
    .i_a(i_a),
    .i_b(i_b),
    .o_sum(o_sum)

);

endmodule

adder/adder_4b.vcd
$date
	Sun Apr 14 14:34:46 2024
$end
$version
	Icarus Verilog
$end
$timescale
	1s
$end
$scope module adder_4b_tb $end
$var wire 5 ! o_sum [4:0] $end
$var parameter 32 " WIDTH $end
$var reg 4 # i_a [3:0] $end
$var reg 4 $ i_b [3:0] $end
$scope module u_adder_4b $end
$var wire 4 % i_a [3:0] $end
$var wire 4 & i_b [3:0] $end
$var wire 5 ' o_sum [4:0] $end
$var parameter 32 ( WIDTH $end
$var reg 4 ) cout [3:0] $end
$var reg 5 * sum_p [4:0] $end
$upscope $end
$upscope $end
$enddefinitions $end
$comment Show the parameter values. $end
$dumpall
b100 (
b100 "
$end
#0
$dumpvars
b0 *
b0 )
b0 '
b0 &
b0 %
b0 $
b0 #
b0 !
$end
#30
b1 !
b1 '
b1 *
b1 #
b1 %
#40
b1 )
b10 !
b10 '
b10 *
b1 $
b1 &
#50
b0 )
b1 !
b1 '
b1 *
b0 #
b0 %
#70
b1111 )
b10000 !
b10000 '
b10000 *
b1111 #
b1111 %
#80
b11110 !
b11110 '
b11110 *
b1111 $
b1111 &
#90
b0 )
b1111 !
b1111 '
b1111 *
b0 #
b0 %
#100
b0 !
b0 '
b0 *
b0 $
b0 &
