adder/adder_12in_1b.v
    //////////////////////////////////////////////////////////////////////
    // Module Name: adder_12in_1b.v
    // Description: 4-bit adder
    // Designer: Barney Peng
    // Date: 04/13/2024
    //////////////////////////////////////////////////////////////////////



    module adder_12in_1b (

        input [WIDTH_in-1:0] i_a,

        output [WIDTH_out:0] o_sum
    
    );
        parameter WIDTH_in = 12; 
        parameter WIDTH_out = 4;
        

        reg [WIDTH_out:0] sum_p;
        //reg [WIDTH_out:0] cout;
        //reg [WIDTH_in:0] cin;
  


always @(*)
    begin
        sum_p = i_a[0] + i_a[1] + i_a[2] + i_a[3] + i_a[4] + i_a[5] + i_a[6] + i_a[7] + i_a[8] + i_a[9] + i_a[10] + i_a[11];



    end

    assign o_sum = sum_p;

    endmodule//adder_12in_1b

adder/adder_12in_1b_tb.v
//////////////////////////////////////////////////////////////////////
// Module Name: adder_12in_1b_tb.v
// Description: 4-bit adder testbench
// Designer: Barney Peng
// Date: 04/13/2024
//////////////////////////////////////////////////////////////////////

module adder_12in_1b_tb;

    parameter WIDTH_in = 12; 
    parameter WIDTH_out = 4;

    reg [WIDTH_in -1 :0] i_a;
    wire [WIDTH_out : 0] o_sum;


    initial begin
        i_a <= 4'b0000;

        #20; // Delay to allow simulation to progress


        #10; i_a[0] <= 1'b1;
        #10; i_a[1] <= 1'b1;
        #10; i_a[2] <= 1'b1;
        #10; i_a[3] <= 1'b1;
        #10; i_a[4] <= 1'b1;
        #10; i_a[5] <= 1'b1;
        #10; i_a[6] <= 1'b1;
        #10; i_a[7] <= 1'b1;
        #10; i_a[8] <= 1'b1;
        #10; i_a[9] <= 1'b1;
        #10; i_a[10] <= 1'b1;
        #10; i_a[11] <= 1'b1;

        #10; i_a[0] <= 1'b0;
        #10; i_a[1] <= 1'b0;
        #10; i_a[2] <= 1'b0;
        #10; i_a[3] <= 1'b0;
        #10; i_a[4] <= 1'b0;
        #10; i_a[5] <= 1'b0;
        #10; i_a[6] <= 1'b0;
        #10; i_a[7] <= 1'b0;
        #10; i_a[8] <= 1'b0;
        #10; i_a[9] <= 1'b0;
        #10; i_a[10] <= 1'b0;
        #10; i_a[11] <= 1'b0;

        #10; i_a[10] <= 1'b1;
        #10; i_a[8] <= 1'b1;
        #10; i_a[6] <= 1'b1;
        #10; i_a[4] <= 1'b1;
        #10; i_a[2] <= 1'b1;
        #10; i_a[0] <= 1'b1;

        #10; i_a[1] <= 1'b1;
        #10; i_a[3] <= 1'b1;
        #10; i_a[5] <= 1'b1;
        #10; i_a[7] <= 1'b1;
        #10; i_a[9] <= 1'b1;
        #10; i_a[11] <= 1'b1;


    



        #1000;
        $finish;
    end

    initial begin
        $monitor("At time %t, o_sum = %h (%0d)", $time, o_sum, o_sum);
    end

    initial begin
        $dumpfile("adder_12in_1b.vcd");
        $dumpvars(0, adder_12in_1b_tb);
    end
    

adder_12in_1b u_adder_12in_1b (
 
    .i_a(i_a),

    .o_sum(o_sum)

);

endmodule

adder/adder_12in_1b.vcd
$date
	Sun Apr 14 14:39:52 2024
$end
$version
	Icarus Verilog
$end
$timescale
	1s
$end
$scope module adder_12in_1b_tb $end
$var wire 5 ! o_sum [4:0] $end
$var parameter 32 " WIDTH_in $end
$var parameter 32 # WIDTH_out $end
$var reg 12 $ i_a [11:0] $end
$scope module u_adder_12in_1b $end
$var wire 12 % i_a [11:0] $end
$var wire 5 & o_sum [4:0] $end
$var parameter 32 ' WIDTH_in $end
$var parameter 32 ( WIDTH_out $end
$var reg 5 ) sum_p [4:0] $end
$upscope $end
$upscope $end
$enddefinitions $end
$comment Show the parameter values. $end
$dumpall
b100 (
b1100 '
b100 #
b1100 "
$end
#0
$dumpvars
b0 )
b0 &
b0 %
b0 $
b0 !
$end
#30
b1 !
b1 &
b1 )
b1 $
b1 %
#40
b10 !
b10 &
b10 )
b11 $
b11 %
#50
b11 !
b11 &
b11 )
b111 $
b111 %
#60
b100 !
b100 &
b100 )
b1111 $
b1111 %
#70
b101 !
b101 &
b101 )
b11111 $
b11111 %
#80
b110 !
b110 &
b110 )
b111111 $
b111111 %
#90
b111 !
b111 &
b111 )
b1111111 $
b1111111 %
#100
b1000 !
b1000 &
b1000 )
b11111111 $
b11111111 %
#110
b1001 !
b1001 &
b1001 )
b111111111 $
b111111111 %
#120
b1010 !
b1010 &
b1010 )
b1111111111 $
b1111111111 %
#130
b1011 !
b1011 &
b1011 )
b11111111111 $
b11111111111 %
#140
b1100 !
b1100 &
b1100 )
b111111111111 $
b111111111111 %
#150
b1011 !
b1011 &
b1011 )
b111111111110 $
b111111111110 %
#160
b1010 !
b1010 &
b1010 )
b111111111100 $
b111111111100 %
#170
b1001 !
b1001 &
b1001 )
b111111111000 $
b111111111000 %
#180
b1000 !
b1000 &
b1000 )
b111111110000 $
b111111110000 %
#190
b111 !
b111 &
b111 )
b111111100000 $
b111111100000 %
#200
b110 !
b110 &
b110 )
b111111000000 $
b111111000000 %
#210
b101 !
b101 &
b101 )
b111110000000 $
b111110000000 %
#220
b100 !
b100 &
b100 )
b111100000000 $
b111100000000 %
#230
b11 !
b11 &
b11 )
b111000000000 $
b111000000000 %
#240
b10 !
b10 &
b10 )
b110000000000 $
b110000000000 %
#250
b1 !
b1 &
b1 )
b100000000000 $
b100000000000 %
#260
b0 !
b0 &
b0 )
b0 $
b0 %
#270
b1 !
b1 &
b1 )
b10000000000 $
b10000000000 %
#280
b10 !
b10 &
b10 )
b10100000000 $
b10100000000 %
#290
b11 !
b11 &
b11 )
b10101000000 $
b10101000000 %
#300
b100 !
b100 &
b100 )
b10101010000 $
b10101010000 %
#310
b101 !
b101 &
b101 )
b10101010100 $
b10101010100 %
#320
b110 !
b110 &
b110 )
b10101010101 $
b10101010101 %
#330
b111 !
b111 &
b111 )
b10101010111 $
b10101010111 %
#340
b1000 !
b1000 &
b1000 )
b10101011111 $
b10101011111 %
#350
b1001 !
b1001 &
b1001 )
b10101111111 $
b10101111111 %
#360
b1010 !
b1010 &
b1010 )
b10111111111 $
b10111111111 %
#370
b1011 !
b1011 &
b1011 )
b11111111111 $
b11111111111 %
#380
b1100 !
b1100 &
b1100 )
b111111111111 $
b111111111111 %
