counter/counterCase02.v
//////////////////////////////////////////////////////////////////////
// Module Name: counterCase02.v
// Description: Counter with clock gating and counter valid control
// Designer: Barney Peng
// Date: 03/18/2024
//////////////////////////////////////////////////////////////////////

//module counter #(parameter WIDTH (8) /* 8 bit counter*/)(
module counterCase02 (
  input clk,
  input resetn,
  input i_clk_en,           // Clock and reset and enable inputs
  input i_count_valid,
  output o_count_end, 		      // counter reaches max value
  output wire [WIDTH-1 : 0] o_count   // Output of the counter(remember that 8-bit: [7:0](7 to 0))
);
//Reference: https://youtu.be/5Kync4z5VOw?si=u34tsfena2Eo7J3K

	parameter WIDTH = 8; /* 8 bit counter*/

	reg [WIDTH-1 : 0] o_count_p;
	wire clk_gate;		// gated clock
	
	assign clk_gate = clk & i_clk_en;

	always @(negedge resetn or posedge clk_gate)       // At every positive edge of the clock or negative edge of restn
		begin
			if  (~resetn)
		 		o_count_p <= 8'h0;		 // If reset is asserted, set the counter to 0
			else if(i_count_valid)
				o_count_p <=  o_count_p + 1;         // Increment the counter by 1
			else
				o_count_p <=  o_count_p;      // Otherwise, deassign the output
		end

	assign o_count_end = (o_count == 8'd255);
	assign o_count = o_count_p;


endmodule // counter

counter/counterCase02_tb.v
`timescale 1ns / 1ps //set the timescale for the module
//////////////////////////////////////////////////////////////////////
// Module Name: counterCase02_tb.v
// Description: Counter with clock gating and counter valid control
// Designer: Barney Peng
// Date: 03/18/2024
//////////////////////////////////////////////////////////////////////

module counterCase02_tb;
//Reference: https://youtu.be/5Kync4z5VOw?si=u34tsfena2Eo7J3K

/* Make a reset that pulse once. */
reg resetn;
reg i_clk_en; //give initial values to the signals
reg i_count_valid; //give initial values to the signals
wire  o_count_end;
wire [7:0] o_count;

initial begin
    resetn = 0;
    #20   resetn = 1;
    #4000 resetn = 1;
    $finish;
end

// free running clock clk
reg clk = 0;
always #1 clk = !clk;

initial begin
    $monitor("At time %t, o_count = %h (%0d)", $time, o_count, o_count);
end

initial begin
          i_clk_en = 0;
    #100  i_clk_en = 1; // gated the clock the counter after some delay
    #1500 i_clk_en = 0; // gated the clock the counter after some cycles
end

initial begin
         i_count_valid = 0;  
    #250 i_count_valid = 1; // valid the counter after some delay
    #100 i_count_valid = 0; // valid the counter after some delay
    #40  i_count_valid = 1; // valid the counter after some delay
    #200 i_count_valid = 0; // valid the counter after some delay
    #40  i_count_valid = 1; // valid the counter after some delay
    #80  i_count_valid = 0; // valid the counter after some delay
    #10  i_count_valid = 1; // valid the counter after some delay
    #400 i_count_valid = 0; // valid the counter after some delay
    #50  i_count_valid = 1; // valid the counter after some delay
    #800 i_count_valid = 0; // valid the counter after some delay
end

initial begin
    $dumpfile("counterCase02.vcd");
    $dumpvars(0,counterCase02_tb);
end

counterCase02 u_counterCase02 (
    .clk(clk),
    .resetn(resetn),
    .i_clk_en(i_clk_en),
    .i_count_valid(i_count_valid),
    .o_count_end(o_count_end),
    .o_count(o_count)
);

endmodule

counter/counterCase02.vcd
$date
	Tue Mar 19 00:25:55 2024
$end
$version
	Icarus Verilog
$end
$timescale
	1ps
$end
$scope module counterCase02_tb $end
$var wire 1 ! o_count_end $end
$var wire 8 " o_count [7:0] $end
$var reg 1 # clk $end
$var reg 1 $ i_clk_en $end
$var reg 1 % i_count_valid $end
$var reg 1 & resetn $end
$scope module u_counterCase02 $end
$var wire 1 # clk $end
$var wire 1 ' clk_gate $end
$var wire 1 $ i_clk_en $end
$var wire 1 % i_count_valid $end
$var wire 1 & resetn $end
$var wire 1 ! o_count_end $end
$var wire 8 ( o_count [7:0] $end
$var parameter 32 ) WIDTH $end
$var reg 8 * o_count_p [7:0] $end
$upscope $end
$upscope $end
$enddefinitions $end
$comment Show the parameter values. $end
$dumpall
b1000 )
$end
#0
$dumpvars
b0 *
b0 (
0'
0&
0%
0$
0#
b0 "
0!
$end
#1000
1#
#2000
0#
#3000
1#
#4000
0#
#5000
1#
#6000
0#
#7000
1#
#8000
0#
#9000
1#
#10000
0#
#11000
1#
#12000
0#
#13000
1#
#14000
0#
#15000
1#
#16000
0#
#17000
1#
#18000
0#
#19000
1#
#20000
0#
1&
#21000
1#
#22000
0#
#23000
1#
#24000
0#
#25000
1#
#26000
0#
#27000
1#
#28000
0#
#29000
1#
#30000
0#
#31000
1#
#32000
0#
#33000
1#
#34000
0#
#35000
1#
#36000
0#
#37000
1#
#38000
0#
#39000
1#
#40000
0#
#41000
1#
#42000
0#
#43000
1#
#44000
0#
#45000
1#
#46000
0#
#47000
1#
#48000
0#
#49000
1#
#50000
0#
#51000
1#
#52000
0#
#53000
1#
#54000
0#
#55000
1#
#56000
0#
#57000
1#
#58000
0#
#59000
1#
#60000
0#
#61000
1#
#62000
0#
#63000
1#
#64000
0#
#65000
1#
#66000
0#
#67000
1#
#68000
0#
#69000
1#
#70000
0#
#71000
1#
#72000
0#
#73000
1#
#74000
0#
#75000
1#
#76000
0#
#77000
1#
#78000
0#
#79000
1#
#80000
0#
#81000
1#
#82000
0#
#83000
1#
#84000
0#
#85000
1#
#86000
0#
#87000
1#
#88000
0#
#89000
1#
#90000
0#
#91000
1#
#92000
0#
#93000
1#
#94000
0#
#95000
1#
#96000
0#
#97000
1#
#98000
0#
#99000
1#
#100000
0#
1$
#101000
1'
1#
#102000
0'
0#
#103000
1'
1#
#104000
0'
0#
#105000
1'
1#
#106000
0'
0#
#107000
1'
1#
#108000
0'
0#
#109000
1'
1#
#110000
0'
0#
#111000
1'
1#
#112000
0'
0#
#113000
1'
1#
#114000
0'
0#
#115000
1'
1#
#116000
0'
0#
#117000
1'
1#
#118000
0'
0#
#119000
1'
1#
#120000
0'
0#
#121000
1'
1#
#122000
0'
0#
#123000
1'
1#
#124000
0'
0#
#125000
1'
1#
#126000
0'
0#
#127000
1'
1#
#128000
0'
0#
#129000
1'
1#
#130000
0'
0#
#131000
1'
1#
#132000
0'
0#
#133000
1'
1#
#134000
0'
0#
#135000
1'
1#
#136000
0'
0#
#137000
1'
1#
#138000
0'
0#
#139000
1'
1#
#140000
0'
0#
#141000
1'
1#
#142000
0'
0#
#143000
1'
1#
#144000
0'
0#
#145000
1'
1#
#146000
0'
0#
#147000
1'
1#
#148000
0'
0#
#149000
1'
1#
#150000
0'
0#
#151000
1'
1#
#152000
0'
0#
#153000
1'
1#
#154000
0'
0#
#155000
1'
1#
#156000
0'
0#
#157000
1'
1#
#158000
0'
0#
#159000
1'
1#
#160000
0'
0#
#161000
1'
1#
#162000
0'
0#
#163000
1'
1#
#164000
0'
0#
#165000
1'
1#
#166000
0'
0#
#167000
1'
1#
#168000
0'
0#
#169000
1'
1#
#170000
0'
0#
#171000
1'
1#
#172000
0'
0#
#173000
1'
1#
#174000
0'
0#
#175000
1'
1#
#176000
0'
0#
#177000
1'
1#
#178000
0'
0#
#179000
1'
1#
#180000
0'
0#
#181000
1'
1#
#182000
0'
0#
#183000
1'
1#
#184000
0'
0#
#185000
1'
1#
#186000
0'
0#
#187000
1'
1#
#188000
0'
0#
#189000
1'
1#
#190000
0'
0#
#191000
1'
1#
#192000
0'
0#
#193000
1'
1#
#194000
0'
0#
#195000
1'
1#
#196000
0'
0#
#197000
1'
1#
#198000
0'
0#
#199000
1'
1#
#200000
0'
0#
#201000
1'
1#
#202000
0'
0#
#203000
1'
1#
#204000
0'
0#
#205000
1'
1#
#206000
0'
0#
#207000
1'
1#
#208000
0'
0#
#209000
1'
1#
#210000
0'
0#
#211000
1'
1#
#212000
0'
0#
#213000
1'
1#
#214000
0'
0#
#215000
1'
1#
#216000
0'
0#
#217000
1'
1#
#218000
0'
0#
#219000
1'
1#
#220000
0'
0#
#221000
1'
1#
#222000
0'
0#
#223000
1'
1#
#224000
0'
0#
#225000
1'
1#
#226000
0'
0#
#227000
1'
1#
#228000
0'
0#
#229000
1'
1#
#230000
0'
0#
#231000
1'
1#
#232000
0'
0#
#233000
1'
1#
#234000
0'
0#
#235000
1'
1#
#236000
0'
0#
#237000
1'
1#
#238000
0'
0#
#239000
1'
1#
#240000
0'
0#
#241000
1'
1#
#242000
0'
0#
#243000
1'
1#
#244000
0'
0#
#245000
1'
1#
#246000
0'
0#
#247000
1'
1#
#248000
0'
0#
#249000
1'
1#
#250000
0'
0#
1%
#251000
b1 "
b1 (
b1 *
1'
1#
#252000
0'
0#
#253000
b10 "
b10 (
b10 *
1'
1#
#254000
0'
0#
#255000
b11 "
b11 (
b11 *
1'
1#
#256000
0'
0#
#257000
b100 "
b100 (
b100 *
1'
1#
#258000
0'
0#
#259000
b101 "
b101 (
b101 *
1'
1#
#260000
0'
0#
#261000
b110 "
b110 (
b110 *
1'
1#
#262000
0'
0#
#263000
b111 "
b111 (
b111 *
1'
1#
#264000
0'
0#
#265000
b1000 "
b1000 (
b1000 *
1'
1#
#266000
0'
0#
#267000
b1001 "
b1001 (
b1001 *
1'
1#
#268000
0'
0#
#269000
b1010 "
b1010 (
b1010 *
1'
1#
#270000
0'
0#
#271000
b1011 "
b1011 (
b1011 *
1'
1#
#272000
0'
0#
#273000
b1100 "
b1100 (
b1100 *
1'
1#
#274000
0'
0#
#275000
b1101 "
b1101 (
b1101 *
1'
1#
#276000
0'
0#
#277000
b1110 "
b1110 (
b1110 *
1'
1#
#278000
0'
0#
#279000
b1111 "
b1111 (
b1111 *
1'
1#
#280000
0'
0#
#281000
b10000 "
b10000 (
b10000 *
1'
1#
#282000
0'
0#
#283000
b10001 "
b10001 (
b10001 *
1'
1#
#284000
0'
0#
#285000
b10010 "
b10010 (
b10010 *
1'
1#
#286000
0'
0#
#287000
b10011 "
b10011 (
b10011 *
1'
1#
#288000
0'
0#
#289000
b10100 "
b10100 (
b10100 *
1'
1#
#290000
0'
0#
#291000
b10101 "
b10101 (
b10101 *
1'
1#
#292000
0'
0#
#293000
b10110 "
b10110 (
b10110 *
1'
1#
#294000
0'
0#
#295000
b10111 "
b10111 (
b10111 *
1'
1#
#296000
0'
0#
#297000
b11000 "
b11000 (
b11000 *
1'
1#
#298000
0'
0#
#299000
b11001 "
b11001 (
b11001 *
1'
1#
#300000
0'
0#
#301000
b11010 "
b11010 (
b11010 *
1'
1#
#302000
0'
0#
#303000
b11011 "
b11011 (
b11011 *
1'
1#
#304000
0'
0#
#305000
b11100 "
b11100 (
b11100 *
1'
1#
#306000
0'
0#
#307000
b11101 "
b11101 (
b11101 *
1'
1#
#308000
0'
0#
#309000
b11110 "
b11110 (
b11110 *
1'
1#
#310000
0'
0#
#311000
b11111 "
b11111 (
b11111 *
1'
1#
#312000
0'
0#
#313000
b100000 "
b100000 (
b100000 *
1'
1#
#314000
0'
0#
#315000
b100001 "
b100001 (
b100001 *
1'
1#
#316000
0'
0#
#317000
b100010 "
b100010 (
b100010 *
1'
1#
#318000
0'
0#
#319000
b100011 "
b100011 (
b100011 *
1'
1#
#320000
0'
0#
#321000
b100100 "
b100100 (
b100100 *
1'
1#
#322000
0'
0#
#323000
b100101 "
b100101 (
b100101 *
1'
1#
#324000
0'
0#
#325000
b100110 "
b100110 (
b100110 *
1'
1#
#326000
0'
0#
#327000
b100111 "
b100111 (
b100111 *
1'
1#
#328000
0'
0#
#329000
b101000 "
b101000 (
b101000 *
1'
1#
#330000
0'
0#
#331000
b101001 "
b101001 (
b101001 *
1'
1#
#332000
0'
0#
#333000
b101010 "
b101010 (
b101010 *
1'
1#
#334000
0'
0#
#335000
b101011 "
b101011 (
b101011 *
1'
1#
#336000
0'
0#
#337000
b101100 "
b101100 (
b101100 *
1'
1#
#338000
0'
0#
#339000
b101101 "
b101101 (
b101101 *
1'
1#
#340000
0'
0#
#341000
b101110 "
b101110 (
b101110 *
1'
1#
#342000
0'
0#
#343000
b101111 "
b101111 (
b101111 *
1'
1#
#344000
0'
0#
#345000
b110000 "
b110000 (
b110000 *
1'
1#
#346000
0'
0#
#347000
b110001 "
b110001 (
b110001 *
1'
1#
#348000
0'
0#
#349000
b110010 "
b110010 (
b110010 *
1'
1#
#350000
0'
0#
0%
#351000
1'
1#
#352000
0'
0#
#353000
1'
1#
#354000
0'
0#
#355000
1'
1#
#356000
0'
0#
#357000
1'
1#
#358000
0'
0#
#359000
1'
1#
#360000
0'
0#
#361000
1'
1#
#362000
0'
0#
#363000
1'
1#
#364000
0'
0#
#365000
1'
1#
#366000
0'
0#
#367000
1'
1#
#368000
0'
0#
#369000
1'
1#
#370000
0'
0#
#371000
1'
1#
#372000
0'
0#
#373000
1'
1#
#374000
0'
0#
#375000
1'
1#
#376000
0'
0#
#377000
1'
1#
#378000
0'
0#
#379000
1'
1#
#380000
0'
0#
#381000
1'
1#
#382000
0'
0#
#383000
1'
1#
#384000
0'
0#
#385000
1'
1#
#386000
0'
0#
#387000
1'
1#
#388000
0'
0#
#389000
1'
1#
#390000
0'
0#
1%
#391000
b110011 "
b110011 (
b110011 *
1'
1#
#392000
0'
0#
#393000
b110100 "
b110100 (
b110100 *
1'
1#
#394000
0'
0#
#395000
b110101 "
b110101 (
b110101 *
1'
1#
#396000
0'
0#
#397000
b110110 "
b110110 (
b110110 *
1'
1#
#398000
0'
0#
#399000
b110111 "
b110111 (
b110111 *
1'
1#
#400000
0'
0#
#401000
b111000 "
b111000 (
b111000 *
1'
1#
#402000
0'
0#
#403000
b111001 "
b111001 (
b111001 *
1'
1#
#404000
0'
0#
#405000
b111010 "
b111010 (
b111010 *
1'
1#
#406000
0'
0#
#407000
b111011 "
b111011 (
b111011 *
1'
1#
#408000
0'
0#
#409000
b111100 "
b111100 (
b111100 *
1'
1#
#410000
0'
0#
#411000
b111101 "
b111101 (
b111101 *
1'
1#
#412000
0'
0#
#413000
b111110 "
b111110 (
b111110 *
1'
1#
#414000
0'
0#
#415000
b111111 "
b111111 (
b111111 *
1'
1#
#416000
0'
0#
#417000
b1000000 "
b1000000 (
b1000000 *
1'
1#
#418000
0'
0#
#419000
b1000001 "
b1000001 (
b1000001 *
1'
1#
#420000
0'
0#
#421000
b1000010 "
b1000010 (
b1000010 *
1'
1#
#422000
0'
0#
#423000
b1000011 "
b1000011 (
b1000011 *
1'
1#
#424000
0'
0#
#425000
b1000100 "
b1000100 (
b1000100 *
1'
1#
#426000
0'
0#
#427000
b1000101 "
b1000101 (
b1000101 *
1'
1#
#428000
0'
0#
#429000
b1000110 "
b1000110 (
b1000110 *
1'
1#
#430000
0'
0#
#431000
b1000111 "
b1000111 (
b1000111 *
1'
1#
#432000
0'
0#
#433000
b1001000 "
b1001000 (
b1001000 *
1'
1#
#434000
0'
0#
#435000
b1001001 "
b1001001 (
b1001001 *
1'
1#
#436000
0'
0#
#437000
b1001010 "
b1001010 (
b1001010 *
1'
1#
#438000
0'
0#
#439000
b1001011 "
b1001011 (
b1001011 *
1'
1#
#440000
0'
0#
#441000
b1001100 "
b1001100 (
b1001100 *
1'
1#
#442000
0'
0#
#443000
b1001101 "
b1001101 (
b1001101 *
1'
1#
#444000
0'
0#
#445000
b1001110 "
b1001110 (
b1001110 *
1'
1#
#446000
0'
0#
#447000
b1001111 "
b1001111 (
b1001111 *
1'
1#
#448000
0'
0#
#449000
b1010000 "
b1010000 (
b1010000 *
1'
1#
#450000
0'
0#
#451000
b1010001 "
b1010001 (
b1010001 *
1'
1#
#452000
0'
0#
#453000
b1010010 "
b1010010 (
b1010010 *
1'
1#
#454000
0'
0#
#455000
b1010011 "
b1010011 (
b1010011 *
1'
1#
#456000
0'
0#
#457000
b1010100 "
b1010100 (
b1010100 *
1'
1#
#458000
0'
0#
#459000
b1010101 "
b1010101 (
b1010101 *
1'
1#
#460000
0'
0#
#461000
b1010110 "
b1010110 (
b1010110 *
1'
1#
#462000
0'
0#
#463000
b1010111 "
b1010111 (
b1010111 *
1'
1#
#464000
0'
0#
#465000
b1011000 "
b1011000 (
b1011000 *
1'
1#
#466000
0'
0#
#467000
b1011001 "
b1011001 (
b1011001 *
1'
1#
#468000
0'
0#
#469000
b1011010 "
b1011010 (
b1011010 *
1'
1#
#470000
0'
0#
#471000
b1011011 "
b1011011 (
b1011011 *
1'
1#
#472000
0'
0#
#473000
b1011100 "
b1011100 (
b1011100 *
1'
1#
#474000
0'
0#
#475000
b1011101 "
b1011101 (
b1011101 *
1'
1#
#476000
0'
0#
#477000
b1011110 "
b1011110 (
b1011110 *
1'
1#
#478000
0'
0#
#479000
b1011111 "
b1011111 (
b1011111 *
1'
1#
#480000
0'
0#
#481000
b1100000 "
b1100000 (
b1100000 *
1'
1#
#482000
0'
0#
#483000
b1100001 "
b1100001 (
b1100001 *
1'
1#
#484000
0'
0#
#485000
b1100010 "
b1100010 (
b1100010 *
1'
1#
#486000
0'
0#
#487000
b1100011 "
b1100011 (
b1100011 *
1'
1#
#488000
0'
0#
#489000
b1100100 "
b1100100 (
b1100100 *
1'
1#
#490000
0'
0#
#491000
b1100101 "
b1100101 (
b1100101 *
1'
1#
#492000
0'
0#
#493000
b1100110 "
b1100110 (
b1100110 *
1'
1#
#494000
0'
0#
#495000
b1100111 "
b1100111 (
b1100111 *
1'
1#
#496000
0'
0#
#497000
b1101000 "
b1101000 (
b1101000 *
1'
1#
#498000
0'
0#
#499000
b1101001 "
b1101001 (
b1101001 *
1'
1#
#500000
0'
0#
#501000
b1101010 "
b1101010 (
b1101010 *
1'
1#
#502000
0'
0#
#503000
b1101011 "
b1101011 (
b1101011 *
1'
1#
#504000
0'
0#
#505000
b1101100 "
b1101100 (
b1101100 *
1'
1#
#506000
0'
0#
#507000
b1101101 "
b1101101 (
b1101101 *
1'
1#
#508000
0'
0#
#509000
b1101110 "
b1101110 (
b1101110 *
1'
1#
#510000
0'
0#
#511000
b1101111 "
b1101111 (
b1101111 *
1'
1#
#512000
0'
0#
#513000
b1110000 "
b1110000 (
b1110000 *
1'
1#
#514000
0'
0#
#515000
b1110001 "
b1110001 (
b1110001 *
1'
1#
#516000
0'
0#
#517000
b1110010 "
b1110010 (
b1110010 *
1'
1#
#518000
0'
0#
#519000
b1110011 "
b1110011 (
b1110011 *
1'
1#
#520000
0'
0#
#521000
b1110100 "
b1110100 (
b1110100 *
1'
1#
#522000
0'
0#
#523000
b1110101 "
b1110101 (
b1110101 *
1'
1#
#524000
0'
0#
#525000
b1110110 "
b1110110 (
b1110110 *
1'
1#
#526000
0'
0#
#527000
b1110111 "
b1110111 (
b1110111 *
1'
1#
#528000
0'
0#
#529000
b1111000 "
b1111000 (
b1111000 *
1'
1#
#530000
0'
0#
#531000
b1111001 "
b1111001 (
b1111001 *
1'
1#
#532000
0'
0#
#533000
b1111010 "
b1111010 (
b1111010 *
1'
1#
#534000
0'
0#
#535000
b1111011 "
b1111011 (
b1111011 *
1'
1#
#536000
0'
0#
#537000
b1111100 "
b1111100 (
b1111100 *
1'
1#
#538000
0'
0#
#539000
b1111101 "
b1111101 (
b1111101 *
1'
1#
#540000
0'
0#
#541000
b1111110 "
b1111110 (
b1111110 *
1'
1#
#542000
0'
0#
#543000
b1111111 "
b1111111 (
b1111111 *
1'
1#
#544000
0'
0#
#545000
b10000000 "
b10000000 (
b10000000 *
1'
1#
#546000
0'
0#
#547000
b10000001 "
b10000001 (
b10000001 *
1'
1#
#548000
0'
0#
#549000
b10000010 "
b10000010 (
b10000010 *
1'
1#
#550000
0'
0#
#551000
b10000011 "
b10000011 (
b10000011 *
1'
1#
#552000
0'
0#
#553000
b10000100 "
b10000100 (
b10000100 *
1'
1#
#554000
0'
0#
#555000
b10000101 "
b10000101 (
b10000101 *
1'
1#
#556000
0'
0#
#557000
b10000110 "
b10000110 (
b10000110 *
1'
1#
#558000
0'
0#
#559000
b10000111 "
b10000111 (
b10000111 *
1'
1#
#560000
0'
0#
#561000
b10001000 "
b10001000 (
b10001000 *
1'
1#
#562000
0'
0#
#563000
b10001001 "
b10001001 (
b10001001 *
1'
1#
#564000
0'
0#
#565000
b10001010 "
b10001010 (
b10001010 *
1'
1#
#566000
0'
0#
#567000
b10001011 "
b10001011 (
b10001011 *
1'
1#
#568000
0'
0#
#569000
b10001100 "
b10001100 (
b10001100 *
1'
1#
#570000
0'
0#
#571000
b10001101 "
b10001101 (
b10001101 *
1'
1#
#572000
0'
0#
#573000
b10001110 "
b10001110 (
b10001110 *
1'
1#
#574000
0'
0#
#575000
b10001111 "
b10001111 (
b10001111 *
1'
1#
#576000
0'
0#
#577000
b10010000 "
b10010000 (
b10010000 *
1'
1#
#578000
0'
0#
#579000
b10010001 "
b10010001 (
b10010001 *
1'
1#
#580000
0'
0#
#581000
b10010010 "
b10010010 (
b10010010 *
1'
1#
#582000
0'
0#
#583000
b10010011 "
b10010011 (
b10010011 *
1'
1#
#584000
0'
0#
#585000
b10010100 "
b10010100 (
b10010100 *
1'
1#
#586000
0'
0#
#587000
b10010101 "
b10010101 (
b10010101 *
1'
1#
#588000
0'
0#
#589000
b10010110 "
b10010110 (
b10010110 *
1'
1#
#590000
0'
0#
0%
#591000
1'
1#
#592000
0'
0#
#593000
1'
1#
#594000
0'
0#
#595000
1'
1#
#596000
0'
0#
#597000
1'
1#
#598000
0'
0#
#599000
1'
1#
#600000
0'
0#
#601000
1'
1#
#602000
0'
0#
#603000
1'
1#
#604000
0'
0#
#605000
1'
1#
#606000
0'
0#
#607000
1'
1#
#608000
0'
0#
#609000
1'
1#
#610000
0'
0#
#611000
1'
1#
#612000
0'
0#
#613000
1'
1#
#614000
0'
0#
#615000
1'
1#
#616000
0'
0#
#617000
1'
1#
#618000
0'
0#
#619000
1'
1#
#620000
0'
0#
#621000
1'
1#
#622000
0'
0#
#623000
1'
1#
#624000
0'
0#
#625000
1'
1#
#626000
0'
0#
#627000
1'
1#
#628000
0'
0#
#629000
1'
1#
#630000
0'
0#
1%
#631000
b10010111 "
b10010111 (
b10010111 *
1'
1#
#632000
0'
0#
#633000
b10011000 "
b10011000 (
b10011000 *
1'
1#
#634000
0'
0#
#635000
b10011001 "
b10011001 (
b10011001 *
1'
1#
#636000
0'
0#
#637000
b10011010 "
b10011010 (
b10011010 *
1'
1#
#638000
0'
0#
#639000
b10011011 "
b10011011 (
b10011011 *
1'
1#
#640000
0'
0#
#641000
b10011100 "
b10011100 (
b10011100 *
1'
1#
#642000
0'
0#
#643000
b10011101 "
b10011101 (
b10011101 *
1'
1#
#644000
0'
0#
#645000
b10011110 "
b10011110 (
b10011110 *
1'
1#
#646000
0'
0#
#647000
b10011111 "
b10011111 (
b10011111 *
1'
1#
#648000
0'
0#
#649000
b10100000 "
b10100000 (
b10100000 *
1'
1#
#650000
0'
0#
#651000
b10100001 "
b10100001 (
b10100001 *
1'
1#
#652000
0'
0#
#653000
b10100010 "
b10100010 (
b10100010 *
1'
1#
#654000
0'
0#
#655000
b10100011 "
b10100011 (
b10100011 *
1'
1#
#656000
0'
0#
#657000
b10100100 "
b10100100 (
b10100100 *
1'
1#
#658000
0'
0#
#659000
b10100101 "
b10100101 (
b10100101 *
1'
1#
#660000
0'
0#
#661000
b10100110 "
b10100110 (
b10100110 *
1'
1#
#662000
0'
0#
#663000
b10100111 "
b10100111 (
b10100111 *
1'
1#
#664000
0'
0#
#665000
b10101000 "
b10101000 (
b10101000 *
1'
1#
#666000
0'
0#
#667000
b10101001 "
b10101001 (
b10101001 *
1'
1#
#668000
0'
0#
#669000
b10101010 "
b10101010 (
b10101010 *
1'
1#
#670000
0'
0#
#671000
b10101011 "
b10101011 (
b10101011 *
1'
1#
#672000
0'
0#
#673000
b10101100 "
b10101100 (
b10101100 *
1'
1#
#674000
0'
0#
#675000
b10101101 "
b10101101 (
b10101101 *
1'
1#
#676000
0'
0#
#677000
b10101110 "
b10101110 (
b10101110 *
1'
1#
#678000
0'
0#
#679000
b10101111 "
b10101111 (
b10101111 *
1'
1#
#680000
0'
0#
#681000
b10110000 "
b10110000 (
b10110000 *
1'
1#
#682000
0'
0#
#683000
b10110001 "
b10110001 (
b10110001 *
1'
1#
#684000
0'
0#
#685000
b10110010 "
b10110010 (
b10110010 *
1'
1#
#686000
0'
0#
#687000
b10110011 "
b10110011 (
b10110011 *
1'
1#
#688000
0'
0#
#689000
b10110100 "
b10110100 (
b10110100 *
1'
1#
#690000
0'
0#
#691000
b10110101 "
b10110101 (
b10110101 *
1'
1#
#692000
0'
0#
#693000
b10110110 "
b10110110 (
b10110110 *
1'
1#
#694000
0'
0#
#695000
b10110111 "
b10110111 (
b10110111 *
1'
1#
#696000
0'
0#
#697000
b10111000 "
b10111000 (
b10111000 *
1'
1#
#698000
0'
0#
#699000
b10111001 "
b10111001 (
b10111001 *
1'
1#
#700000
0'
0#
#701000
b10111010 "
b10111010 (
b10111010 *
1'
1#
#702000
0'
0#
#703000
b10111011 "
b10111011 (
b10111011 *
1'
1#
#704000
0'
0#
#705000
b10111100 "
b10111100 (
b10111100 *
1'
1#
#706000
0'
0#
#707000
b10111101 "
b10111101 (
b10111101 *
1'
1#
#708000
0'
0#
#709000
b10111110 "
b10111110 (
b10111110 *
1'
1#
#710000
0'
0#
0%
#711000
1'
1#
#712000
0'
0#
#713000
1'
1#
#714000
0'
0#
#715000
1'
1#
#716000
0'
0#
#717000
1'
1#
#718000
0'
0#
#719000
1'
1#
#720000
0'
0#
1%
#721000
b10111111 "
b10111111 (
b10111111 *
1'
1#
#722000
0'
0#
#723000
b11000000 "
b11000000 (
b11000000 *
1'
1#
#724000
0'
0#
#725000
b11000001 "
b11000001 (
b11000001 *
1'
1#
#726000
0'
0#
#727000
b11000010 "
b11000010 (
b11000010 *
1'
1#
#728000
0'
0#
#729000
b11000011 "
b11000011 (
b11000011 *
1'
1#
#730000
0'
0#
#731000
b11000100 "
b11000100 (
b11000100 *
1'
1#
#732000
0'
0#
#733000
b11000101 "
b11000101 (
b11000101 *
1'
1#
#734000
0'
0#
#735000
b11000110 "
b11000110 (
b11000110 *
1'
1#
#736000
0'
0#
#737000
b11000111 "
b11000111 (
b11000111 *
1'
1#
#738000
0'
0#
#739000
b11001000 "
b11001000 (
b11001000 *
1'
1#
#740000
0'
0#
#741000
b11001001 "
b11001001 (
b11001001 *
1'
1#
#742000
0'
0#
#743000
b11001010 "
b11001010 (
b11001010 *
1'
1#
#744000
0'
0#
#745000
b11001011 "
b11001011 (
b11001011 *
1'
1#
#746000
0'
0#
#747000
b11001100 "
b11001100 (
b11001100 *
1'
1#
#748000
0'
0#
#749000
b11001101 "
b11001101 (
b11001101 *
1'
1#
#750000
0'
0#
#751000
b11001110 "
b11001110 (
b11001110 *
1'
1#
#752000
0'
0#
#753000
b11001111 "
b11001111 (
b11001111 *
1'
1#
#754000
0'
0#
#755000
b11010000 "
b11010000 (
b11010000 *
1'
1#
#756000
0'
0#
#757000
b11010001 "
b11010001 (
b11010001 *
1'
1#
#758000
0'
0#
#759000
b11010010 "
b11010010 (
b11010010 *
1'
1#
#760000
0'
0#
#761000
b11010011 "
b11010011 (
b11010011 *
1'
1#
#762000
0'
0#
#763000
b11010100 "
b11010100 (
b11010100 *
1'
1#
#764000
0'
0#
#765000
b11010101 "
b11010101 (
b11010101 *
1'
1#
#766000
0'
0#
#767000
b11010110 "
b11010110 (
b11010110 *
1'
1#
#768000
0'
0#
#769000
b11010111 "
b11010111 (
b11010111 *
1'
1#
#770000
0'
0#
#771000
b11011000 "
b11011000 (
b11011000 *
1'
1#
#772000
0'
0#
#773000
b11011001 "
b11011001 (
b11011001 *
1'
1#
#774000
0'
0#
#775000
b11011010 "
b11011010 (
b11011010 *
1'
1#
#776000
0'
0#
#777000
b11011011 "
b11011011 (
b11011011 *
1'
1#
#778000
0'
0#
#779000
b11011100 "
b11011100 (
b11011100 *
1'
1#
#780000
0'
0#
#781000
b11011101 "
b11011101 (
b11011101 *
1'
1#
#782000
0'
0#
#783000
b11011110 "
b11011110 (
b11011110 *
1'
1#
#784000
0'
0#
#785000
b11011111 "
b11011111 (
b11011111 *
1'
1#
#786000
0'
0#
#787000
b11100000 "
b11100000 (
b11100000 *
1'
1#
#788000
0'
0#
#789000
b11100001 "
b11100001 (
b11100001 *
1'
1#
#790000
0'
0#
#791000
b11100010 "
b11100010 (
b11100010 *
1'
1#
#792000
0'
0#
#793000
b11100011 "
b11100011 (
b11100011 *
1'
1#
#794000
0'
0#
#795000
b11100100 "
b11100100 (
b11100100 *
1'
1#
#796000
0'
0#
#797000
b11100101 "
b11100101 (
b11100101 *
1'
1#
#798000
0'
0#
#799000
b11100110 "
b11100110 (
b11100110 *
1'
1#
#800000
0'
0#
#801000
b11100111 "
b11100111 (
b11100111 *
1'
1#
#802000
0'
0#
#803000
b11101000 "
b11101000 (
b11101000 *
1'
1#
#804000
0'
0#
#805000
b11101001 "
b11101001 (
b11101001 *
1'
1#
#806000
0'
0#
#807000
b11101010 "
b11101010 (
b11101010 *
1'
1#
#808000
0'
0#
#809000
b11101011 "
b11101011 (
b11101011 *
1'
1#
#810000
0'
0#
#811000
b11101100 "
b11101100 (
b11101100 *
1'
1#
#812000
0'
0#
#813000
b11101101 "
b11101101 (
b11101101 *
1'
1#
#814000
0'
0#
#815000
b11101110 "
b11101110 (
b11101110 *
1'
1#
#816000
0'
0#
#817000
b11101111 "
b11101111 (
b11101111 *
1'
1#
#818000
0'
0#
#819000
b11110000 "
b11110000 (
b11110000 *
1'
1#
#820000
0'
0#
#821000
b11110001 "
b11110001 (
b11110001 *
1'
1#
#822000
0'
0#
#823000
b11110010 "
b11110010 (
b11110010 *
1'
1#
#824000
0'
0#
#825000
b11110011 "
b11110011 (
b11110011 *
1'
1#
#826000
0'
0#
#827000
b11110100 "
b11110100 (
b11110100 *
1'
1#
#828000
0'
0#
#829000
b11110101 "
b11110101 (
b11110101 *
1'
1#
#830000
0'
0#
#831000
b11110110 "
b11110110 (
b11110110 *
1'
1#
#832000
0'
0#
#833000
b11110111 "
b11110111 (
b11110111 *
1'
1#
#834000
0'
0#
