sequence_detector/sequence_detector.v
//////////////////////////////////////////////////////////////////////
// Module Name: sequence detector.v
// Description: sequence_detector for 101001
// Designer: Barney Peng
// Date: 03/30/2024
//////////////////////////////////////////////////////////////////////

//module counter #(parameter WIDTH (3) /* 3 bit counter*/)(
module sequence_detector (
	input i_clk,
	input i_resetn,
	input i_data,

	output o_count_end, 		      // counter reaches max value
	output wire [WIDTH-1 : 0] o_count,   // Output of the counter(remember that 8-bit: [7:0](7 to 0))
	output o_pattern_found



);

	parameter WIDTH = 6; /* 6  bit counter*/
	//parameter TGT_pattern = 6'b101001; 

	reg [WIDTH-1 : 0] o_count_p;

	parameter A = 6'd1,
			  B = 6'd2, //S1
			  C = 6'd3,	//S10
			  D = 6'd4,	//S101
			  E = 6'd5, //S1010
			  F = 6'd6; //S10100
			   
 	reg [WIDTH-1 : 0] cur_state, next_state; //current state and next state


	wire clk_gate;		// gated clock
	
	
	assign clk_gate = i_clk;
	// Counter
	always @(negedge i_resetn or posedge clk_gate)       // At every positive edge of the clock or negative edge of restn
		begin
			if  (~i_resetn)
		 		o_count_p <= 2'h0;		 // If reset is asserted, set the counter to 0
			else if(o_count_p >= 6'd63)
				o_count_p <=  2'h0;      // Otherwise, deassign the output

			else 
				o_count_p <=  o_count_p + 1;         // Increment the counter by 1
		end//Counter

	// Sequence Detector: initial state is A	
	always @(negedge i_resetn or posedge clk_gate)       // At every positive edge of the clock or negative edge of restn
		begin
			if  (~i_resetn)
				cur_state <= A;		 // If reset is asserted, set the state to A (initial State)
			else
				cur_state <= next_state;         // Else, set the state to the next state
		end// Sequence Detector: initial state is A


	// Sequence Detector
	always @(cur_state or i_data)
	 begin
		case(cur_state)
			A: begin
				if(i_data == 1'b1)
					next_state = B;
				else
					 next_state = A;
			end
			B: begin
				if(i_data == 1'b1)
					next_state = B;
				else
					 next_state = C;			
			end
			C: begin
				if(i_data == 1'b1)
					next_state = D;
				else
					 next_state = A;
			end
			D: begin
				if(i_data == 1'b1)
					next_state = B;
				else
					 next_state = E;
			end
			E: begin
				if(i_data == 1'b1)
					next_state = D;
				else
					 next_state = F;
			end
			F: begin
				if(i_data == 1'b1)
					next_state = B; // detected the pattern
				else
					 next_state = A;
			end
			default: next_state = A;
		endcase
	
	 end	
	
	
	assign o_count_end = (o_count == 6'd63);
	assign o_count = o_count_p;
	assign o_pattern_found = (cur_state == F) && (i_data == 1)? 1:0;


endmodule // counter

sequence_detector/sequence_detector_tb.v
`timescale 1ns / 1ps //set the timescale for the module
//////////////////////////////////////////////////////////////////////
// Module Name: sequence detector_tb.v
// Description: sequence_detector for 101001
// Designer: Barney Peng
// Date: 03/30/2024
//////////////////////////////////////////////////////////////////////

module sequence_detector_tb;

parameter WIDTH = 6; /* xx  bit counter*/


reg i_resetn;
reg i_data;
wire  o_count_end;
wire [WIDTH-1:0] o_count;


// restn
initial begin
    i_resetn = 0;
    #20   i_resetn = 1;
    #4000 i_resetn = 1;
    $finish;
end//restn

// input "i_data"
initial begin
    @(posedge i_clk) i_data <= 1;
    @(posedge i_clk) i_data <= 0; 
    @(posedge i_clk) i_data <= 1;
    @(posedge i_clk) i_data <= 0; 
    
    @(posedge i_clk) i_data <= 1;
    @(posedge i_clk) i_data <= 0;  
    @(posedge i_clk) i_data <= 1;
    @(posedge i_clk) i_data <= 0;
    @(posedge i_clk) i_data <= 0;
    @(posedge i_clk) i_data <= 1;  //101001 //but before the restn, thus not detected

    @(posedge i_clk) i_data <= 0;  
    @(posedge i_clk) i_data <= 1;
    @(posedge i_clk) i_data <= 0;
    @(posedge i_clk) i_data <= 0;

    @(posedge i_clk) i_data <= 1;//101001
    @(posedge i_clk) i_data <= 0;
    @(posedge i_clk) i_data <= 1;
    @(posedge i_clk) i_data <= 0;
    @(posedge i_clk) i_data <= 0;
    @(posedge i_clk) i_data <= 1; //101001 


    @(posedge i_clk) i_data <= 0; //overlaping 
    @(posedge i_clk) i_data <= 1;
    @(posedge i_clk) i_data <= 0;
    @(posedge i_clk) i_data <= 0;
    @(posedge i_clk) i_data <= 1; //101001 

    @(posedge i_clk) i_data <= 0;
    @(posedge i_clk) i_data <= 0;
    @(posedge i_clk) i_data <= 0;
    @(posedge i_clk) i_data <= 1;
    @(posedge i_clk) i_data <= 0;

    @(posedge i_clk) i_data <= 1;
    @(posedge i_clk) i_data <= 0;
    @(posedge i_clk) i_data <= 1;
    @(posedge i_clk) i_data <= 0;
    @(posedge i_clk) i_data <= 0;
    @(posedge i_clk) i_data <= 1; //101001 


    @(posedge i_clk) i_data <= 1;
    @(posedge i_clk) i_data <= 0;
    @(posedge i_clk) i_data <= 1;
    @(posedge i_clk) i_data <= 1;
    @(posedge i_clk) i_data <= 1;

    @(posedge i_clk) i_data <= 1;
    @(posedge i_clk) i_data <= 0;
    @(posedge i_clk) i_data <= 1;
    @(posedge i_clk) i_data <= 0;
    @(posedge i_clk) i_data <= 0;
    @(posedge i_clk) i_data <= 1; //101001 


    @(posedge i_clk) i_data <= 1;
    @(posedge i_clk) i_data <= 0;
    @(posedge i_clk) i_data <= 1;
    @(posedge i_clk) i_data <= 1;
    @(posedge i_clk) i_data <= 0;
    @(posedge i_clk) i_data <= 1;
    @(posedge i_clk) i_data <= 0;
    @(posedge i_clk) i_data <= 1;
    @(posedge i_clk) i_data <= 0;
    @(posedge i_clk) i_data <= 0;
    @(posedge i_clk) i_data <= 1; //101001 




end// input "i_data"

// free running clock i_clk
reg i_clk = 0;
always #1 i_clk = !i_clk;

initial begin
    $monitor("At time %t, o_count = %h (%0d)", $time, o_count, o_count);
end

initial begin
    $monitor("At time %t, o_pattern_found = %h (%0d)", $time, o_pattern_found, o_pattern_found);
end



initial begin
    $dumpfile("sequence_detector.vcd");
    $dumpvars(0,sequence_detector_tb);
end

sequence_detector u_sequence_detector (
    .i_clk(i_clk),
    .i_resetn(i_resetn),
    .i_data(i_data),

    .o_count_end(o_count_end),
    .o_count(o_count),

    .o_pattern_found(o_pattern_found)


);

endmodule

sequence_detector/sequence_detector.vcd
$date
	Sat Mar 30 16:25:18 2024
$end
$version
	Icarus Verilog
$end
$timescale
	1ps
$end
$scope module sequence_detector_tb $end
$var wire 1 ! o_pattern_found $end
$var wire 1 " o_count_end $end
$var wire 6 # o_count [5:0] $end
$var parameter 32 $ WIDTH $end
$var reg 1 % i_clk $end
$var reg 1 & i_data $end
$var reg 1 ' i_resetn $end
$scope module u_sequence_detector $end
$var wire 1 ( clk_gate $end
$var wire 1 % i_clk $end
$var wire 1 & i_data $end
$var wire 1 ' i_resetn $end
$var wire 1 ! o_pattern_found $end
$var wire 1 " o_count_end $end
$var wire 6 ) o_count [5:0] $end
$var parameter 6 * A $end
$var parameter 6 + B $end
$var parameter 6 , C $end
$var parameter 6 - D $end
$var parameter 6 . E $end
$var parameter 6 / F $end
$var parameter 32 0 WIDTH $end
$var reg 6 1 cur_state [5:0] $end
$var reg 6 2 next_state [5:0] $end
$var reg 6 3 o_count_p [5:0] $end
$upscope $end
$upscope $end
$enddefinitions $end
$comment Show the parameter values. $end
$dumpall
b110 0
b110 /
b101 .
b100 -
b11 ,
b10 +
b1 *
b110 $
$end
#0
$dumpvars
b0 3
b1 2
b1 1
b0 )
0(
0'
x&
0%
b0 #
0"
0!
$end
#1000
b10 2
1&
1(
1%
#2000
0(
0%
#3000
b1 2
0&
1(
1%
#4000
0(
0%
#5000
b10 2
1&
1(
1%
#6000
0(
0%
#7000
b1 2
0&
1(
1%
#8000
0(
0%
#9000
b10 2
1&
1(
1%
#10000
0(
0%
#11000
b1 2
0&
1(
1%
#12000
0(
0%
#13000
b10 2
1&
1(
1%
#14000
0(
0%
#15000
b1 2
0&
1(
1%
#16000
0(
0%
#17000
1(
1%
#18000
0(
0%
#19000
b10 2
1&
1(
1%
#20000
0(
0%
1'
#21000
b11 2
b10 1
b1 #
b1 )
b1 3
0&
1(
1%
#22000
0(
0%
#23000
b100 2
b10 #
b10 )
b10 3
b11 1
1&
1(
1%
#24000
0(
0%
#25000
b101 2
b100 1
b11 #
b11 )
b11 3
0&
1(
1%
#26000
0(
0%
#27000
b110 2
b100 #
b100 )
b100 3
b101 1
1(
1%
#28000
0(
0%
#29000
1!
b10 2
b110 1
b101 #
b101 )
b101 3
1&
1(
1%
#30000
0(
0%
#31000
0!
b11 2
b110 #
b110 )
b110 3
b10 1
0&
1(
1%
#32000
0(
0%
#33000
b100 2
b11 1
b111 #
b111 )
b111 3
1&
1(
1%
#34000
0(
0%
#35000
b101 2
b1000 #
b1000 )
b1000 3
b100 1
0&
1(
1%
#36000
0(
0%
#37000
b110 2
b101 1
b1001 #
b1001 )
b1001 3
1(
1%
#38000
0(
0%
#39000
1!
b10 2
b1010 #
b1010 )
b1010 3
b110 1
1&
1(
1%
#40000
0(
0%
#41000
0!
b11 2
b10 1
b1011 #
b1011 )
b1011 3
0&
1(
1%
#42000
0(
0%
#43000
b100 2
b1100 #
b1100 )
b1100 3
b11 1
1&
1(
1%
#44000
0(
0%
#45000
b101 2
b100 1
b1101 #
b1101 )
b1101 3
0&
1(
1%
#46000
0(
0%
#47000
b110 2
b1110 #
b1110 )
b1110 3
b101 1
1(
1%
#48000
0(
0%
#49000
1!
b10 2
b110 1
b1111 #
b1111 )
b1111 3
1&
1(
1%
#50000
0(
0%
#51000
0!
b11 2
b10000 #
b10000 )
b10000 3
b10 1
0&
1(
1%
#52000
0(
0%
#53000
b1 2
b11 1
b10001 #
b10001 )
b10001 3
1(
1%
#54000
0(
0%
#55000
b10010 #
b10010 )
b10010 3
b1 1
1(
1%
#56000
0(
0%
#57000
b10 2
b10011 #
b10011 )
b10011 3
1&
1(
1%
#58000
0(
0%
#59000
b11 2
b10100 #
b10100 )
b10100 3
b10 1
0&
1(
1%
#60000
0(
0%
#61000
b100 2
b11 1
b10101 #
b10101 )
b10101 3
1&
1(
1%
#62000
0(
0%
#63000
b101 2
b10110 #
b10110 )
b10110 3
b100 1
0&
1(
1%
#64000
0(
0%
#65000
b100 2
b101 1
b10111 #
b10111 )
b10111 3
1&
1(
1%
#66000
0(
0%
#67000
b101 2
b11000 #
b11000 )
b11000 3
b100 1
0&
1(
1%
#68000
0(
0%
#69000
b110 2
b101 1
b11001 #
b11001 )
b11001 3
1(
1%
#70000
0(
0%
#71000
1!
b10 2
b11010 #
b11010 )
b11010 3
b110 1
1&
1(
1%
#72000
0(
0%
#73000
0!
b10 1
b11011 #
b11011 )
b11011 3
1(
1%
#74000
0(
0%
#75000
b11 2
b11100 #
b11100 )
b11100 3
0&
1(
1%
#76000
0(
0%
#77000
b100 2
b11 1
b11101 #
b11101 )
b11101 3
1&
1(
1%
#78000
0(
0%
#79000
b10 2
b11110 #
b11110 )
b11110 3
b100 1
1(
1%
#80000
0(
0%
#81000
b10 1
b11111 #
b11111 )
b11111 3
1(
1%
#82000
0(
0%
#83000
b100000 #
b100000 )
b100000 3
1(
1%
#84000
0(
0%
#85000
b11 2
b100001 #
b100001 )
b100001 3
0&
1(
1%
#86000
0(
0%
#87000
b100 2
b100010 #
b100010 )
b100010 3
b11 1
1&
1(
1%
#88000
0(
0%
#89000
b101 2
b100 1
b100011 #
b100011 )
b100011 3
0&
1(
1%
#90000
0(
0%
#91000
b110 2
b100100 #
b100100 )
b100100 3
b101 1
1(
1%
#92000
0(
0%
#93000
1!
b10 2
b110 1
b100101 #
b100101 )
b100101 3
1&
1(
1%
#94000
0(
0%
#95000
0!
b100110 #
b100110 )
b100110 3
b10 1
1(
1%
#96000
0(
0%
#97000
b11 2
b100111 #
b100111 )
b100111 3
0&
1(
1%
#98000
0(
0%
#99000
b100 2
b101000 #
b101000 )
b101000 3
b11 1
1&
1(
1%
#100000
0(
0%
#101000
b10 2
b100 1
b101001 #
b101001 )
b101001 3
1(
1%
#102000
0(
0%
#103000
b11 2
b101010 #
b101010 )
b101010 3
b10 1
0&
1(
1%
#104000
0(
0%
#105000
b100 2
b11 1
b101011 #
b101011 )
b101011 3
1&
1(
1%
#106000
0(
0%
#107000
b101 2
b101100 #
b101100 )
b101100 3
b100 1
0&
1(
1%
#108000
0(
0%
#109000
b100 2
b101 1
b101101 #
b101101 )
b101101 3
1&
1(
1%
#110000
0(
0%
#111000
b101 2
b101110 #
b101110 )
b101110 3
b100 1
0&
1(
1%
#112000
0(
0%
#113000
b110 2
b101 1
b101111 #
b101111 )
b101111 3
1(
1%
#114000
0(
0%
#115000
1!
b10 2
b110000 #
b110000 )
b110000 3
b110 1
1&
1(
1%
#116000
0(
0%
#117000
0!
b10 1
b110001 #
b110001 )
b110001 3
1(
1%
#118000
0(
0%
#119000
b110010 #
b110010 )
b110010 3
1(
1%
#120000
0(
0%
#121000
b110011 #
b110011 )
b110011 3
1(
1%
#122000
0(
0%
#123000
b110100 #
b110100 )
b110100 3
1(
1%
#124000
0(
0%
#125000
b110101 #
b110101 )
b110101 3
1(
1%
#126000
0(
0%
#127000
b110110 #
b110110 )
b110110 3
1(
1%
#128000
0(
0%
#129000
b110111 #
b110111 )
b110111 3
1(
1%
#130000
0(
0%
#131000
b111000 #
b111000 )
b111000 3
1(
1%
#132000
0(
0%
#133000
b111001 #
b111001 )
b111001 3
1(
1%
#134000
0(
0%
#135000
b111010 #
b111010 )
b111010 3
1(
1%
#136000
0(
0%
#137000
b111011 #
b111011 )
b111011 3
1(
1%
#138000
0(
0%
#139000
b111100 #
b111100 )
b111100 3
1(
1%
#140000
0(
0%
#141000
b111101 #
b111101 )
b111101 3
1(
1%
#142000
0(
0%
#143000
b111110 #
b111110 )
b111110 3
1(
1%
#144000
0(
0%
#145000
1"
b111111 #
b111111 )
b111111 3
1(
1%
#146000
0(
0%
#147000
0"
b0 #
b0 )
b0 3
1(
1%
#148000
0(
0%
#149000
b1 #
b1 )
b1 3
1(
1%
#150000
0(
0%
#151000
b10 #
b10 )
b10 3
1(
1%
#152000
0(
0%
#153000
b11 #
b11 )
b11 3
1(
1%
#154000
0(
0%
#155000
b100 #
b100 )
b100 3
1(
1%
#156000
0(
0%
#157000
b101 #
b101 )
b101 3
1(
1%
#158000
0(
0%
#159000
b110 #
b110 )
b110 3
1(
1%
#160000
0(
0%
#161000
b111 #
b111 )
b111 3
1(
1%
#162000
0(
0%
#163000
b1000 #
b1000 )
b1000 3
1(
1%
#164000
0(
0%
#165000
b1001 #
b1001 )
b1001 3
1(
1%
#166000
0(
0%
#167000
b1010 #
b1010 )
b1010 3
1(
1%
#168000
0(
0%
#169000
b1011 #
b1011 )
b1011 3
1(
1%
#170000
0(
0%
#171000
b1100 #
b1100 )
b1100 3
1(
1%
#172000
0(
0%
#173000
b1101 #
b1101 )
b1101 3
1(
1%
#174000
0(
0%
#175000
b1110 #
b1110 )
b1110 3
1(
1%
#176000
0(
0%
#177000
b1111 #
b1111 )
b1111 3
1(
1%
#178000
0(
0%
#179000
b10000 #
b10000 )
b10000 3
1(
1%
#180000
0(
0%
#181000
b10001 #
b10001 )
b10001 3
1(
1%
#182000
0(
0%
#183000
b10010 #
b10010 )
b10010 3
1(
1%
#184000
0(
0%
#185000
b10011 #
b10011 )
b10011 3
1(
1%
#186000
0(
0%
#187000
b10100 #
b10100 )
b10100 3
1(
1%
#188000
0(
0%
#189000
b10101 #
b10101 )
b10101 3
1(
1%
#190000
0(
0%
#191000
b10110 #
b10110 )
b10110 3
1(
1%
#192000
0(
0%
#193000
b10111 #
b10111 )
b10111 3
1(
1%
#194000
0(
0%
#195000
b11000 #
b11000 )
b11000 3
1(
1%
#196000
0(
0%
#197000
b11001 #
b11001 )
b11001 3
1(
1%
#198000
0(
0%
#199000
b11010 #
b11010 )
b11010 3
1(
1%
#200000
0(
0%
#201000
b11011 #
b11011 )
b11011 3
1(
1%
#202000
0(
0%
#203000
b11100 #
b11100 )
b11100 3
1(
1%
#204000
0(
0%
#205000
b11101 #
b11101 )
b11101 3
1(
1%
#206000
0(
0%
#207000
b11110 #
b11110 )
b11110 3
1(
1%
#208000
0(
0%
#209000
b11111 #
b11111 )
b11111 3
1(
1%
#210000
0(
0%
#211000
b100000 #
b100000 )
b100000 3
1(
1%
#212000
0(
0%
#213000
b100001 #
b100001 )
b100001 3
1(
1%
#214000
0(
0%
#215000
b100010 #
b100010 )
b100010 3
1(
1%
#216000
0(
0%
#217000
b100011 #
b100011 )
b100011 3
1(
1%
#218000
0(
0%
#219000
b100100 #
b100100 )
b100100 3
1(
1%
#220000
0(
0%
#221000
b100101 #
b100101 )
b100101 3
1(
1%
#222000
0(
0%
#223000
b100110 #
b100110 )
b100110 3
1(
1%
#224000
0(
0%
#225000
b100111 #
b100111 )
b100111 3
1(
1%
#226000
0(
0%
#227000
b101000 #
b101000 )
b101000 3
1(
1%
#228000
0(
0%
#229000
b101001 #
b101001 )
b101001 3
1(
1%
#230000
0(
0%
#231000
b101010 #
b101010 )
b101010 3
1(
1%
#232000
0(
0%
#233000
b101011 #
b101011 )
b101011 3
1(
1%
#234000
0(
0%
#235000
b101100 #
b101100 )
b101100 3
1(
1%
#236000
0(
0%
#237000
b101101 #
b101101 )
b101101 3
1(
1%
#238000
0(
0%
#239000
b101110 #
b101110 )
b101110 3
1(
1%
#240000
0(
0%
#241000
b101111 #
b101111 )
b101111 3
1(
1%
#242000
0(
0%
#243000
b110000 #
b110000 )
b110000 3
1(
1%
#244000
0(
0%
#245000
b110001 #
b110001 )
b110001 3
1(
1%
#246000
0(
0%
#247000
b110010 #
b110010 )
b110010 3
1(
1%
#248000
0(
0%
#249000
b110011 #
b110011 )
b110011 3
1(
1%
#250000
0(
0%
#251000
b110100 #
b110100 )
b110100 3
1(
1%
#252000
0(
0%
#253000
b110101 #
b110101 )
b110101 3
1(
1%
#254000
0(
0%
#255000
b110110 #
b110110 )
b110110 3
1(
1%
#256000
0(
0%
#257000
b110111 #
b110111 )
b110111 3
1(
1%
#258000
0(
0%
#259000
b111000 #
b111000 )
b111000 3
1(
1%
#260000
0(
0%
#261000
b111001 #
b111001 )
b111001 3
1(
1%
#262000
0(
0%
#263000
b111010 #
b111010 )
b111010 3
1(
1%
#264000
0(
0%
#265000
b111011 #
b111011 )
b111011 3
1(
1%
#266000
0(
0%
#267000
b111100 #
b111100 )
b111100 3
1(
1%
#268000
0(
0%
#269000
b111101 #
b111101 )
b111101 3
1(
1%
#270000
0(
0%
#271000
b111110 #
b111110 )
b111110 3
1(
1%
#272000
0(
0%
#273000
1"
b111111 #
b111111 )
b111111 3
1(
1%
#274000
0(
0%
#275000
0"
b0 #
b0 )
b0 3
1(
1%
#276000
0(
0%
#277000
b1 #
b1 )
b1 3
1(
1%
#278000
0(
0%
#279000
b10 #
b10 )
b10 3
1(
1%
#280000
0(
0%
#281000
b11 #
b11 )
b11 3
1(
1%
#282000
0(
0%
#283000
b100 #
b100 )
b100 3
1(
1%
#284000
0(
0%
#285000
b101 #
b101 )
b101 3
1(
1%
#286000
0(
0%
#287000
b110 #
b110 )
b110 3
1(
1%
#288000
0(
0%
#289000
b111 #
b111 )
b111 3
1(
1%
#290000
0(
0%
#291000
b1000 #
b1000 )
b1000 3
1(
1%
#292000
0(
0%
#293000
b1001 #
b1001 )
b1001 3
1(
1%
#294000
0(
0%
#295000
b1010 #
b1010 )
b1010 3
1(
1%
#296000
0(
0%
#297000
b1011 #
b1011 )
b1011 3
1(
1%
#298000
0(
0%
#299000
b1100 #
b1100 )
b1100 3
1(
1%
#300000
0(
0%
#301000
b1101 #
b1101 )
b1101 3
1(
1%
#302000
0(
0%
#303000
b1110 #
b1110 )
b1110 3
1(
1%
#304000
0(
0%
#305000
b1111 #
b1111 )
b1111 3
1(
1%
#306000
0(
0%
#307000
b10000 #
b10000 )
b10000 3
1(
1%
#308000
0(
0%
#309000
b10001 #
b10001 )
b10001 3
1(
1%
#310000
0(
0%
#311000
b10010 #
b10010 )
b10010 3
1(
1%
#312000
0(
0%
#313000
b10011 #
b10011 )
b10011 3
1(
1%
#314000
0(
0%
#315000
b10100 #
b10100 )
b10100 3
1(
1%
#316000
0(
0%
#317000
b10101 #
b10101 )
b10101 3
1(
1%
#318000
0(
0%
#319000
b10110 #
b10110 )
b10110 3
1(
1%
#320000
0(
0%
#321000
b10111 #
b10111 )
b10111 3
1(
1%
#322000
0(
0%
#323000
b11000 #
b11000 )
b11000 3
1(
1%
#324000
0(
0%
#325000
b11001 #
b11001 )
b11001 3
1(
1%
#326000
0(
0%
#327000
b11010 #
b11010 )
b11010 3
1(
1%
#328000
0(
0%
#329000
b11011 #
b11011 )
b11011 3
1(
1%
#330000
0(
0%
#331000
b11100 #
b11100 )
b11100 3
1(
1%
#332000
0(
0%
#333000
b11101 #
b11101 )
b11101 3
1(
1%
#334000
0(
0%
#335000
b11110 #
b11110 )
b11110 3
1(
1%
#336000
0(
0%
#337000
b11111 #
b11111 )
b11111 3
1(
1%
#338000
0(
0%
#339000
b100000 #
b100000 )
b100000 3
1(
1%
#340000
0(
0%
#341000
b100001 #
b100001 )
b100001 3
1(
1%
#342000
0(
0%
#343000
b100010 #
b100010 )
b100010 3
1(
1%
#344000
0(
0%
#345000
b100011 #
b100011 )
b100011 3
1(
1%
#346000
0(
0%
#347000
b100100 #
b100100 )
b100100 3
1(
1%
#348000
0(
0%
#349000
b100101 #
b100101 )
b100101 3
1(
1%
#350000
0(
0%
#351000
b100110 #
b100110 )
b100110 3
1(
1%
#352000
0(
0%
#353000
b100111 #
b100111 )
b100111 3
1(
1%
#354000
0(
0%
#355000
b101000 #
b101000 )
b101000 3
1(
1%
#356000
0(
0%
#357000
b101001 #
b101001 )
b101001 3
1(
1%
#358000
0(
0%
#359000
b101010 #
b101010 )
b101010 3
1(
1%
#360000
0(
0%
#361000
b101011 #
b101011 )
b101011 3
1(
1%
#362000
0(
0%
#363000
b101100 #
b101100 )
b101100 3
1(
1%
#364000
0(
0%
#365000
b101101 #
b101101 )
b101101 3
1(
1%
#366000
0(
0%
#367000
b101110 #
b101110 )
b101110 3
1(
1%
#368000
0(
0%
#369000
b101111 #
b101111 )
b101111 3
1(
1%
#370000
0(
0%
#371000
b110000 #
b110000 )
b110000 3
1(
1%
#372000
0(
0%
#373000
b110001 #
b110001 )
b110001 3
1(
1%
#374000
0(
0%
#375000
b110010 #
b110010 )
b110010 3
1(
1%
#376000
0(
0%
#377000
b110011 #
b110011 )
b110011 3
1(
1%
#378000
0(
0%
#379000
b110100 #
b110100 )
b110100 3
1(
1%
#380000
0(
0%
#381000
b110101 #
b110101 )
b110101 3
1(
1%
#382000
0(
0%
#383000
b110110 #
b110110 )
b110110 3
1(
1%
#384000
0(
0%
#385000
b110111 #
b110111 )
b110111 3
1(
1%
#386000
0(
0%
#387000
b111000 #
b111000 )
b111000 3
1(
1%
#388000
0(
0%
#389000
b111001 #
b111001 )
b111001 3
1(
1%
#390000
0(
0%
#391000
b111010 #
b111010 )
b111010 3
1(
1%
#392000
0(
0%
#393000
b111011 #
b111011 )
b111011 3
1(
1%
#394000
0(
0%
#395000
b111100 #
b111100 )
b111100 3
1(
1%
#396000
0(
0%
#397000
b111101 #
b111101 )
b111101 3
1(
1%
#398000
0(
0%
#399000
b111110 #
b111110 )
b111110 3
1(
1%
#400000
0(
0%
#401000
1"
b111111 #
b111111 )
b111111 3
1(
1%
#402000
0(
0%
#403000
0"
b0 #
b0 )
b0 3
1(
1%
#404000
0(
0%
#405000
b1 #
b1 )
b1 3
1(
1%
#406000
0(
0%
#407000
b10 #
b10 )
b10 3
1(
1%
#408000
0(
0%
#409000
b11 #
b11 )
b11 3
1(
1%
#410000
0(
0%
#411000
b100 #
b100 )
b100 3
1(
1%
#412000
0(
0%
#413000
b101 #
b101 )
b101 3
1(
1%
#414000
0(
0%
#415000
b110 #
b110 )
b110 3
1(
1%
#416000
0(
0%
#417000
b111 #
b111 )
b111 3
1(
1%
#418000
0(
0%
#419000
b1000 #
b1000 )
b1000 3
1(
1%
#420000
0(
0%
#421000
b1001 #
b1001 )
b1001 3
1(
1%
#422000
0(
0%
#423000
b1010 #
b1010 )
b1010 3
1(
1%
#424000
0(
0%
#425000
b1011 #
b1011 )
b1011 3
1(
1%
#426000
0(
0%
#427000
b1100 #
b1100 )
b1100 3
1(
1%
#428000
0(
0%
#429000
b1101 #
b1101 )
b1101 3
1(
1%
#430000
0(
0%
#431000
b1110 #
b1110 )
b1110 3
1(
1%
#432000
0(
0%
#433000
b1111 #
b1111 )
b1111 3
1(
1%
#434000
0(
0%
#435000
b10000 #
b10000 )
b10000 3
1(
1%
#436000
0(
0%
#437000
b10001 #
b10001 )
b10001 3
1(
1%
#438000
0(
0%
#439000
b10010 #
b10010 )
b10010 3
1(
1%
#440000
0(
0%
#441000
b10011 #
b10011 )
b10011 3
1(
1%
#442000
0(
0%
#443000
b10100 #
b10100 )
b10100 3
1(
1%
#444000
0(
0%
#445000
b10101 #
b10101 )
b10101 3
1(
1%
#446000
0(
0%
#447000
b10110 #
b10110 )
b10110 3
1(
1%
#448000
0(
0%
#449000
b10111 #
b10111 )
b10111 3
1(
1%
#450000
0(
0%
#451000
b11000 #
b11000 )
b11000 3
1(
1%
#452000
0(
0%
#453000
b11001 #
b11001 )
b11001 3
1(
1%
#454000
0(
0%
#455000
b11010 #
b11010 )
b11010 3
1(
1%
#456000
0(
0%
#457000
b11011 #
b11011 )
b11011 3
1(
1%
#458000
0(
0%
#459000
b11100 #
b11100 )
b11100 3
1(
1%
#460000
0(
0%
#461000
b11101 #
b11101 )
b11101 3
1(
1%
#462000
0(
0%
#463000
b11110 #
b11110 )
b11110 3
1(
1%
#464000
0(
0%
#465000
b11111 #
b11111 )
b11111 3
1(
1%
#466000
0(
0%
#467000
b100000 #
b100000 )
b100000 3
1(
1%
#468000
0(
0%
#469000
b100001 #
b100001 )
b100001 3
1(
1%
#470000
0(
0%
#471000
b100010 #
b100010 )
b100010 3
1(
1%
#472000
0(
0%
#473000
b100011 #
b100011 )
b100011 3
1(
1%
#474000
0(
0%
#475000
b100100 #
b100100 )
b100100 3
1(
1%
#476000
0(
0%
#477000
b100101 #
b100101 )
b100101 3
1(
1%
#478000
0(
0%
#479000
b100110 #
b100110 )
b100110 3
1(
1%
#480000
0(
0%
#481000
b100111 #
b100111 )
b100111 3
1(
1%
#482000
0(
0%
#483000
b101000 #
b101000 )
b101000 3
1(
1%
#484000
0(
0%
#485000
b101001 #
b101001 )
b101001 3
1(
1%
#486000
0(
0%
#487000
b101010 #
b101010 )
b101010 3
1(
1%
#488000
0(
0%
#489000
b101011 #
b101011 )
b101011 3
1(
1%
#490000
0(
0%
#491000
b101100 #
b101100 )
b101100 3
1(
1%
#492000
0(
0%
#493000
b101101 #
b101101 )
b101101 3
1(
1%
#494000
0(
0%
#495000
b101110 #
b101110 )
b101110 3
1(
1%
#496000
0(
0%
#497000
b101111 #
b101111 )
b101111 3
1(
1%
#498000
0(
0%
#499000
b110000 #
b110000 )
b110000 3
1(
1%
#500000
0(
0%
#501000
b110001 #
b110001 )
b110001 3
1(
1%
#502000
0(
0%
#503000
b110010 #
b110010 )
b110010 3
1(
1%
#504000
0(
0%
#505000
b110011 #
b110011 )
b110011 3
1(
1%
#506000
0(
0%
#507000
b110100 #
b110100 )
b110100 3
1(
1%
#508000
0(
0%
#509000
b110101 #
b110101 )
b110101 3
1(
1%
#510000
0(
0%
#511000
b110110 #
b110110 )
b110110 3
1(
1%
#512000
0(
0%
#513000
b110111 #
b110111 )
b110111 3
1(
1%
#514000
0(
0%
#515000
b111000 #
b111000 )
b111000 3
1(
1%
#516000
0(
0%
#517000
b111001 #
b111001 )
b111001 3
1(
1%
#518000
0(
0%
#519000
b111010 #
b111010 )
b111010 3
1(
1%
#520000
0(
0%
#521000
b111011 #
b111011 )
b111011 3
1(
1%
#522000
0(
0%
#523000
b111100 #
b111100 )
b111100 3
1(
1%
#524000
0(
0%
#525000
b111101 #
b111101 )
b111101 3
1(
1%
#526000
0(
0%
#527000
b111110 #
b111110 )
b111110 3
1(
1%
#528000
0(
0%
#529000
1"
b111111 #
b111111 )
b111111 3
1(
1%
#530000
0(
0%
#531000
0"
b0 #
b0 )
b0 3
1(
1%
#532000
0(
0%
#533000
b1 #
b1 )
b1 3
1(
1%
#534000
0(
0%
#535000
b10 #
b10 )
b10 3
1(
1%
#536000
0(
0%
#537000
b11 #
b11 )
b11 3
1(
1%
#538000
0(
0%
#539000
b100 #
b100 )
b100 3
1(
1%
#540000
0(
0%
#541000
b101 #
b101 )
b101 3
1(
1%
#542000
0(
0%
#543000
b110 #
b110 )
b110 3
1(
1%
#544000
0(
0%
#545000
b111 #
b111 )
b111 3
1(
1%
#546000
0(
0%
#547000
b1000 #
b1000 )
b1000 3
1(
1%
#548000
0(
0%
#549000
b1001 #
b1001 )
b1001 3
1(
1%
#550000
0(
0%
#551000
b1010 #
b1010 )
b1010 3
1(
1%
#552000
0(
0%
#553000
b1011 #
b1011 )
b1011 3
1(
1%
#554000
0(
0%
#555000
b1100 #
b1100 )
b1100 3
1(
1%
#556000
0(
0%
#557000
b1101 #
b1101 )
b1101 3
1(
1%
#558000
0(
0%
#559000
b1110 #
b1110 )
b1110 3
1(
1%
#560000
0(
0%
#561000
b1111 #
b1111 )
b1111 3
1(
1%
#562000
0(
0%
#563000
b10000 #
b10000 )
b10000 3
1(
1%
#564000
0(
0%
#565000
b10001 #
b10001 )
b10001 3
1(
1%
#566000
0(
0%
#567000
b10010 #
b10010 )
b10010 3
1(
1%
#568000
0(
0%
#569000
b10011 #
b10011 )
b10011 3
1(
1%
#570000
0(
0%
#571000
b10100 #
b10100 )
b10100 3
1(
1%
#572000
0(
0%
#573000
b10101 #
b10101 )
b10101 3
1(
1%
#574000
0(
0%
#575000
b10110 #
b10110 )
b10110 3
1(
1%
#576000
0(
0%
