sequence_detector/sequence_detector_ShiftReg_111000101011_2bErrorTol.v
//////////////////////////////////////////////////////////////////////
// Module Name: sequence detector.v
// Description: sequence_detector_ShiftReg_111000101011_2bErrorTol for 101001 (over-laping sequence detector)
// Designer: Barney Peng
// Date: 04/21/2024
// References: https://www.youtube.com/watch?v=T_gSYkQe3EU
//////////////////////////////////////////////////////////////////////
	

module sequence_detector_ShiftReg_111000101011_2bErrorTol  (
	input i_clk,
	input i_resetn,
	input i_data,

	output o_pattern_found

);

	parameter WIDTH = 12; 
	//parameter TGT_pattern = 12'b111000101011; 
    //parameter ERROR_TOLERANCE = 2; // Maximum number of tolerated errors



	reg [WIDTH-1 : 0] seq_reg; //sequence register
	reg [WIDTH-1 : 0] pattern_match_XOR;
	wire [WIDTH-1 : 0] Bit_sum;
	reg pattern_found_p;
	wire clk_gate;		// gated clock
	reg detect_en;

	reg [WIDTH-1 : 0] count_p;

	assign clk_gate = i_clk;

	// instantiate adder_12in_1b
	adder_12in_1b adder_inst (
        .i_a(pattern_match_XOR),
        .o_sum(Bit_sum)
    );// adder_12in_1b

	//sequence register
	always @(negedge i_resetn or posedge clk_gate)//sequential logic: use "<=" instead of "="
		begin
			if (~i_resetn)	
				begin
					seq_reg <= 12'h0;
					count_p <= 0;
					pattern_match_XOR[11:0] <= 12'h0;
				end
			else if(count_p >= 12'd4095) // Max Value 12 bit can represent
				count_p <= WIDTH; //to prevent disbling detect_en after exceeding max value of count_p
			else
				begin
					seq_reg <= {seq_reg[WIDTH-2 : 0], i_data};
					count_p <= count_p + 1;
					pattern_match_XOR[11:0] <= (seq_reg ^ 12'b111000101011);
				end
		end //sequence register

	//detect_en
		always @(negedge i_resetn or posedge clk_gate)
		begin
			if (~i_resetn)
				detect_en <= 0;
			else if (count_p >= WIDTH)
				detect_en <= 1;
			else
				detect_en <= 0;
		end//detect_en		

		//Bit_sum// Bit_sum is the sum of howm nmany error bits in the
	 
	/*always @* 
		begin
		   Bit_sum = pattern_match_XOR[0] + pattern_match_XOR[1] + pattern_match_XOR[2] + pattern_match_XOR[3] + pattern_match_XOR[4] + pattern_match_XOR[5] + pattern_match_XOR[6] + pattern_match_XOR[7] + pattern_match_XOR[8] + pattern_match_XOR[9] + pattern_match_XOR[10] + pattern_match_XOR[11];

   end//Bit_sum//
   */


	//pattern_found_p
   always @(negedge i_resetn or posedge clk_gate) 
   begin
	   if (~i_resetn)
	   pattern_found_p <= 0;
	   else if (detect_en && (Bit_sum <= 2))
	   pattern_found_p <= 1;
	   else
	   pattern_found_p <= 0;
   end//pattern_found_p


	assign o_pattern_found = pattern_found_p;
	


endmodule //sequence_detector_ShiftReg_111000101011_2bErrorTol

module adder_12in_1b (

	input [WIDTH_in-1:0] i_a,

	output [WIDTH_out-1:0] o_sum

);
	parameter WIDTH_in = 12; 
	parameter WIDTH_out = 12;
	

	reg [WIDTH_out:0] sum_p;
	//reg [WIDTH_out:0] cout;
	//reg [WIDTH_in:0] cin;



always @(*)
begin
	sum_p = i_a[0] + i_a[1] + i_a[2] + i_a[3] + i_a[4] + i_a[5] + i_a[6] + i_a[7] + i_a[8] + i_a[9] + i_a[10] + i_a[11];

end

assign o_sum = sum_p;

endmodule//adder_12in_1b

sequence_detector/sequence_detector_ShiftReg_111000101011_2bErrorTol_tb.v
`timescale 1ns / 1ps //set the timescale for the module
//////////////////////////////////////////////////////////////////////
// Module Name: sequence detector_tb.v
// Description: sequence_detector_ShiftReg_111000101011_2bErrorTol for 101001
// Designer: Barney Peng
// Date: 04/21/2024
//////////////////////////////////////////////////////////////////////

module sequence_detector_ShiftReg_111000101011_2bErrorTol_tb;

parameter WIDTH = 12; /* xx  bit counter*/


reg i_resetn;
reg i_data;
wire [WIDTH-1:0] o_pattern_match_XOR;


// restn
initial begin
    i_resetn = 0;
    #20   i_resetn = 1;
    #4000 i_resetn = 1;
    $finish;
end//restn

// input "i_data"
initial begin
    @(posedge i_clk) i_data <= 1;
    @(posedge i_clk) i_data <= 0; 
    @(posedge i_clk) i_data <= 1;
    @(posedge i_clk) i_data <= 0; 
    
    @(posedge i_clk) i_data <= 1;
    @(posedge i_clk) i_data <= 0;  
    @(posedge i_clk) i_data <= 1;
    @(posedge i_clk) i_data <= 0;
    @(posedge i_clk) i_data <= 0;
    
    @(posedge i_clk) i_data <= 1;
    @(posedge i_clk) i_data <= 1;
    @(posedge i_clk) i_data <= 1;
    @(posedge i_clk) i_data <= 0;
    @(posedge i_clk) i_data <= 0;
    @(posedge i_clk) i_data <= 0;
    @(posedge i_clk) i_data <= 1;
    @(posedge i_clk) i_data <= 0;
    @(posedge i_clk) i_data <= 1;
    @(posedge i_clk) i_data <= 0;
    @(posedge i_clk) i_data <= 1;
    @(posedge i_clk) i_data <= 1; //111000101011

    @(posedge i_clk) i_data <= 1;

    @(posedge i_clk) i_data <= 0;
    @(posedge i_clk) i_data <= 0;
    @(posedge i_clk) i_data <= 0;
    @(posedge i_clk) i_data <= 1;
    @(posedge i_clk) i_data <= 0;
    @(posedge i_clk) i_data <= 1;
    @(posedge i_clk) i_data <= 0;
    @(posedge i_clk) i_data <= 1;
    @(posedge i_clk) i_data <= 1; //111000101011



    @(posedge i_clk) i_data <= 1;
    @(posedge i_clk) i_data <= 1;
    @(posedge i_clk) i_data <= 0;
    @(posedge i_clk) i_data <= 0;
    @(posedge i_clk) i_data <= 0;
    @(posedge i_clk) i_data <= 1;
    @(posedge i_clk) i_data <= 0;
    @(posedge i_clk) i_data <= 1;
    @(posedge i_clk) i_data <= 0;
    @(posedge i_clk) i_data <= 1;
    @(posedge i_clk) i_data <= 0;//111000101011, 1 error bit

    @(posedge i_clk) i_data <= 1;
    @(posedge i_clk) i_data <= 1;
    @(posedge i_clk) i_data <= 1;
    @(posedge i_clk) i_data <= 0;
    @(posedge i_clk) i_data <= 0;
    @(posedge i_clk) i_data <= 0;
    @(posedge i_clk) i_data <= 1;
    @(posedge i_clk) i_data <= 0;
    @(posedge i_clk) i_data <= 1;
    @(posedge i_clk) i_data <= 0;
    @(posedge i_clk) i_data <= 1;
    @(posedge i_clk) i_data <= 0;//111000101011, 1 error bit

    @(posedge i_clk) i_data <= 1;
    @(posedge i_clk) i_data <= 1;
    @(posedge i_clk) i_data <= 1;
    @(posedge i_clk) i_data <= 0;
    @(posedge i_clk) i_data <= 0;
    @(posedge i_clk) i_data <= 0;
    @(posedge i_clk) i_data <= 1;
    @(posedge i_clk) i_data <= 0;
    @(posedge i_clk) i_data <= 0;
    @(posedge i_clk) i_data <= 0;
    @(posedge i_clk) i_data <= 1;
    @(posedge i_clk) i_data <= 1;//111000101011, 1 error bit

    @(posedge i_clk) i_data <= 1;
    @(posedge i_clk) i_data <= 1;
    @(posedge i_clk) i_data <= 1;
    @(posedge i_clk) i_data <= 0;
    @(posedge i_clk) i_data <= 0;
    @(posedge i_clk) i_data <= 0;
    @(posedge i_clk) i_data <= 1;
    @(posedge i_clk) i_data <= 1;
    @(posedge i_clk) i_data <= 1;
    @(posedge i_clk) i_data <= 0;
    @(posedge i_clk) i_data <= 1;
    @(posedge i_clk) i_data <= 0; //111000101011, 2 error bits

    @(posedge i_clk) i_data <= 1;
    @(posedge i_clk) i_data <= 1;
    @(posedge i_clk) i_data <= 1;
    @(posedge i_clk) i_data <= 0;
    @(posedge i_clk) i_data <= 0;
    @(posedge i_clk) i_data <= 0;
    @(posedge i_clk) i_data <= 1;
    @(posedge i_clk) i_data <= 1;
    @(posedge i_clk) i_data <= 1;
    @(posedge i_clk) i_data <= 0;
    @(posedge i_clk) i_data <= 1;
    @(posedge i_clk) i_data <= 0; //111000101011, 2 error bits
end// input "i_data"

// free running clock i_clk
reg i_clk = 0;
always #1 i_clk = !i_clk;



initial begin
    $monitor("At time %t, o_pattern_found = %h (%0d)", $time, o_pattern_found, o_pattern_found);
end



initial begin
    $dumpfile("sequence_detector_ShiftReg_111000101011_2bErrorTol.vcd");
    $dumpvars(0,sequence_detector_ShiftReg_111000101011_2bErrorTol_tb);
end

sequence_detector_ShiftReg_111000101011_2bErrorTol u_sequence_detector_ShiftReg_111000101011_2bErrorTol (
    .i_clk(i_clk),
    .i_resetn(i_resetn),
    .i_data(i_data),


    .o_pattern_found(o_pattern_found)


);


endmodule

sequence_detector/sequence_detector_ShiftReg_111000101011_2bErrorTol.vcd
$date
	Sun Apr 21 23:01:50 2024
$end
$version
	Icarus Verilog
$end
$timescale
	1ps
$end
$scope module sequence_detector_ShiftReg_111000101011_2bErrorTol_tb $end
$var wire 1 ! o_pattern_found $end
$var parameter 32 " WIDTH $end
$var reg 1 # i_clk $end
$var reg 1 $ i_data $end
$var reg 1 % i_resetn $end
$scope module u_sequence_detector_ShiftReg_111000101011_2bErrorTol $end
$var wire 1 & clk_gate $end
$var wire 1 # i_clk $end
$var wire 1 $ i_data $end
$var wire 1 % i_resetn $end
$var wire 1 ! o_pattern_found $end
$var wire 12 ' Bit_sum [11:0] $end
$var parameter 32 ( WIDTH $end
$var reg 12 ) count_p [11:0] $end
$var reg 1 * detect_en $end
$var reg 1 + pattern_found_p $end
$var reg 12 , pattern_match_XOR [11:0] $end
$var reg 12 - seq_reg [11:0] $end
$scope module adder_inst $end
$var wire 12 . i_a [11:0] $end
$var wire 12 / o_sum [11:0] $end
$var parameter 32 0 WIDTH_in $end
$var parameter 32 1 WIDTH_out $end
$var reg 13 2 sum_p [12:0] $end
$upscope $end
$upscope $end
$upscope $end
$enddefinitions $end
$comment Show the parameter values. $end
$dumpall
b1100 1
b1100 0
b1100 (
b1100 "
$end
#0
$dumpvars
b0 2
b0 /
b0 .
b0 -
b0 ,
0+
0*
b0 )
b0 '
0&
0%
x$
0#
0!
$end
#1000
1$
1&
1#
#2000
0&
0#
#3000
0$
1&
1#
#4000
0&
0#
#5000
1$
1&
1#
#6000
0&
0#
#7000
0$
1&
1#
#8000
0&
0#
#9000
1$
1&
1#
#10000
0&
0#
#11000
0$
1&
1#
#12000
0&
0#
#13000
1$
1&
1#
#14000
0&
0#
#15000
0$
1&
1#
#16000
0&
0#
#17000
1&
1#
#18000
0&
0#
#19000
1$
1&
1#
#20000
0&
0#
1%
#21000
b111 '
b111 /
b111 2
b111000101011 ,
b111000101011 .
b1 )
b1 -
1&
1#
#22000
0&
0#
#23000
b110 '
b110 /
b110 2
b111000101010 ,
b111000101010 .
b10 )
b11 -
1&
1#
#24000
0&
0#
#25000
b101 '
b101 /
b101 2
b111000101000 ,
b111000101000 .
b11 )
b111 -
0$
1&
1#
#26000
0&
0#
#27000
b110 '
b110 /
b110 2
b111000101100 ,
b111000101100 .
b100 )
b1110 -
1&
1#
#28000
0&
0#
#29000
b111000100101 ,
b111000100101 .
b101 )
b11100 -
1&
1#
#30000
0&
0#
#31000
b1000 '
b1000 /
b1000 2
b111000110111 ,
b111000110111 .
b110 )
b111000 -
1$
1&
1#
#32000
0&
0#
#33000
b110 '
b110 /
b110 2
b111000010011 ,
b111000010011 .
b111 )
b1110001 -
0$
1&
1#
#34000
0&
0#
#35000
b111 '
b111 /
b111 2
b111001011010 ,
b111001011010 .
b1000 )
b11100010 -
1$
1&
1#
#36000
0&
0#
#37000
b111011001001 ,
b111011001001 .
b1001 )
b111000101 -
0$
1&
1#
#38000
0&
0#
#39000
b1010 '
b1010 /
b1010 2
b111111101110 ,
b111111101110 .
b1010 )
b1110001010 -
1$
1&
1#
#40000
0&
0#
#41000
b110 '
b110 /
b110 2
b110110100001 ,
b110110100001 .
b1011 )
b11100010101 -
1&
1#
#42000
0&
0#
#43000
b111 '
b111 /
b111 2
b100100111110 ,
b100100111110 .
b1100 )
b111000101011 -
1&
1#
#44000
0&
0#
#45000
b0 '
b0 /
b0 2
1*
b0 ,
b0 .
b1101 )
b110001010111 -
0$
1&
1#
#46000
0&
0#
#47000
b110 '
b110 /
b110 2
b1001111100 ,
b1001111100 .
b1110 )
b100010101110 -
1!
1+
1&
1#
#48000
0&
0#
#49000
b101 '
b101 /
b101 2
0!
0+
b11010000101 ,
b11010000101 .
b1111 )
b101011100 -
1&
1#
#50000
0&
0#
#51000
b1010 '
b1010 /
b1010 2
b111101110111 ,
b111101110111 .
b10000 )
b1010111000 -
1$
1&
1#
#52000
0&
0#
#53000
b110 '
b110 /
b110 2
b110010010011 ,
b110010010011 .
b10001 )
b10101110001 -
0$
1&
1#
#54000
0&
0#
#55000
b111 '
b111 /
b111 2
b101101011010 ,
b101101011010 .
b10010 )
b101011100010 -
1$
1&
1#
#56000
0&
0#
#57000
b101 '
b101 /
b101 2
b10011001001 ,
b10011001001 .
b10011 )
b10111000101 -
0$
1&
1#
#58000
0&
0#
#59000
b1001 '
b1001 /
b1001 2
b101111101110 ,
b101111101110 .
b10100 )
b101110001010 -
1$
1&
1#
#60000
0&
0#
#61000
b101 '
b101 /
b101 2
b10110100001 ,
b10110100001 .
b10101 )
b11100010101 -
1&
1#
#62000
0&
0#
#63000
b111 '
b111 /
b111 2
b100100111110 ,
b100100111110 .
b10110 )
b111000101011 -
1&
1#
#64000
0&
0#
#65000
b0 '
b0 /
b0 2
b0 ,
b0 .
b10111 )
b110001010111 -
1&
1#
#66000
0&
0#
#67000
b110 '
b110 /
b110 2
b1001111100 ,
b1001111100 .
b11000 )
b100010101111 -
1!
1+
0$
1&
1#
#68000
0&
0#
#69000
b100 '
b100 /
b100 2
0!
0+
b11010000100 ,
b11010000100 .
b11001 )
b101011110 -
1&
1#
#70000
0&
0#
#71000
b1001 '
b1001 /
b1001 2
b111101110101 ,
b111101110101 .
b11010 )
b1010111100 -
1&
1#
#72000
0&
0#
#73000
b111 '
b111 /
b111 2
b110010010111 ,
b110010010111 .
b11011 )
b10101111000 -
1$
1&
1#
#74000
0&
0#
#75000
b101101010011 ,
b101101010011 .
b11100 )
b101011110001 -
0$
1&
1#
#76000
0&
0#
#77000
b110 '
b110 /
b110 2
b10011011010 ,
b10011011010 .
b11101 )
b10111100010 -
1$
1&
1#
#78000
0&
0#
#79000
b111 '
b111 /
b111 2
b101111001001 ,
b101111001001 .
b11110 )
b101111000101 -
0$
1&
1#
#80000
0&
0#
#81000
b1000 '
b1000 /
b1000 2
b10111101110 ,
b10111101110 .
b11111 )
b11110001010 -
1$
1&
1#
#82000
0&
0#
#83000
b101 '
b101 /
b101 2
b100110100001 ,
b100110100001 .
b100000 )
b111100010101 -
0$
1&
1#
#84000
0&
0#
#85000
b110 '
b110 /
b110 2
b100111110 ,
b100111110 .
b100001 )
b111000101010 -
1$
1&
1#
#86000
0&
0#
#87000
b1 '
b1 /
b1 2
b1 ,
b1 .
b100010 )
b110001010101 -
1&
1#
#88000
0&
0#
#89000
b111 '
b111 /
b111 2
1!
1+
b1001111110 ,
b1001111110 .
b100011 )
b100010101011 -
1&
1#
#90000
0&
0#
#91000
b11 '
b11 /
b11 2
b11010000000 ,
b11010000000 .
b100100 )
b101010111 -
0!
0+
0$
1&
1#
#92000
0&
0#
#93000
b1001 '
b1001 /
b1001 2
b111101111100 ,
b111101111100 .
b100101 )
b1010101110 -
1&
1#
#94000
0&
0#
#95000
b101 '
b101 /
b101 2
b110010000101 ,
b110010000101 .
b100110 )
b10101011100 -
1&
1#
#96000
0&
0#
#97000
b1001 '
b1001 /
b1001 2
b101101110111 ,
b101101110111 .
b100111 )
b101010111000 -
1$
1&
1#
#98000
0&
0#
#99000
b101 '
b101 /
b101 2
b10010010011 ,
b10010010011 .
b101000 )
b10101110001 -
0$
1&
1#
#100000
0&
0#
#101000
b111 '
b111 /
b111 2
b101101011010 ,
b101101011010 .
b101001 )
b101011100010 -
1$
1&
1#
#102000
0&
0#
#103000
b101 '
b101 /
b101 2
b10011001001 ,
b10011001001 .
b101010 )
b10111000101 -
0$
1&
1#
#104000
0&
0#
#105000
b1001 '
b1001 /
b1001 2
b101111101110 ,
b101111101110 .
b101011 )
b101110001010 -
1$
1&
1#
#106000
0&
0#
#107000
b101 '
b101 /
b101 2
b10110100001 ,
b10110100001 .
b101100 )
b11100010101 -
0$
1&
1#
#108000
0&
0#
#109000
b111 '
b111 /
b111 2
b100100111110 ,
b100100111110 .
b101101 )
b111000101010 -
1$
1&
1#
#110000
0&
0#
#111000
b1 '
b1 /
b1 2
b1 ,
b1 .
b101110 )
b110001010101 -
1&
1#
#112000
0&
0#
#113000
b111 '
b111 /
b111 2
1!
1+
b1001111110 ,
b1001111110 .
b101111 )
b100010101011 -
1&
1#
#114000
0&
0#
#115000
b11 '
b11 /
b11 2
b11010000000 ,
b11010000000 .
b110000 )
b101010111 -
0!
0+
0$
1&
1#
#116000
0&
0#
#117000
b1001 '
b1001 /
b1001 2
b111101111100 ,
b111101111100 .
b110001 )
b1010101110 -
1&
1#
#118000
0&
0#
#119000
b101 '
b101 /
b101 2
b110010000101 ,
b110010000101 .
b110010 )
b10101011100 -
1&
1#
#120000
0&
0#
#121000
b1001 '
b1001 /
b1001 2
b101101110111 ,
b101101110111 .
b110011 )
b101010111000 -
1$
1&
1#
#122000
0&
0#
#123000
b101 '
b101 /
b101 2
b10010010011 ,
b10010010011 .
b110100 )
b10101110001 -
0$
1&
1#
#124000
0&
0#
#125000
b111 '
b111 /
b111 2
b101101011010 ,
b101101011010 .
b110101 )
b101011100010 -
1&
1#
#126000
0&
0#
#127000
b101 '
b101 /
b101 2
b10011001001 ,
b10011001001 .
b110110 )
b10111000100 -
1&
1#
#128000
0&
0#
#129000
b1010 '
b1010 /
b1010 2
b101111101111 ,
b101111101111 .
b110111 )
b101110001000 -
1$
1&
1#
#130000
0&
0#
#131000
b110 '
b110 /
b110 2
b10110100011 ,
b10110100011 .
b111000 )
b11100010001 -
1&
1#
#132000
0&
0#
#133000
b100100111010 ,
b100100111010 .
b111001 )
b111000100011 -
1&
1#
#134000
0&
0#
#135000
b1 '
b1 /
b1 2
b1000 ,
b1000 .
b111010 )
b110001000111 -
1&
1#
#136000
0&
0#
#137000
b101 '
b101 /
b101 2
1!
1+
b1001101100 ,
b1001101100 .
b111011 )
b100010001111 -
1&
1#
#138000
0&
0#
#139000
b11010100100 ,
b11010100100 .
b111100 )
b100011111 -
0!
0+
0$
1&
1#
#140000
0&
0#
#141000
b111 '
b111 /
b111 2
b111100110100 ,
b111100110100 .
b111101 )
b1000111110 -
1&
1#
#142000
0&
0#
#143000
b101 '
b101 /
b101 2
b110000010101 ,
b110000010101 .
b111110 )
b10001111100 -
1&
1#
#144000
0&
0#
#145000
b111 '
b111 /
b111 2
b101001010111 ,
b101001010111 .
b111111 )
b100011111000 -
1$
1&
1#
#146000
0&
0#
#147000
b11011010011 ,
b11011010011 .
b1000000 )
b111110001 -
1&
1#
#148000
0&
0#
#149000
b1001 '
b1001 /
b1001 2
b111111011010 ,
b111111011010 .
b1000001 )
b1111100011 -
1&
1#
#150000
0&
0#
#151000
b110 '
b110 /
b110 2
b110111001000 ,
b110111001000 .
b1000010 )
b11111000111 -
0$
1&
1#
#152000
0&
0#
#153000
b111 '
b111 /
b111 2
b100111101100 ,
b100111101100 .
b1000011 )
b111110001110 -
1$
1&
1#
#154000
0&
0#
#155000
b101 '
b101 /
b101 2
b110100101 ,
b110100101 .
b1000100 )
b111100011101 -
0$
1&
1#
#156000
0&
0#
#157000
b100110110 ,
b100110110 .
b1000101 )
b111000111010 -
1$
1&
1#
#158000
0&
0#
#159000
b10 '
b10 /
b10 2
b10001 ,
b10001 .
b1000110 )
b110001110101 -
1&
1#
#160000
0&
0#
#161000
b110 '
b110 /
b110 2
1!
1+
b1001011110 ,
b1001011110 .
b1000111 )
b100011101011 -
1&
1#
#162000
0&
0#
#163000
b100 '
b100 /
b100 2
b11011000000 ,
b11011000000 .
b1001000 )
b111010111 -
0!
0+
0$
1&
1#
#164000
0&
0#
#165000
b1010 '
b1010 /
b1010 2
b111111111100 ,
b111111111100 .
b1001001 )
b1110101110 -
1&
1#
#166000
0&
0#
#167000
b110 '
b110 /
b110 2
b110110000101 ,
b110110000101 .
b1001010 )
b11101011100 -
1&
1#
#168000
0&
0#
#169000
b1000 '
b1000 /
b1000 2
b100101110111 ,
b100101110111 .
b1001011 )
b111010111000 -
1$
1&
1#
#170000
0&
0#
#171000
b100 '
b100 /
b100 2
b10010011 ,
b10010011 .
b1001100 )
b110101110001 -
1&
1#
#172000
0&
0#
#173000
b110 '
b110 /
b110 2
b1101011010 ,
b1101011010 .
b1001101 )
b101011100011 -
1&
1#
#174000
0&
0#
#175000
b100 '
b100 /
b100 2
b10011001000 ,
b10011001000 .
b1001110 )
b10111000111 -
0$
1&
1#
#176000
0&
0#
#177000
b1000 '
b1000 /
b1000 2
b101111101100 ,
b101111101100 .
b1001111 )
b101110001110 -
1$
1&
1#
#178000
0&
0#
#179000
b110 '
b110 /
b110 2
b10110100101 ,
b10110100101 .
b1010000 )
b11100011101 -
0$
1&
1#
#180000
0&
0#
#181000
b100100110110 ,
b100100110110 .
b1010001 )
b111000111010 -
1&
1#
#182000
0&
0#
#183000
b10 '
b10 /
b10 2
b10001 ,
b10001 .
b1010010 )
b110001110100 -
1&
1#
#184000
0&
0#
#185000
b111 '
b111 /
b111 2
1!
1+
b1001011111 ,
b1001011111 .
b1010011 )
b100011101000 -
1&
1#
#186000
0&
0#
#187000
b110 '
b110 /
b110 2
b11011000011 ,
b11011000011 .
b1010100 )
b111010000 -
0!
0+
1&
1#
#188000
0&
0#
#189000
b1011 '
b1011 /
b1011 2
b111111111011 ,
b111111111011 .
b1010101 )
b1110100000 -
1&
1#
#190000
0&
0#
#191000
b111 '
b111 /
b111 2
b110110001011 ,
b110110001011 .
b1010110 )
b11101000000 -
1&
1#
#192000
0&
0#
#193000
b100101101011 ,
b100101101011 .
b1010111 )
b111010000000 -
1&
1#
#194000
0&
0#
#195000
b101 '
b101 /
b101 2
b10101011 ,
b10101011 .
b1011000 )
b110100000000 -
1&
1#
#196000
0&
0#
#197000
b110 '
b110 /
b110 2
b1100101011 ,
b1100101011 .
b1011001 )
b101000000000 -
1&
1#
#198000
0&
0#
#199000
b101 '
b101 /
b101 2
b10000101011 ,
b10000101011 .
b1011010 )
b10000000000 -
1&
1#
#200000
0&
0#
#201000
b110 '
b110 /
b110 2
b101000101011 ,
b101000101011 .
b1011011 )
b100000000000 -
1&
1#
#202000
0&
0#
#203000
b11000101011 ,
b11000101011 .
b1011100 )
b0 -
1&
1#
#204000
0&
0#
#205000
b111 '
b111 /
b111 2
b111000101011 ,
b111000101011 .
b1011101 )
1&
1#
#206000
0&
0#
#207000
b1011110 )
1&
1#
#208000
0&
0#
#209000
b1011111 )
1&
1#
#210000
0&
0#
#211000
b1100000 )
1&
1#
#212000
0&
0#
#213000
b1100001 )
1&
1#
#214000
0&
0#
#215000
b1100010 )
1&
1#
#216000
0&
0#
#217000
b1100011 )
1&
1#
#218000
0&
0#
#219000
b1100100 )
1&
1#
#220000
0&
0#
#221000
b1100101 )
1&
1#
#222000
0&
0#
#223000
b1100110 )
1&
1#
#224000
0&
0#
#225000
b1100111 )
1&
1#
#226000
0&
0#
#227000
b1101000 )
1&
1#
#228000
0&
0#
#229000
b1101001 )
1&
1#
#230000
0&
0#
#231000
b1101010 )
1&
1#
#232000
0&
0#
#233000
b1101011 )
1&
1#
#234000
0&
0#
#235000
b1101100 )
1&
1#
#236000
0&
0#
#237000
b1101101 )
1&
1#
#238000
0&
0#
#239000
b1101110 )
1&
1#
#240000
0&
0#
#241000
b1101111 )
1&
1#
#242000
0&
0#
#243000
b1110000 )
1&
1#
#244000
0&
0#
#245000
b1110001 )
1&
1#
#246000
0&
0#
#247000
b1110010 )
1&
1#
#248000
0&
0#
#249000
b1110011 )
1&
1#
#250000
0&
0#
#251000
b1110100 )
1&
1#
#252000
0&
0#
#253000
b1110101 )
1&
1#
#254000
0&
0#
#255000
b1110110 )
1&
1#
#256000
0&
0#
#257000
b1110111 )
1&
1#
#258000
0&
0#
#259000
b1111000 )
1&
1#
#260000
0&
0#
#261000
b1111001 )
1&
1#
#262000
0&
0#
#263000
b1111010 )
1&
1#
#264000
0&
0#
#265000
b1111011 )
1&
1#
#266000
0&
0#
#267000
b1111100 )
1&
1#
#268000
0&
0#
#269000
b1111101 )
1&
1#
#270000
0&
0#
#271000
b1111110 )
1&
1#
#272000
0&
0#
#273000
b1111111 )
1&
1#
#274000
0&
0#
#275000
b10000000 )
1&
1#
#276000
0&
0#
#277000
b10000001 )
1&
1#
#278000
0&
0#
#279000
b10000010 )
1&
1#
#280000
0&
0#
#281000
b10000011 )
1&
1#
#282000
0&
0#
#283000
b10000100 )
1&
1#
#284000
0&
0#
#285000
b10000101 )
1&
1#
#286000
0&
0#
#287000
b10000110 )
1&
1#
#288000
0&
0#
#289000
b10000111 )
1&
1#
#290000
0&
0#
#291000
b10001000 )
1&
1#
#292000
0&
0#
#293000
b10001001 )
1&
1#
#294000
0&
0#
#295000
b10001010 )
1&
1#
#296000
0&
0#
#297000
b10001011 )
1&
1#
#298000
0&
0#
#299000
b10001100 )
1&
1#
#300000
0&
0#
#301000
b10001101 )
1&
1#
#302000
0&
0#
#303000
b10001110 )
1&
1#
#304000
0&
0#
#305000
b10001111 )
1&
1#
#306000
0&
0#
#307000
b10010000 )
1&
1#
#308000
0&
0#
#309000
b10010001 )
1&
1#
#310000
0&
0#
#311000
b10010010 )
1&
1#
#312000
0&
0#
#313000
b10010011 )
1&
1#
#314000
0&
0#
#315000
b10010100 )
1&
1#
#316000
0&
0#
#317000
b10010101 )
1&
1#
#318000
0&
0#
#319000
b10010110 )
1&
1#
#320000
0&
0#
#321000
b10010111 )
1&
1#
#322000
0&
0#
#323000
b10011000 )
1&
1#
#324000
0&
0#
#325000
b10011001 )
1&
1#
#326000
0&
0#
#327000
b10011010 )
1&
1#
#328000
0&
0#
#329000
b10011011 )
1&
1#
#330000
0&
0#
#331000
b10011100 )
1&
1#
#332000
0&
0#
#333000
b10011101 )
1&
1#
#334000
0&
0#
#335000
b10011110 )
1&
1#
#336000
0&
0#
#337000
b10011111 )
1&
1#
#338000
0&
0#
#339000
b10100000 )
1&
1#
#340000
0&
0#
#341000
b10100001 )
1&
1#
#342000
0&
0#
#343000
b10100010 )
1&
1#
#344000
0&
0#
#345000
b10100011 )
1&
1#
#346000
0&
0#
#347000
b10100100 )
1&
1#
#348000
0&
0#
#349000
b10100101 )
1&
1#
#350000
0&
0#
#351000
b10100110 )
1&
1#
#352000
0&
0#
#353000
b10100111 )
1&
1#
#354000
0&
0#
#355000
b10101000 )
1&
1#
#356000
0&
0#
#357000
b10101001 )
1&
1#
#358000
0&
0#
#359000
b10101010 )
1&
1#
#360000
0&
0#
#361000
b10101011 )
1&
1#
#362000
0&
0#
#363000
b10101100 )
1&
1#
#364000
0&
0#
#365000
b10101101 )
1&
1#
#366000
0&
0#
#367000
b10101110 )
1&
1#
#368000
0&
0#
#369000
b10101111 )
1&
1#
#370000
0&
0#
#371000
b10110000 )
1&
1#
#372000
0&
0#
#373000
b10110001 )
1&
1#
#374000
0&
0#
#375000
b10110010 )
1&
1#
#376000
0&
0#
#377000
b10110011 )
1&
1#
#378000
0&
0#
#379000
b10110100 )
1&
1#
#380000
0&
0#
#381000
b10110101 )
1&
1#
#382000
0&
0#
#383000
b10110110 )
1&
1#
#384000
0&
0#
#385000
b10110111 )
1&
1#
#386000
0&
0#
#387000
b10111000 )
1&
1#
#388000
0&
0#
#389000
b10111001 )
1&
1#
#390000
0&
0#
#391000
b10111010 )
1&
1#
#392000
0&
0#
#393000
b10111011 )
1&
1#
#394000
0&
0#
#395000
b10111100 )
1&
1#
#396000
0&
0#
#397000
b10111101 )
1&
1#
#398000
0&
0#
#399000
b10111110 )
1&
1#
#400000
0&
0#
#401000
b10111111 )
1&
1#
#402000
0&
0#
#403000
b11000000 )
1&
1#
#404000
0&
0#
#405000
b11000001 )
1&
1#
#406000
0&
0#
#407000
b11000010 )
1&
1#
#408000
0&
0#
#409000
b11000011 )
1&
1#
#410000
0&
0#
#411000
b11000100 )
1&
1#
#412000
0&
0#
#413000
b11000101 )
1&
1#
#414000
0&
0#
#415000
b11000110 )
1&
1#
#416000
0&
0#
#417000
b11000111 )
1&
1#
#418000
0&
0#
#419000
b11001000 )
1&
1#
#420000
0&
0#
#421000
b11001001 )
1&
1#
#422000
0&
0#
#423000
b11001010 )
1&
1#
#424000
0&
0#
#425000
b11001011 )
1&
1#
#426000
0&
0#
#427000
b11001100 )
1&
1#
#428000
0&
0#
#429000
b11001101 )
1&
1#
#430000
0&
0#
#431000
b11001110 )
1&
1#
#432000
0&
0#
#433000
b11001111 )
1&
1#
#434000
0&
0#
#435000
b11010000 )
1&
1#
#436000
0&
0#
#437000
b11010001 )
1&
1#
#438000
0&
0#
#439000
b11010010 )
1&
1#
#440000
0&
0#
#441000
b11010011 )
1&
1#
#442000
0&
0#
#443000
b11010100 )
1&
1#
#444000
0&
0#
#445000
b11010101 )
1&
1#
#446000
0&
0#
#447000
b11010110 )
1&
1#
#448000
0&
0#
#449000
b11010111 )
1&
1#
#450000
0&
0#
#451000
b11011000 )
1&
1#
#452000
0&
0#
#453000
b11011001 )
1&
1#
#454000
0&
0#
#455000
b11011010 )
1&
1#
#456000
0&
0#
#457000
b11011011 )
1&
1#
#458000
0&
0#
#459000
b11011100 )
1&
1#
#460000
0&
0#
#461000
b11011101 )
1&
1#
#462000
0&
0#
#463000
b11011110 )
1&
1#
#464000
0&
0#
#465000
b11011111 )
1&
1#
#466000
0&
0#
#467000
b11100000 )
1&
1#
#468000
0&
0#
#469000
b11100001 )
1&
1#
#470000
0&
0#
#471000
b11100010 )
1&
1#
#472000
0&
0#
#473000
b11100011 )
1&
1#
#474000
0&
0#
#475000
b11100100 )
1&
1#
#476000
0&
0#
#477000
b11100101 )
1&
1#
#478000
0&
0#
