sequence_detector/sequence_detector_FSM_101001.v
//////////////////////////////////////////////////////////////////////
// Module Name: sequence detector.v
// Description: sequence_detector_FSM_101001 for 101001
// Designer: Barney Peng
// Date: 03/31/2024
//////////////////////////////////////////////////////////////////////


module sequence_detector_FSM_101001 (
	input i_clk,
	input i_resetn,
	input i_data,



	output o_pattern_found



);

	parameter WIDTH = 6; /* 6  bit counter*/
	//parameter TGT_pattern = 6'b101001; 



	parameter S_initial = 6'd1,
			  S1 = 6'd2, //S1
			  S10 = 6'd3,	//S10
			  S101 = 6'd4,	//S101
			  S1010 = 6'd5, //S1010
			  S10100 = 6'd6; //S10100
			   
 	reg [WIDTH-1 : 0] cur_state, next_state; //current state and next state


	wire clk_gate;		// gated clock
	
	
	assign clk_gate = i_clk;


	// Sequence Detector: initial state is S_initial	
	always @(negedge i_resetn or posedge clk_gate)       // At every positive edge of the clock or negative edge of restn
		begin
			if  (~i_resetn)
				cur_state <= S_initial;		 // If reset is asserted, set the state to S_initial (initial State)
			else
				cur_state <= next_state;         // Else, set the state to the next state
		end// Sequence Detector: initial state is S_initial


	// Sequence Detector
	always @(cur_state or i_data)
	 begin
		case(cur_state)
			S_initial: begin
				if(i_data == 1'b1)
					next_state = S1;
				else
					 next_state = S_initial;
			end
			S1: begin
				if(i_data == 1'b1)
					next_state = S1;
				else
					 next_state = S10;			
			end
			S10: begin
				if(i_data == 1'b1)
					next_state = S101;
				else
					 next_state = S_initial;
			end
			S101: begin
				if(i_data == 1'b1)
					next_state = S1;
				else
					 next_state = S1010;
			end
			S1010: begin
				if(i_data == 1'b1)
					next_state = S101;
				else
					 next_state = S10100;
			end
			S10100: begin
				if(i_data == 1'b1)
					next_state = S1; // detected the pattern
				else
					 next_state = S_initial;
			end
			default: next_state = S_initial;
		endcase
	
	 end	
	
	


	assign o_pattern_found = (cur_state == S10100) && (i_data == 1)? 1:0;


endmodule // sequence_detector_FSM_101001

sequence_detector/sequence_detector_FSM_101001_tb.v
`timescale 1ns / 1ps //set the timescale for the module
//////////////////////////////////////////////////////////////////////
// Module Name: sequence detector_tb.v
// Description: sequence_detector_FSM_101001 for 101001
// Designer: Barney Peng
// Date: 03/30/2024
//////////////////////////////////////////////////////////////////////

module sequence_detector_FSM_101001_tb;

parameter WIDTH = 6; /* xx  bit counter*/


reg i_resetn;
reg i_data;



// restn
initial begin
    i_resetn = 0;
    #20   i_resetn = 1;
    #4000 i_resetn = 1;
    $finish;
end//restn

// input "i_data"
initial begin
    @(posedge i_clk) i_data <= 1;
    @(posedge i_clk) i_data <= 0; 
    @(posedge i_clk) i_data <= 1;
    @(posedge i_clk) i_data <= 0; 
    
    @(posedge i_clk) i_data <= 1;
    @(posedge i_clk) i_data <= 0;  
    @(posedge i_clk) i_data <= 1;
    @(posedge i_clk) i_data <= 0;
    @(posedge i_clk) i_data <= 0;
    @(posedge i_clk) i_data <= 1;  //101001 //but before the restn, thus not detected

    @(posedge i_clk) i_data <= 0;  
    @(posedge i_clk) i_data <= 1;
    @(posedge i_clk) i_data <= 0;
    @(posedge i_clk) i_data <= 0;

    @(posedge i_clk) i_data <= 1;//101001
    @(posedge i_clk) i_data <= 0;
    @(posedge i_clk) i_data <= 1;
    @(posedge i_clk) i_data <= 0;
    @(posedge i_clk) i_data <= 0;
    @(posedge i_clk) i_data <= 1; //101001 


    @(posedge i_clk) i_data <= 0; //overlaping 
    @(posedge i_clk) i_data <= 1;
    @(posedge i_clk) i_data <= 0;
    @(posedge i_clk) i_data <= 0;
    @(posedge i_clk) i_data <= 1; //101001 

    @(posedge i_clk) i_data <= 0;
    @(posedge i_clk) i_data <= 0;
    @(posedge i_clk) i_data <= 0;
    @(posedge i_clk) i_data <= 1;
    @(posedge i_clk) i_data <= 0;

    @(posedge i_clk) i_data <= 1;
    @(posedge i_clk) i_data <= 0;
    @(posedge i_clk) i_data <= 1;
    @(posedge i_clk) i_data <= 0;
    @(posedge i_clk) i_data <= 0;
    @(posedge i_clk) i_data <= 1; //101001 


    @(posedge i_clk) i_data <= 1;
    @(posedge i_clk) i_data <= 0;
    @(posedge i_clk) i_data <= 1;
    @(posedge i_clk) i_data <= 1;
    @(posedge i_clk) i_data <= 1;

    @(posedge i_clk) i_data <= 1;
    @(posedge i_clk) i_data <= 0;
    @(posedge i_clk) i_data <= 1;
    @(posedge i_clk) i_data <= 0;
    @(posedge i_clk) i_data <= 0;
    @(posedge i_clk) i_data <= 1; //101001 


    @(posedge i_clk) i_data <= 1;
    @(posedge i_clk) i_data <= 0;
    @(posedge i_clk) i_data <= 1;
    @(posedge i_clk) i_data <= 1;
    @(posedge i_clk) i_data <= 0;
    @(posedge i_clk) i_data <= 1;
    @(posedge i_clk) i_data <= 0;
    @(posedge i_clk) i_data <= 1;
    @(posedge i_clk) i_data <= 0;
    @(posedge i_clk) i_data <= 0;
    @(posedge i_clk) i_data <= 1; //101001 




end// input "i_data"

// free running clock i_clk
reg i_clk = 0;
always #1 i_clk = !i_clk;



initial begin
    $monitor("At time %t, o_pattern_found = %h (%0d)", $time, o_pattern_found, o_pattern_found);
end



initial begin
    $dumpfile("sequence_detector_FSM_101001.vcd");
    $dumpvars(0,sequence_detector_FSM_101001_tb);
end

sequence_detector_FSM_101001 u_sequence_detector_FSM_101001 (
    .i_clk(i_clk),
    .i_resetn(i_resetn),
    .i_data(i_data),



    .o_pattern_found(o_pattern_found)


);

endmodule

sequence_detector/sequence_detector_FSM_101001.vcd
$date
	Sun Mar 31 15:07:30 2024
$end
$version
	Icarus Verilog
$end
$timescale
	1ps
$end
$scope module sequence_detector_FSM_101001_tb $end
$var wire 1 ! o_pattern_found $end
$var parameter 32 " WIDTH $end
$var reg 1 # i_clk $end
$var reg 1 $ i_data $end
$var reg 1 % i_resetn $end
$scope module u_sequence_detector_FSM_101001 $end
$var wire 1 & clk_gate $end
$var wire 1 # i_clk $end
$var wire 1 $ i_data $end
$var wire 1 % i_resetn $end
$var wire 1 ! o_pattern_found $end
$var parameter 6 ' S1 $end
$var parameter 6 ( S10 $end
$var parameter 6 ) S101 $end
$var parameter 6 * S1010 $end
$var parameter 6 + S10100 $end
$var parameter 6 , S_initial $end
$var parameter 32 - WIDTH $end
$var reg 6 . cur_state [5:0] $end
$var reg 6 / next_state [5:0] $end
$upscope $end
$upscope $end
$enddefinitions $end
$comment Show the parameter values. $end
$dumpall
b110 -
b1 ,
b110 +
b101 *
b100 )
b11 (
b10 '
b110 "
$end
#0
$dumpvars
b1 /
b1 .
0&
0%
x$
0#
0!
$end
#1000
b10 /
1$
1&
1#
#2000
0&
0#
#3000
b1 /
0$
1&
1#
#4000
0&
0#
#5000
b10 /
1$
1&
1#
#6000
0&
0#
#7000
b1 /
0$
1&
1#
#8000
0&
0#
#9000
b10 /
1$
1&
1#
#10000
0&
0#
#11000
b1 /
0$
1&
1#
#12000
0&
0#
#13000
b10 /
1$
1&
1#
#14000
0&
0#
#15000
b1 /
0$
1&
1#
#16000
0&
0#
#17000
1&
1#
#18000
0&
0#
#19000
b10 /
1$
1&
1#
#20000
0&
0#
1%
#21000
b11 /
b10 .
0$
1&
1#
#22000
0&
0#
#23000
b100 /
b11 .
1$
1&
1#
#24000
0&
0#
#25000
b101 /
b100 .
0$
1&
1#
#26000
0&
0#
#27000
b110 /
b101 .
1&
1#
#28000
0&
0#
#29000
1!
b10 /
b110 .
1$
1&
1#
#30000
0&
0#
#31000
0!
b11 /
b10 .
0$
1&
1#
#32000
0&
0#
#33000
b100 /
b11 .
1$
1&
1#
#34000
0&
0#
#35000
b101 /
b100 .
0$
1&
1#
#36000
0&
0#
#37000
b110 /
b101 .
1&
1#
#38000
0&
0#
#39000
1!
b10 /
b110 .
1$
1&
1#
#40000
0&
0#
#41000
0!
b11 /
b10 .
0$
1&
1#
#42000
0&
0#
#43000
b100 /
b11 .
1$
1&
1#
#44000
0&
0#
#45000
b101 /
b100 .
0$
1&
1#
#46000
0&
0#
#47000
b110 /
b101 .
1&
1#
#48000
0&
0#
#49000
1!
b10 /
b110 .
1$
1&
1#
#50000
0&
0#
#51000
0!
b11 /
b10 .
0$
1&
1#
#52000
0&
0#
#53000
b1 /
b11 .
1&
1#
#54000
0&
0#
#55000
b1 .
1&
1#
#56000
0&
0#
#57000
b10 /
1$
1&
1#
#58000
0&
0#
#59000
b11 /
b10 .
0$
1&
1#
#60000
0&
0#
#61000
b100 /
b11 .
1$
1&
1#
#62000
0&
0#
#63000
b101 /
b100 .
0$
1&
1#
#64000
0&
0#
#65000
b100 /
b101 .
1$
1&
1#
#66000
0&
0#
#67000
b101 /
b100 .
0$
1&
1#
#68000
0&
0#
#69000
b110 /
b101 .
1&
1#
#70000
0&
0#
#71000
1!
b10 /
b110 .
1$
1&
1#
#72000
0&
0#
#73000
0!
b10 .
1&
1#
#74000
0&
0#
#75000
b11 /
0$
1&
1#
#76000
0&
0#
#77000
b100 /
b11 .
1$
1&
1#
#78000
0&
0#
#79000
b10 /
b100 .
1&
1#
#80000
0&
0#
#81000
b10 .
1&
1#
#82000
0&
0#
#83000
1&
1#
#84000
0&
0#
#85000
b11 /
0$
1&
1#
#86000
0&
0#
#87000
b100 /
b11 .
1$
1&
1#
#88000
0&
0#
#89000
b101 /
b100 .
0$
1&
1#
#90000
0&
0#
#91000
b110 /
b101 .
1&
1#
#92000
0&
0#
#93000
1!
b10 /
b110 .
1$
1&
1#
#94000
0&
0#
#95000
0!
b10 .
1&
1#
#96000
0&
0#
#97000
b11 /
0$
1&
1#
#98000
0&
0#
#99000
b100 /
b11 .
1$
1&
1#
#100000
0&
0#
#101000
b10 /
b100 .
1&
1#
#102000
0&
0#
#103000
b11 /
b10 .
0$
1&
1#
#104000
0&
0#
#105000
b100 /
b11 .
1$
1&
1#
#106000
0&
0#
#107000
b101 /
b100 .
0$
1&
1#
#108000
0&
0#
#109000
b100 /
b101 .
1$
1&
1#
#110000
0&
0#
#111000
b101 /
b100 .
0$
1&
1#
#112000
0&
0#
#113000
b110 /
b101 .
1&
1#
#114000
0&
0#
#115000
1!
b10 /
b110 .
1$
1&
1#
#116000
0&
0#
#117000
0!
b10 .
1&
1#
