sequence_detector/sequence_detector_ShiftReg_101001_2bErrorTol.v
//////////////////////////////////////////////////////////////////////
// Module Name: sequence detector.v
// Description: sequence_detector_ShiftReg_101001_2bErrorTol for 101001 (over-laping sequence detector)
// Designer: Barney Peng
// Date: 04/21/2024
// References: https://www.youtube.com/watch?v=T_gSYkQe3EU
//////////////////////////////////////////////////////////////////////
	

module sequence_detector_ShiftReg_101001_2bErrorTol (
	input i_clk,
	input i_resetn,
	input i_data,

	output o_pattern_found

);

	parameter WIDTH = 6; /* 6  bit counter*/
	//parameter TGT_pattern = 6'b101001; 

	parameter pattern = 6'b101001;

	reg [WIDTH-1 : 0] seq_reg; //sequence register
	reg [WIDTH-1 : 0] pattern_match_XOR;
	wire [WIDTH-1 : 0] Bit_sum;
	reg pattern_found_p;
	wire clk_gate;		// gated clock
	reg detect_en;

	reg [WIDTH-1 : 0] count_p;
	
	assign clk_gate = i_clk;


	// instantiate adder_6in_1b
	adder_6in_1b adder_inst (
        .i_a(pattern_match_XOR),
        .o_sum(Bit_sum)
    );// adder_6in_1b

	//sequence register
	always @(negedge i_resetn or posedge clk_gate)//sequential logic: use "<=" instead of "="
		begin
			if (~i_resetn)	
				begin
					seq_reg <= 6'h0;
					count_p <= 0;
					pattern_match_XOR[5:0] <= 6'h0;
				end
			else if(count_p >= 6'd63) // Max Value 6 bit can represent
				count_p <= WIDTH; //to prevent disbling detect_en after exceeding max value of count_p
			else
				begin
					seq_reg <= {seq_reg[WIDTH-2 : 0], i_data}; //shifter, shift seq_reg to the left by 1 bit, and put i_data to the right most bit
					count_p <= count_p + 1;
					pattern_match_XOR[5:0] <= (seq_reg ^ 6'b101001);
				end
		end //sequence register

		//detect_en
		always @(negedge i_resetn or posedge clk_gate)
		begin
			if (~i_resetn)
				detect_en <= 0;
			else if (count_p >= WIDTH)
				detect_en <= 1;
			else
				detect_en <= 0;
		end//detect_en



	 
	 /*always @* 
	 	begin
			Bit_sum = pattern_match_XOR[0] + pattern_match_XOR[1] + pattern_match_XOR[2] + pattern_match_XOR[3] + pattern_match_XOR[4] + pattern_match_XOR[5];

	end//Bit_sum//
*/





	//pattern_found_p
	always @(negedge i_resetn or posedge clk_gate) 
		begin
			if (~i_resetn)
			pattern_found_p <= 0;
			else if (detect_en && (Bit_sum <= 2))
			pattern_found_p <= 1;
			else
			pattern_found_p <= 0;
		end//pattern_found_p


	assign o_pattern_found = pattern_found_p;

	
endmodule //sequence_detector_ShiftReg_101001_2bErrorTol



module adder_6in_1b (

	input [WIDTH_in-1:0] i_a,

	output [WIDTH_out-1:0] o_sum

);
	parameter WIDTH_in = 6; 
	parameter WIDTH_out = 6;
	

	reg [WIDTH_out:0] sum_p;
	//reg [WIDTH_out:0] cout;
	//reg [WIDTH_in:0] cin;



always @(*)
begin
	sum_p = i_a[0] + i_a[1] + i_a[2] + i_a[3] + i_a[4] + i_a[5];



end

assign o_sum = sum_p;

endmodule//adder_6in_1b

sequence_detector/sequence_detector_ShiftReg_101001_2bErrorTol_tb.v
`timescale 1ns / 1ps //set the timescale for the module
//////////////////////////////////////////////////////////////////////
// Module Name: sequence detector_tb.v
// Description: sequence_detector_ShiftReg_101001_2bErrorTol for 101001
// Designer: Barney Peng
// Date: 04/21/2024
//////////////////////////////////////////////////////////////////////

module sequence_detector_ShiftReg_101001_2bErrorTol_tb;

parameter WIDTH = 6; /* xx  bit counter*/


reg i_resetn;
reg i_data;



// restn
initial begin
    i_resetn = 0;
    #20   i_resetn = 1;
    #4000 i_resetn = 0;
    $finish;
end//restn

// input "i_data"
initial begin
    i_data = 0;
    #19 i_data <= 0; //restn is #20

    @(posedge i_clk) i_data <= 1; 
    @(posedge i_clk) i_data <= 0; 
    @(posedge i_clk) i_data <= 1; 
    @(posedge i_clk) i_data <= 0;
    @(posedge i_clk) i_data <= 0;
    @(posedge i_clk) i_data <= 1; //101001 
    /*
    @(posedge i_clk) i_data <= 1; 
    @(posedge i_clk) i_data <= 0; 
    @(posedge i_clk) i_data <= 0; //0
    @(posedge i_clk) i_data <= 0; 
    @(posedge i_clk) i_data <= 1; //0
    @(posedge i_clk) i_data <= 0; 
    */
    /*
    @(posedge i_clk) i_data <= 1;
    @(posedge i_clk) i_data <= 1;
    @(posedge i_clk) i_data <= 1;
    @(posedge i_clk) i_data <= 1; //1
    @(posedge i_clk) i_data <= 1; //0
    @(posedge i_clk) i_data <= 1; //1
*/
    @(posedge i_clk) i_data <= 1; //0
    @(posedge i_clk) i_data <= 0; //0
    @(posedge i_clk) i_data <= 1; //1: 101001 with 2 b error
    @(posedge i_clk) i_data <= 0;
    @(posedge i_clk) i_data <= 0;
    @(posedge i_clk) i_data <= 1; //101001 ,overlaping

    @(posedge i_clk) i_data <= 0;
    @(posedge i_clk) i_data <= 0;
    @(posedge i_clk) i_data <= 1; //101001 with 1 b error  ,overlaping
/*
    @(posedge i_clk) i_data <= 1; 
    @(posedge i_clk) i_data <= 1; 
    @(posedge i_clk) i_data <= 1; 
    @(posedge i_clk) i_data <= 1; 
*/
end// input "i_data"

// free running clock i_clk
reg i_clk = 0;
always #1 i_clk = !i_clk;



initial begin
    $monitor("At time %t, o_pattern_found = %h (%0d)", $time, o_pattern_found, o_pattern_found);
end



initial begin
    $dumpfile("sequence_detector_ShiftReg_101001_2bErrorTol.vcd");
    $dumpvars(0,sequence_detector_ShiftReg_101001_2bErrorTol_tb);
end

sequence_detector_ShiftReg_101001_2bErrorTol u_sequence_detector_ShiftReg_101001_2bErrorTol (
    .i_clk(i_clk),
    .i_resetn(i_resetn),
    .i_data(i_data),



    .o_pattern_found(o_pattern_found)


);

endmodule

sequence_detector/sequence_detector_ShiftReg_101001_2bErrorTol.vcd
$date
	Sun Apr 21 23:23:36 2024
$end
$version
	Icarus Verilog
$end
$timescale
	1ps
$end
$scope module sequence_detector_ShiftReg_101001_2bErrorTol_tb $end
$var wire 1 ! o_pattern_found $end
$var parameter 32 " WIDTH $end
$var reg 1 # i_clk $end
$var reg 1 $ i_data $end
$var reg 1 % i_resetn $end
$scope module u_sequence_detector_ShiftReg_101001_2bErrorTol $end
$var wire 1 & clk_gate $end
$var wire 1 # i_clk $end
$var wire 1 $ i_data $end
$var wire 1 % i_resetn $end
$var wire 1 ! o_pattern_found $end
$var wire 6 ' Bit_sum [5:0] $end
$var parameter 32 ( WIDTH $end
$var parameter 6 ) pattern $end
$var reg 6 * count_p [5:0] $end
$var reg 1 + detect_en $end
$var reg 1 , pattern_found_p $end
$var reg 6 - pattern_match_XOR [5:0] $end
$var reg 6 . seq_reg [5:0] $end
$scope module adder_inst $end
$var wire 6 / i_a [5:0] $end
$var wire 6 0 o_sum [5:0] $end
$var parameter 32 1 WIDTH_in $end
$var parameter 32 2 WIDTH_out $end
$var reg 7 3 sum_p [6:0] $end
$upscope $end
$upscope $end
$upscope $end
$enddefinitions $end
$comment Show the parameter values. $end
$dumpall
b110 2
b110 1
b101001 )
b110 (
b110 "
$end
#0
$dumpvars
b0 3
b0 0
b0 /
b0 .
b0 -
0,
0+
b0 *
b0 '
0&
0%
0$
0#
0!
$end
#1000
1&
1#
#2000
0&
0#
#3000
1&
1#
#4000
0&
0#
#5000
1&
1#
#6000
0&
0#
#7000
1&
1#
#8000
0&
0#
#9000
1&
1#
#10000
0&
0#
#11000
1&
1#
#12000
0&
0#
#13000
1&
1#
#14000
0&
0#
#15000
1&
1#
#16000
0&
0#
#17000
1&
1#
#18000
0&
0#
#19000
1$
1&
1#
#20000
0&
0#
1%
#21000
b11 '
b11 0
b11 3
b101001 -
b101001 /
b1 *
b1 .
0$
1&
1#
#22000
0&
0#
#23000
b10 '
b10 0
b10 3
b101000 -
b101000 /
b10 *
b10 .
1$
1&
1#
#24000
0&
0#
#25000
b100 '
b100 0
b100 3
b101011 -
b101011 /
b11 *
b101 .
0$
1&
1#
#26000
0&
0#
#27000
b11 '
b11 0
b11 3
b101100 -
b101100 /
b100 *
b1010 .
1&
1#
#28000
0&
0#
#29000
b100011 -
b100011 /
b101 *
b10100 .
1$
1&
1#
#30000
0&
0#
#31000
b101 '
b101 0
b101 3
b111101 -
b111101 /
b110 *
b101001 .
1&
1#
#32000
0&
0#
#33000
b0 '
b0 0
b0 3
1+
b0 -
b0 /
b111 *
b10011 .
0$
1&
1#
#34000
0&
0#
#35000
b100 '
b100 0
b100 3
b111010 -
b111010 /
b1000 *
b100110 .
1!
1,
1$
1&
1#
#36000
0&
0#
#37000
0!
0,
b1111 -
b1111 /
b1001 *
b1101 .
0$
1&
1#
#38000
0&
0#
#39000
b10 '
b10 0
b10 3
b100100 -
b100100 /
b1010 *
b11010 .
1&
1#
#40000
0&
0#
#41000
b100 '
b100 0
b100 3
1!
1,
b110011 -
b110011 /
b1011 *
b110100 .
1$
1&
1#
#42000
0&
0#
#43000
b11101 -
b11101 /
b1100 *
b101001 .
0!
0,
0$
1&
1#
#44000
0&
0#
#45000
b0 '
b0 0
b0 3
b0 -
b0 /
b1101 *
b10010 .
1&
1#
#46000
0&
0#
#47000
b101 '
b101 0
b101 3
b111011 -
b111011 /
b1110 *
b100100 .
1!
1,
1$
1&
1#
#48000
0&
0#
#49000
b11 '
b11 0
b11 3
0!
0,
b1101 -
b1101 /
b1111 *
b1001 .
1&
1#
#50000
0&
0#
#51000
b1 '
b1 0
b1 3
b100000 -
b100000 /
b10000 *
b10011 .
1&
1#
#52000
0&
0#
#53000
b100 '
b100 0
b100 3
1!
1,
b111010 -
b111010 /
b10001 *
b100111 .
1&
1#
#54000
0&
0#
#55000
b11 '
b11 0
b11 3
b1110 -
b1110 /
b10010 *
b1111 .
0!
0,
1&
1#
#56000
0&
0#
#57000
b100110 -
b100110 /
b10011 *
b11111 .
1&
1#
#58000
0&
0#
#59000
b100 '
b100 0
b100 3
b110110 -
b110110 /
b10100 *
b111111 .
1&
1#
#60000
0&
0#
#61000
b11 '
b11 0
b11 3
b10110 -
b10110 /
b10101 *
1&
1#
#62000
0&
0#
#63000
b10110 *
1&
1#
#64000
0&
0#
#65000
b10111 *
1&
1#
#66000
0&
0#
#67000
b11000 *
1&
1#
#68000
0&
0#
#69000
b11001 *
1&
1#
#70000
0&
0#
#71000
b11010 *
1&
1#
#72000
0&
0#
#73000
b11011 *
1&
1#
#74000
0&
0#
#75000
b11100 *
1&
1#
#76000
0&
0#
#77000
b11101 *
1&
1#
#78000
0&
0#
#79000
b11110 *
1&
1#
#80000
0&
0#
#81000
b11111 *
1&
1#
#82000
0&
0#
#83000
b100000 *
1&
1#
#84000
0&
0#
#85000
b100001 *
1&
1#
#86000
0&
0#
#87000
b100010 *
1&
1#
#88000
0&
0#
#89000
b100011 *
1&
1#
#90000
0&
0#
#91000
b100100 *
1&
1#
#92000
0&
0#
#93000
b100101 *
1&
1#
#94000
0&
0#
#95000
b100110 *
1&
1#
#96000
0&
0#
#97000
b100111 *
1&
1#
#98000
0&
0#
#99000
b101000 *
1&
1#
#100000
0&
0#
#101000
b101001 *
1&
1#
#102000
0&
0#
#103000
b101010 *
1&
1#
#104000
0&
0#
#105000
b101011 *
1&
1#
#106000
0&
0#
#107000
b101100 *
1&
1#
#108000
0&
0#
#109000
b101101 *
1&
1#
#110000
0&
0#
#111000
b101110 *
1&
1#
#112000
0&
0#
#113000
b101111 *
1&
1#
#114000
0&
0#
#115000
b110000 *
1&
1#
#116000
0&
0#
#117000
b110001 *
1&
1#
#118000
0&
0#
#119000
b110010 *
1&
1#
#120000
0&
0#
#121000
b110011 *
1&
1#
#122000
0&
0#
#123000
b110100 *
1&
1#
#124000
0&
0#
#125000
b110101 *
1&
1#
#126000
0&
0#
#127000
b110110 *
1&
1#
#128000
0&
0#
#129000
b110111 *
1&
1#
#130000
0&
0#
#131000
b111000 *
1&
1#
#132000
0&
0#
#133000
b111001 *
1&
1#
#134000
0&
0#
#135000
b111010 *
1&
1#
#136000
0&
0#
#137000
b111011 *
1&
1#
#138000
0&
0#
#139000
b111100 *
1&
1#
#140000
0&
0#
#141000
b111101 *
1&
1#
#142000
0&
0#
#143000
b111110 *
1&
1#
#144000
0&
0#
#145000
b111111 *
1&
1#
#146000
0&
0#
#147000
b110 *
1&
1#
#148000
0&
0#
#149000
b111 *
1&
1#
#150000
0&
0#
#151000
b1000 *
1&
1#
#152000
0&
0#
#153000
b1001 *
1&
1#
#154000
0&
0#
#155000
b1010 *
1&
1#
#156000
0&
0#
#157000
b1011 *
1&
1#
#158000
0&
0#
#159000
b1100 *
1&
1#
#160000
0&
0#
#161000
b1101 *
1&
1#
#162000
0&
0#
#163000
b1110 *
1&
1#
#164000
0&
0#
#165000
b1111 *
1&
1#
#166000
0&
0#
#167000
b10000 *
1&
1#
#168000
0&
0#
#169000
b10001 *
1&
1#
#170000
0&
0#
#171000
b10010 *
1&
1#
#172000
0&
0#
#173000
b10011 *
1&
1#
#174000
0&
0#
#175000
b10100 *
1&
1#
#176000
0&
0#
#177000
b10101 *
1&
1#
#178000
0&
0#
#179000
b10110 *
1&
1#
#180000
0&
0#
#181000
b10111 *
1&
1#
#182000
0&
0#
#183000
b11000 *
1&
1#
#184000
0&
0#
#185000
b11001 *
1&
1#
#186000
0&
0#
#187000
b11010 *
1&
1#
#188000
0&
0#
#189000
b11011 *
1&
1#
#190000
0&
0#
#191000
b11100 *
1&
1#
#192000
0&
0#
#193000
b11101 *
1&
1#
#194000
0&
0#
#195000
b11110 *
1&
1#
#196000
0&
0#
#197000
b11111 *
1&
1#
#198000
0&
0#
#199000
b100000 *
1&
1#
#200000
0&
0#
#201000
b100001 *
1&
1#
#202000
0&
0#
#203000
b100010 *
1&
1#
#204000
0&
0#
#205000
b100011 *
1&
1#
#206000
0&
0#
#207000
b100100 *
1&
1#
#208000
0&
0#
#209000
b100101 *
1&
1#
#210000
0&
0#
#211000
b100110 *
1&
1#
#212000
0&
0#
#213000
b100111 *
1&
1#
#214000
0&
0#
#215000
b101000 *
1&
1#
#216000
0&
0#
#217000
b101001 *
1&
1#
#218000
0&
0#
#219000
b101010 *
1&
1#
#220000
0&
0#
#221000
b101011 *
1&
1#
#222000
0&
0#
#223000
b101100 *
1&
1#
#224000
0&
0#
#225000
b101101 *
1&
1#
#226000
0&
0#
#227000
b101110 *
1&
1#
#228000
0&
0#
#229000
b101111 *
1&
1#
#230000
0&
0#
#231000
b110000 *
1&
1#
#232000
0&
0#
#233000
b110001 *
1&
1#
#234000
0&
0#
#235000
b110010 *
1&
1#
#236000
0&
0#
#237000
b110011 *
1&
1#
#238000
0&
0#
#239000
b110100 *
1&
1#
#240000
0&
0#
#241000
b110101 *
1&
1#
#242000
0&
0#
#243000
b110110 *
1&
1#
#244000
0&
0#
#245000
b110111 *
1&
1#
#246000
0&
0#
#247000
b111000 *
1&
1#
#248000
0&
0#
#249000
b111001 *
1&
1#
#250000
0&
0#
#251000
b111010 *
1&
1#
#252000
0&
0#
#253000
b111011 *
1&
1#
#254000
0&
0#
#255000
b111100 *
1&
1#
#256000
0&
0#
#257000
b111101 *
1&
1#
#258000
0&
0#
#259000
b111110 *
1&
1#
#260000
0&
0#
#261000
b111111 *
1&
1#
#262000
0&
0#
#263000
b110 *
1&
1#
#264000
0&
0#
#265000
b111 *
1&
1#
#266000
0&
0#
#267000
b1000 *
1&
1#
#268000
0&
0#
#269000
b1001 *
1&
1#
#270000
0&
0#
#271000
b1010 *
1&
1#
#272000
0&
0#
#273000
b1011 *
1&
1#
#274000
0&
0#
#275000
b1100 *
1&
1#
#276000
0&
0#
#277000
b1101 *
1&
1#
#278000
0&
0#
#279000
b1110 *
1&
1#
#280000
0&
0#
#281000
b1111 *
1&
1#
#282000
0&
0#
#283000
b10000 *
1&
1#
#284000
0&
0#
#285000
b10001 *
1&
1#
#286000
0&
0#
#287000
b10010 *
1&
1#
#288000
0&
0#
#289000
b10011 *
1&
1#
#290000
0&
0#
#291000
b10100 *
1&
1#
#292000
0&
0#
#293000
b10101 *
1&
1#
#294000
0&
0#
#295000
b10110 *
1&
1#
#296000
0&
0#
#297000
b10111 *
1&
1#
#298000
0&
0#
#299000
b11000 *
1&
1#
#300000
0&
0#
#301000
b11001 *
1&
1#
#302000
0&
0#
#303000
b11010 *
1&
1#
#304000
0&
0#
#305000
b11011 *
1&
1#
#306000
0&
0#
#307000
b11100 *
1&
1#
#308000
0&
0#
#309000
b11101 *
1&
1#
#310000
0&
0#
#311000
b11110 *
1&
1#
#312000
0&
0#
#313000
b11111 *
1&
1#
#314000
0&
0#
#315000
b100000 *
1&
1#
#316000
0&
0#
#317000
b100001 *
1&
1#
#318000
0&
0#
#319000
b100010 *
1&
1#
#320000
0&
0#
#321000
b100011 *
1&
1#
#322000
0&
0#
#323000
b100100 *
1&
1#
#324000
0&
0#
#325000
b100101 *
1&
1#
#326000
0&
0#
#327000
b100110 *
1&
1#
#328000
0&
0#
#329000
b100111 *
1&
1#
#330000
0&
0#
#331000
b101000 *
1&
1#
#332000
0&
0#
#333000
b101001 *
1&
1#
#334000
0&
0#
#335000
b101010 *
1&
1#
#336000
0&
0#
#337000
b101011 *
1&
1#
#338000
0&
0#
#339000
b101100 *
1&
1#
#340000
0&
0#
#341000
b101101 *
1&
1#
#342000
0&
0#
#343000
b101110 *
1&
1#
#344000
0&
0#
#345000
b101111 *
1&
1#
#346000
0&
0#
#347000
b110000 *
1&
1#
#348000
0&
0#
#349000
b110001 *
1&
1#
#350000
0&
0#
#351000
b110010 *
1&
1#
#352000
0&
0#
#353000
b110011 *
1&
1#
#354000
0&
0#
#355000
b110100 *
1&
1#
#356000
0&
0#
#357000
b110101 *
1&
1#
#358000
0&
0#
#359000
b110110 *
1&
1#
#360000
0&
0#
#361000
b110111 *
1&
1#
#362000
0&
0#
#363000
b111000 *
1&
1#
#364000
0&
0#
#365000
b111001 *
1&
1#
#366000
0&
0#
#367000
b111010 *
1&
1#
#368000
0&
0#
#369000
b111011 *
1&
1#
#370000
0&
0#
#371000
b111100 *
1&
1#
#372000
0&
0#
#373000
b111101 *
1&
1#
#374000
0&
0#
#375000
b111110 *
1&
1#
#376000
0&
0#
#377000
b111111 *
1&
1#
#378000
0&
0#
#379000
b110 *
1&
1#
#380000
0&
0#
#381000
b111 *
1&
1#
#382000
0&
0#
#383000
b1000 *
1&
1#
#384000
0&
0#
#385000
b1001 *
1&
1#
#386000
0&
0#
#387000
b1010 *
1&
1#
#388000
0&
0#
#389000
b1011 *
1&
1#
#390000
0&
0#
#391000
b1100 *
1&
1#
#392000
0&
0#
#393000
b1101 *
1&
1#
#394000
0&
0#
#395000
b1110 *
1&
1#
#396000
0&
0#
#397000
b1111 *
1&
1#
#398000
0&
0#
#399000
b10000 *
1&
1#
#400000
0&
0#
#401000
b10001 *
1&
1#
#402000
0&
0#
#403000
b10010 *
1&
1#
#404000
0&
0#
#405000
b10011 *
1&
1#
#406000
0&
0#
#407000
b10100 *
1&
1#
#408000
0&
0#
#409000
b10101 *
1&
1#
#410000
0&
0#
#411000
b10110 *
1&
1#
#412000
0&
0#
#413000
b10111 *
1&
1#
#414000
0&
0#
#415000
b11000 *
1&
1#
#416000
0&
0#
#417000
b11001 *
1&
1#
#418000
0&
0#
#419000
b11010 *
1&
1#
#420000
0&
0#
#421000
b11011 *
1&
1#
#422000
0&
0#
#423000
b11100 *
1&
1#
#424000
0&
0#
#425000
b11101 *
1&
1#
#426000
0&
0#
#427000
b11110 *
1&
1#
#428000
0&
0#
#429000
b11111 *
1&
1#
#430000
0&
0#
#431000
b100000 *
1&
1#
#432000
0&
0#
#433000
b100001 *
1&
1#
#434000
0&
0#
#435000
b100010 *
1&
1#
#436000
0&
0#
#437000
b100011 *
1&
1#
#438000
0&
0#
#439000
b100100 *
1&
1#
#440000
0&
0#
#441000
b100101 *
1&
1#
#442000
0&
0#
#443000
b100110 *
1&
1#
#444000
0&
0#
#445000
b100111 *
1&
1#
#446000
0&
0#
#447000
b101000 *
1&
1#
#448000
0&
0#
#449000
b101001 *
1&
1#
#450000
0&
0#
#451000
b101010 *
1&
1#
#452000
0&
0#
#453000
b101011 *
1&
1#
#454000
0&
0#
#455000
b101100 *
1&
1#
#456000
0&
0#
#457000
b101101 *
1&
1#
#458000
0&
0#
#459000
b101110 *
1&
1#
#460000
0&
0#
#461000
b101111 *
1&
1#
#462000
0&
0#
#463000
b110000 *
1&
1#
#464000
0&
0#
#465000
b110001 *
1&
1#
#466000
0&
0#
#467000
b110010 *
1&
1#
#468000
0&
0#
#469000
b110011 *
1&
1#
#470000
0&
0#
#471000
b110100 *
1&
1#
#472000
0&
0#
#473000
b110101 *
1&
1#
#474000
0&
0#
#475000
b110110 *
1&
1#
#476000
0&
0#
#477000
b110111 *
1&
1#
#478000
0&
0#
#479000
b111000 *
1&
1#
#480000
0&
0#
#481000
b111001 *
1&
1#
#482000
0&
0#
#483000
b111010 *
1&
1#
#484000
0&
0#
#485000
b111011 *
1&
1#
#486000
0&
0#
#487000
b111100 *
1&
1#
#488000
0&
0#
#489000
b111101 *
1&
1#
#490000
0&
0#
#491000
b111110 *
1&
1#
#492000
0&
0#
#493000
b111111 *
1&
1#
#494000
0&
0#
#495000
b110 *
1&
1#
#496000
0&
0#
#497000
b111 *
1&
1#
#498000
0&
0#
#499000
b1000 *
1&
1#
#500000
0&
0#
#501000
b1001 *
1&
1#
#502000
0&
0#
#503000
b1010 *
1&
1#
#504000
0&
0#
#505000
b1011 *
1&
1#
#506000
0&
0#
#507000
b1100 *
1&
1#
#508000
0&
0#
#509000
b1101 *
1&
1#
#510000
0&
0#
#511000
b1110 *
1&
1#
#512000
0&
0#
#513000
b1111 *
1&
1#
#514000
0&
0#
#515000
b10000 *
1&
1#
#516000
0&
0#
#517000
b10001 *
1&
1#
#518000
0&
0#
#519000
b10010 *
1&
1#
#520000
0&
0#
#521000
b10011 *
1&
1#
#522000
0&
0#
#523000
b10100 *
1&
1#
#524000
0&
0#
#525000
b10101 *
1&
1#
#526000
0&
0#
#527000
b10110 *
1&
1#
#528000
0&
0#
#529000
b10111 *
1&
1#
#530000
0&
0#
#531000
b11000 *
1&
1#
#532000
0&
0#
#533000
b11001 *
1&
1#
#534000
0&
0#
#535000
b11010 *
1&
1#
#536000
0&
0#
#537000
b11011 *
1&
1#
#538000
0&
0#
#539000
b11100 *
1&
1#
#540000
0&
0#
#541000
b11101 *
1&
1#
#542000
0&
0#
#543000
b11110 *
1&
1#
#544000
0&
0#
#545000
b11111 *
1&
1#
#546000
0&
0#
#547000
b100000 *
1&
1#
#548000
0&
0#
#549000
b100001 *
1&
1#
#550000
0&
0#
#551000
b100010 *
1&
1#
#552000
0&
0#
#553000
b100011 *
1&
1#
#554000
0&
0#
#555000
b100100 *
1&
1#
#556000
0&
0#
#557000
b100101 *
1&
1#
#558000
0&
0#
#559000
b100110 *
1&
1#
#560000
0&
0#
#561000
b100111 *
1&
1#
#562000
0&
0#
#563000
b101000 *
1&
1#
#564000
0&
0#
#565000
b101001 *
1&
1#
#566000
0&
0#
#567000
b101010 *
1&
1#
#568000
0&
0#
#569000
b101011 *
1&
1#
#570000
0&
0#
#571000
b101100 *
1&
1#
#572000
0&
0#
#573000
b101101 *
1&
1#
#574000
0&
0#
#575000
b101110 *
1&
1#
#576000
0&
0#
#577000
b101111 *
1&
1#
#578000
0&
0#
#579000
b110000 *
1&
1#
#580000
0&
0#
#581000
b110001 *
1&
1#
#582000
0&
0#
#583000
b110010 *
1&
1#
#584000
0&
0#
#585000
b110011 *
1&
1#
#586000
0&
0#
#587000
b110100 *
1&
1#
#588000
0&
0#
#589000
b110101 *
1&
1#
#590000
0&
0#
#591000
b110110 *
1&
1#
#592000
0&
0#
#593000
b110111 *
1&
1#
#594000
0&
0#
#595000
b111000 *
1&
1#
#596000
0&
0#
#597000
b111001 *
1&
1#
#598000
0&
0#
#599000
b111010 *
1&
1#
#600000
0&
0#
#601000
b111011 *
1&
1#
#602000
0&
0#
#603000
b111100 *
1&
1#
#604000
0&
0#
#605000
b111101 *
1&
1#
#606000
0&
0#
#607000
b111110 *
1&
1#
#608000
0&
0#
#609000
b111111 *
1&
1#
#610000
0&
0#
#611000
b110 *
1&
1#
#612000
0&
0#
#613000
b111 *
1&
1#
#614000
0&
0#
#615000
b1000 *
1&
1#
#616000
0&
0#
#617000
b1001 *
1&
1#
#618000
0&
0#
#619000
b1010 *
1&
1#
#620000
0&
0#
#621000
b1011 *
1&
1#
#622000
0&
0#
#623000
b1100 *
1&
1#
#624000
0&
0#
#625000
b1101 *
1&
1#
#626000
0&
0#
#627000
b1110 *
1&
1#
#628000
0&
0#
#629000
b1111 *
1&
1#
#630000
0&
0#
#631000
b10000 *
1&
1#
#632000
0&
0#
#633000
b10001 *
1&
1#
#634000
0&
0#
#635000
b10010 *
1&
1#
#636000
0&
0#
#637000
b10011 *
1&
1#
#638000
0&
0#
#639000
b10100 *
1&
1#
#640000
0&
0#
#641000
b10101 *
1&
1#
#642000
0&
0#
#643000
b10110 *
1&
1#
#644000
0&
0#
#645000
b10111 *
1&
1#
#646000
0&
0#
#647000
b11000 *
1&
1#
#648000
0&
0#
#649000
b11001 *
1&
1#
#650000
0&
0#
#651000
b11010 *
1&
1#
#652000
0&
0#
#653000
b11011 *
1&
1#
#654000
0&
0#
#655000
b11100 *
1&
1#
#656000
0&
0#
#657000
b11101 *
1&
1#
#658000
0&
0#
#659000
b11110 *
1&
1#
#660000
0&
0#
#661000
b11111 *
1&
1#
#662000
0&
0#
#663000
b100000 *
1&
1#
#664000
0&
0#
#665000
b100001 *
1&
1#
#666000
0&
0#
#667000
b100010 *
1&
1#
#668000
0&
0#
#669000
b100011 *
1&
1#
#670000
0&
0#
#671000
b100100 *
1&
1#
#672000
0&
0#
#673000
b100101 *
1&
1#
#674000
0&
0#
#675000
b100110 *
1&
1#
#676000
0&
0#
#677000
b100111 *
1&
1#
#678000
0&
0#
#679000
b101000 *
1&
1#
#680000
0&
0#
#681000
b101001 *
1&
1#
#682000
0&
0#
#683000
b101010 *
1&
1#
#684000
0&
0#
#685000
b101011 *
1&
1#
#686000
0&
0#
#687000
b101100 *
1&
1#
#688000
0&
0#
#689000
b101101 *
1&
1#
#690000
0&
0#
#691000
b101110 *
1&
1#
#692000
0&
0#
#693000
b101111 *
1&
1#
#694000
0&
0#
#695000
b110000 *
1&
1#
#696000
0&
0#
#697000
b110001 *
1&
1#
#698000
0&
0#
#699000
b110010 *
1&
1#
#700000
0&
0#
#701000
b110011 *
1&
1#
#702000
0&
0#
#703000
b110100 *
1&
1#
#704000
0&
0#
#705000
b110101 *
1&
1#
#706000
0&
0#
#707000
b110110 *
1&
1#
#708000
0&
0#
#709000
b110111 *
1&
1#
#710000
0&
0#
#711000
b111000 *
1&
1#
#712000
0&
0#
#713000
b111001 *
1&
1#
#714000
0&
0#
#715000
b111010 *
1&
1#
#716000
0&
0#
#717000
b111011 *
1&
1#
#718000
0&
0#
#719000
b111100 *
1&
1#
#720000
0&
0#
#721000
b111101 *
1&
1#
#722000
0&
0#
#723000
b111110 *
1&
1#
#724000
0&
0#
#725000
b111111 *
1&
1#
#726000
0&
0#
#727000
b110 *
1&
1#
#728000
0&
0#
#729000
b111 *
1&
1#
#730000
0&
0#
#731000
b1000 *
1&
1#
#732000
0&
0#
#733000
b1001 *
1&
1#
#734000
0&
0#
#735000
b1010 *
1&
1#
#736000
0&
0#
#737000
b1011 *
1&
1#
#738000
0&
0#
#739000
b1100 *
1&
1#
#740000
0&
0#
#741000
b1101 *
1&
1#
#742000
0&
0#
#743000
b1110 *
1&
1#
#744000
0&
0#
#745000
b1111 *
1&
1#
#746000
0&
0#
#747000
b10000 *
1&
1#
#748000
0&
0#
#749000
b10001 *
1&
1#
#750000
0&
0#
#751000
b10010 *
1&
1#
#752000
0&
0#
#753000
b10011 *
1&
1#
#754000
0&
0#
#755000
b10100 *
1&
1#
#756000
0&
0#
#757000
b10101 *
1&
1#
#758000
0&
0#
#759000
b10110 *
1&
1#
#760000
0&
0#
#761000
b10111 *
1&
1#
#762000
0&
0#
#763000
b11000 *
1&
1#
#764000
0&
0#
#765000
b11001 *
1&
1#
#766000
0&
0#
#767000
b11010 *
1&
1#
#768000
0&
0#
#769000
b11011 *
1&
1#
#770000
0&
0#
#771000
b11100 *
1&
1#
#772000
0&
0#
#773000
b11101 *
1&
1#
#774000
0&
0#
#775000
b11110 *
1&
1#
#776000
0&
0#
#777000
b11111 *
1&
1#
#778000
0&
0#
#779000
b100000 *
1&
1#
#780000
0&
0#
#781000
b100001 *
1&
1#
#782000
0&
0#
#783000
b100010 *
1&
1#
#784000
0&
0#
#785000
b100011 *
1&
1#
#786000
0&
0#
#787000
b100100 *
1&
1#
#788000
0&
0#
#789000
b100101 *
1&
1#
#790000
0&
0#
#791000
b100110 *
1&
1#
#792000
0&
0#
#793000
b100111 *
1&
1#
#794000
0&
0#
#795000
b101000 *
1&
1#
#796000
0&
0#
#797000
b101001 *
1&
1#
#798000
0&
0#
#799000
b101010 *
1&
1#
#800000
0&
0#
#801000
b101011 *
1&
1#
#802000
0&
0#
#803000
b101100 *
1&
1#
#804000
0&
0#
#805000
b101101 *
1&
1#
#806000
0&
0#
#807000
b101110 *
1&
1#
#808000
0&
0#
#809000
b101111 *
1&
1#
#810000
0&
0#
#811000
b110000 *
1&
1#
#812000
0&
0#
#813000
b110001 *
1&
1#
#814000
0&
0#
#815000
b110010 *
1&
1#
#816000
0&
0#
#817000
b110011 *
1&
1#
#818000
0&
0#
#819000
b110100 *
1&
1#
#820000
0&
0#
#821000
b110101 *
1&
1#
#822000
0&
0#
#823000
b110110 *
1&
1#
#824000
0&
0#
#825000
b110111 *
1&
1#
#826000
0&
0#
#827000
b111000 *
1&
1#
#828000
0&
0#
#829000
b111001 *
1&
1#
#830000
0&
0#
