sequence_detector/sequence_detector_ShiftReg_101001.v
//////////////////////////////////////////////////////////////////////
// Module Name: sequence detector.v
// Description: sequence_detector_ShiftReg_101001 for 101001 (over-laping sequence detector)
// Designer: Barney Peng
// Date: 03/31/2024
// References: https://www.youtube.com/watch?v=T_gSYkQe3EU
//////////////////////////////////////////////////////////////////////
	

module sequence_detector_ShiftReg_101001 (
	input i_clk,
	input i_resetn,
	input i_data,


	output o_pattern_found



);

	parameter WIDTH = 6; /* 6  bit counter*/
	//parameter TGT_pattern = 6'b101001; 



	reg [WIDTH-1 : 0] seq_reg; //sequence register


	wire clk_gate;		// gated clock
	
	
	assign clk_gate = i_clk;


	
	always @(negedge i_resetn or posedge clk_gate)
		begin
			if (~i_resetn)
			seq_reg <= 6'h0;
			else
			seq_reg <= {seq_reg[WIDTH-2 : 0], i_data};

		end


	assign o_pattern_found = (seq_reg ^ 6'b101001) == 0; // "^" is "XOR" operator 
	//this "XOR" method is better than direct comparison, since it is easier with non-zero bit tolerance.



endmodule //sequence_detector_ShiftReg_101001

sequence_detector/sequence_detector_ShiftReg_101001_tb.v
`timescale 1ns / 1ps //set the timescale for the module
//////////////////////////////////////////////////////////////////////
// Module Name: sequence detector_tb.v
// Description: sequence_detector_ShiftReg_101001 for 101001
// Designer: Barney Peng
// Date: 03/30/2024
//////////////////////////////////////////////////////////////////////

module sequence_detector_ShiftReg_101001_tb;

parameter WIDTH = 6; /* xx  bit counter*/


reg i_resetn;
reg i_data;



// restn
initial begin
    i_resetn = 0;
    #20   i_resetn = 1;
    #4000 i_resetn = 1;
    $finish;
end//restn

// input "i_data"
initial begin
    @(posedge i_clk) i_data <= 1;
    @(posedge i_clk) i_data <= 0; 
    @(posedge i_clk) i_data <= 1;
    @(posedge i_clk) i_data <= 0; 
    
    @(posedge i_clk) i_data <= 1;
    @(posedge i_clk) i_data <= 0;  
    @(posedge i_clk) i_data <= 1;
    @(posedge i_clk) i_data <= 0;
    @(posedge i_clk) i_data <= 0;
    @(posedge i_clk) i_data <= 1;  //101001 //but before the restn, thus not detected

    @(posedge i_clk) i_data <= 0;  
    @(posedge i_clk) i_data <= 1;
    @(posedge i_clk) i_data <= 0;
    @(posedge i_clk) i_data <= 0;

    @(posedge i_clk) i_data <= 1;//101001
    @(posedge i_clk) i_data <= 0;
    @(posedge i_clk) i_data <= 1;
    @(posedge i_clk) i_data <= 0;
    @(posedge i_clk) i_data <= 0;
    @(posedge i_clk) i_data <= 1; //101001 


    @(posedge i_clk) i_data <= 0; //overlaping 
    @(posedge i_clk) i_data <= 1;
    @(posedge i_clk) i_data <= 0;
    @(posedge i_clk) i_data <= 0;
    @(posedge i_clk) i_data <= 1; //101001 

    @(posedge i_clk) i_data <= 0;
    @(posedge i_clk) i_data <= 0;
    @(posedge i_clk) i_data <= 0;
    @(posedge i_clk) i_data <= 1;
    @(posedge i_clk) i_data <= 0;

    @(posedge i_clk) i_data <= 1;
    @(posedge i_clk) i_data <= 0;
    @(posedge i_clk) i_data <= 1;
    @(posedge i_clk) i_data <= 0;
    @(posedge i_clk) i_data <= 0;
    @(posedge i_clk) i_data <= 1; //101001 

    @(posedge i_clk) i_data <= 1; 
    @(posedge i_clk) i_data <= 1;
    @(posedge i_clk) i_data <= 0;
    @(posedge i_clk) i_data <= 1;
    @(posedge i_clk) i_data <= 1;
    @(posedge i_clk) i_data <= 1;

    @(posedge i_clk) i_data <= 1;
    @(posedge i_clk) i_data <= 0;
    @(posedge i_clk) i_data <= 1;
    @(posedge i_clk) i_data <= 0;
    @(posedge i_clk) i_data <= 0;
    @(posedge i_clk) i_data <= 1; //101001 


    @(posedge i_clk) i_data <= 1;
    @(posedge i_clk) i_data <= 0;
    @(posedge i_clk) i_data <= 1;
    @(posedge i_clk) i_data <= 1;
    @(posedge i_clk) i_data <= 0;
    
    @(posedge i_clk) i_data <= 1;
    @(posedge i_clk) i_data <= 0;
    @(posedge i_clk) i_data <= 1;
    @(posedge i_clk) i_data <= 0;
    @(posedge i_clk) i_data <= 0;
    @(posedge i_clk) i_data <= 1; //101001 




end// input "i_data"

// free running clock i_clk
reg i_clk = 0;
always #1 i_clk = !i_clk;



initial begin
    $monitor("At time %t, o_pattern_found = %h (%0d)", $time, o_pattern_found, o_pattern_found);
end



initial begin
    $dumpfile("sequence_detector_ShiftReg_101001.vcd");
    $dumpvars(0,sequence_detector_ShiftReg_101001_tb);
end

sequence_detector_ShiftReg_101001 u_sequence_detector_ShiftReg_101001 (
    .i_clk(i_clk),
    .i_resetn(i_resetn),
    .i_data(i_data),



    .o_pattern_found(o_pattern_found)


);

endmodule

sequence_detector/sequence_detector_ShiftReg_101001.vcd
$date
	Sun Apr 07 13:59:13 2024
$end
$version
	Icarus Verilog
$end
$timescale
	1ps
$end
$scope module sequence_detector_ShiftReg_101001_tb $end
$var wire 1 ! o_pattern_found $end
$var parameter 32 " WIDTH $end
$var reg 1 # i_clk $end
$var reg 1 $ i_data $end
$var reg 1 % i_resetn $end
$scope module u_sequence_detector_ShiftReg_101001 $end
$var wire 1 & clk_gate $end
$var wire 1 # i_clk $end
$var wire 1 $ i_data $end
$var wire 1 % i_resetn $end
$var wire 1 ! o_pattern_found $end
$var parameter 32 ' WIDTH $end
$var reg 6 ( seq_reg [5:0] $end
$upscope $end
$upscope $end
$enddefinitions $end
$comment Show the parameter values. $end
$dumpall
b110 '
b110 "
$end
#0
$dumpvars
b0 (
0&
0%
x$
0#
0!
$end
#1000
1$
1&
1#
#2000
0&
0#
#3000
0$
1&
1#
#4000
0&
0#
#5000
1$
1&
1#
#6000
0&
0#
#7000
0$
1&
1#
#8000
0&
0#
#9000
1$
1&
1#
#10000
0&
0#
#11000
0$
1&
1#
#12000
0&
0#
#13000
1$
1&
1#
#14000
0&
0#
#15000
0$
1&
1#
#16000
0&
0#
#17000
1&
1#
#18000
0&
0#
#19000
1$
1&
1#
#20000
0&
0#
1%
#21000
b1 (
0$
1&
1#
#22000
0&
0#
#23000
b10 (
1$
1&
1#
#24000
0&
0#
#25000
b101 (
0$
1&
1#
#26000
0&
0#
#27000
b1010 (
1&
1#
#28000
0&
0#
#29000
b10100 (
1$
1&
1#
#30000
0&
0#
#31000
1!
b101001 (
0$
1&
1#
#32000
0&
0#
#33000
0!
b10010 (
1$
1&
1#
#34000
0&
0#
#35000
b100101 (
0$
1&
1#
#36000
0&
0#
#37000
b1010 (
1&
1#
#38000
0&
0#
#39000
b10100 (
1$
1&
1#
#40000
0&
0#
#41000
1!
b101001 (
0$
1&
1#
#42000
0&
0#
#43000
0!
b10010 (
1$
1&
1#
#44000
0&
0#
#45000
b100101 (
0$
1&
1#
#46000
0&
0#
#47000
b1010 (
1&
1#
#48000
0&
0#
#49000
b10100 (
1$
1&
1#
#50000
0&
0#
#51000
1!
b101001 (
0$
1&
1#
#52000
0&
0#
#53000
0!
b10010 (
1&
1#
#54000
0&
0#
#55000
b100100 (
1&
1#
#56000
0&
0#
#57000
b1000 (
1$
1&
1#
#58000
0&
0#
#59000
b10001 (
0$
1&
1#
#60000
0&
0#
#61000
b100010 (
1$
1&
1#
#62000
0&
0#
#63000
b101 (
0$
1&
1#
#64000
0&
0#
#65000
b1010 (
1$
1&
1#
#66000
0&
0#
#67000
b10101 (
0$
1&
1#
#68000
0&
0#
#69000
b101010 (
1&
1#
#70000
0&
0#
#71000
b10100 (
1$
1&
1#
#72000
0&
0#
#73000
1!
b101001 (
1&
1#
#74000
0&
0#
#75000
0!
b10011 (
1&
1#
#76000
0&
0#
#77000
b100111 (
0$
1&
1#
#78000
0&
0#
#79000
b1110 (
1$
1&
1#
#80000
0&
0#
#81000
b11101 (
1&
1#
#82000
0&
0#
#83000
b111011 (
1&
1#
#84000
0&
0#
#85000
b110111 (
1&
1#
#86000
0&
0#
#87000
b101111 (
0$
1&
1#
#88000
0&
0#
#89000
b11110 (
1$
1&
1#
#90000
0&
0#
#91000
b111101 (
0$
1&
1#
#92000
0&
0#
#93000
b111010 (
1&
1#
#94000
0&
0#
#95000
b110100 (
1$
1&
1#
#96000
0&
0#
#97000
1!
b101001 (
1&
1#
#98000
0&
0#
#99000
0!
b10011 (
0$
1&
1#
#100000
0&
0#
#101000
b100110 (
1$
1&
1#
#102000
0&
0#
#103000
b1101 (
1&
1#
#104000
0&
0#
#105000
b11011 (
0$
1&
1#
#106000
0&
0#
#107000
b110110 (
1$
1&
1#
#108000
0&
0#
#109000
b101101 (
0$
1&
1#
#110000
0&
0#
#111000
b11010 (
1$
1&
1#
#112000
0&
0#
#113000
b110101 (
0$
1&
1#
#114000
0&
0#
#115000
b101010 (
1&
1#
#116000
0&
0#
#117000
b10100 (
1$
1&
1#
#118000
0&
0#
#119000
1!
b101001 (
1&
1#
#120000
0&
0#
#121000
0!
b10011 (
1&
1#
#122000
0&
0#
#123000
b100111 (
1&
1#
#124000
0&
0#
#125000
b1111 (
1&
1#
#126000
0&
0#
#127000
b11111 (
1&
1#
#128000
0&
0#
#129000
b111111 (
1&
1#
